Workbook

Sheet DSSV
A1: STT | B1: CVHT | C1: Giáo vụ | D1: Tài khoản học | E1: Quyết định nhập học | F1: Ngày ban hành | G1: Thời gian đào tạo | H1: Kết thúc | I1: Cảnh báo | J1: MSV | K1: Họ và tên | L1: Họ | M1: Tên | N1: Ngày sinh | O1: Giới tính | P1: Khóa | Q1: Lớp | R1: Ngành | S1: Email | T1: SĐT | U1: MĐV | V1: Tên đơn vị | W1: Lớp | X1: Ngành | Y1: Đơn vị phối hợp (Mã đơn vị) | Z1: Tên đơn vị phối hợp (Theo uni) | AA1: Hình thức học | AB1: Trạng thái T12.2024 | AC1: Trạng thái T05.2025 | AD1: Trạng thái T12/2025 | AE1: Trạng thái dự kiến T05/2026 | AF1: Chi chú | AG1: EMAIL | AH1: SĐT | AI1: XÉT TN 3.2026
A2: =ROW()-1 -> 1 | B2: Trangnt | C2: Sangpn | D2: aicd | E2: 1301/2024/QĐ-ĐHM | F2: 05/04/2024 | G2: =(YEAR(H2)-YEAR(F2))*12 + MONTH(H2)-MONTH(F2) -> 72 | H2: 05/04/2030 | I2: =IF((H2-TODAY())<=0,"Kết thúc ĐT","Thời gian ĐT còn lại "&(H2-TODAY())&" ngày") -> Thời gian ĐT còn lại 1472 ngày | J2: 24C4702H1713 | K2: Cao Diệu Ái | L2: Cao Diệu | M2: Ái | N2: 27/12/1997 | O2: Nữ | P2: 21 | Q2: NDNVT621 | R2: Thương mại điện tử | S2: =VLOOKUP(D2, 'Mail+SDT'!A620:C2735, 2, 0) -> 24C4702H1713@students.hou.edu.vn | T2: =VLOOKUP(D2, 'Mail+SDT'!$A$2:$C$2117, 3, 0) -> 708239435 | U2: DNVT | V2: Trường Trung cấp Vạn Tường | W2: NDNVT621 | X2: Thương mại điện tử | Z2: Trường Trung cấp Vạn Tường | AA2: Trực tuyến | AB2: HT | AC2: HT | AD2: HT | AG2: {=_xludf.XLOOKUP(D2,'Mail+SDT'!A:A,'Mail+SDT'!B:B)} -> #NAME? | AH2: {=_xludf.XLOOKUP(D2,'Mail+SDT'!A:A,'Mail+SDT'!C:C)} -> #NAME? | AI2: {=_xludf.XLOOKUP(D2,'ETK 3.2026'!I:I,'ETK 3.2026'!AF:AF)} -> #NAME?
A3: =ROW()-1 -> 2 | B3: Trangnt | C3: Sangpn | D3: ailtv | E3: 1379/2024/QĐ-ĐHM | F3: 12/04/2024 | G3: =(YEAR(H3)-YEAR(F3))*12 + MONTH(H3)-MONTH(F3) -> 72 | H3: 12/04/2030 | I3: =IF((H3-TODAY())<=0,"Kết thúc ĐT","Thời gian ĐT còn lại "&(H3-TODAY())&" ngày") -> Thời gian ĐT còn lại 1479 ngày | J3: 24C4102H1911 | K3: Lê Thị Vị Ái | L3: Lê Thị Vị | M3: Ái | N3: 20/03/1985 | O3: Nữ | P3: 21 | Q3: ADNVT621 | R3: Kế toán | S3: =VLOOKUP(D3, 'Mail+SDT'!A366:C2481, 2, 0) -> 24C4102H1911@students.hou.edu.vn | T3: =VLOOKUP(D3, 'Mail+SDT'!$A$2:$C$2117, 3, 0) -> 907234003 | U3: DNVT | V3: Trường Trung cấp Vạn Tường | W3: ADNVT621 | X3: Kế toán | Z3: Trường Trung cấp Vạn Tường | AA3: Trực tuyến | AB3: HT | AC3: HT | AD3: HT | AG3: {=_xludf.XLOOKUP(D3,'Mail+SDT'!A:A,'Mail+SDT'!B:B)} -> #NAME? | AH3: {=_xludf.XLOOKUP(D3,'Mail+SDT'!A:A,'Mail+SDT'!C:C)} -> #NAME? | AI3: {=_xludf.XLOOKUP(D3,'ETK 3.2026'!I:I,'ETK 3.2026'!AF:AF)} -> #NAME?
A4: =ROW()-1 -> 3 | B4: Trangnt | C4: Sangpn | D4: anhbv008 | E4: 2983/2024/QĐ-ĐHM | F4: 26/07/2024 | G4: =(YEAR(H4)-YEAR(F4))*12 + MONTH(H4)-MONTH(F4) -> 72 | H4: 26/07/2030 | I4: =IF((H4-TODAY())<=0,"Kết thúc ĐT","Thời gian ĐT còn lại "&(H4-TODAY())&" ngày") -> Thời gian ĐT còn lại 1584 ngày | J4: 24C4702H4394 | K4: Bùi Vân Anh | L4: Bùi Vân | M4: Anh | N4: 18/04/1982 | O4: Nữ | P4: 21 | Q4: NDNVT321 | R4: Thương mại điện tử | S4: =VLOOKUP(D4, 'Mail+SDT'!A601:C2716, 2, 0) -> 24C4702H4394@students.hou.edu.vn | T4: =VLOOKUP(D4, 'Mail+SDT'!$A$2:$C$2117, 3, 0) -> 907180482 | U4: DNVT | V4: Trường Trung cấp Vạn Tường | W4: NDNVT321 | X4: Thương mại điện tử | Z4: Trường Trung cấp Vạn Tường | AA4: Trực tuyến | AB4: HT | AC4: HT | AD4: HT | AG4: {=_xludf.XLOOKUP(D4,'Mail+SDT'!A:A,'Mail+SDT'!B:B)} -> #NAME? | AH4: {=_xludf.XLOOKUP(D4,'Mail+SDT'!A:A,'Mail+SDT'!C:C)} -> #NAME? | AI4: {=_xludf.XLOOKUP(D4,'ETK 3.2026'!I:I,'ETK 3.2026'!AF:AF)} -> #NAME?
A5: =ROW()-1 -> 4 | B5: Trangnt | C5: Sangpn | D5: anhdlt | E5: 1301/2024/QĐ-ĐHM | F5: 05/04/2024 | G5: =(YEAR(H5)-YEAR(F5))*12 + MONTH(H5)-MONTH(F5) -> 72 | H5: 05/04/2030 | I5: =IF((H5-TODAY())<=0,"Kết thúc ĐT","Thời gian ĐT còn lại "&(H5-TODAY())&" ngày") -> Thời gian ĐT còn lại 1472 ngày | J5: 24C4102H1701 | K5: Đỗ Lê Thục Anh | L5: Đỗ Lê Thục | M5: Anh | N5: 02/03/2002 | O5: Nữ | P5: 21 | Q5: ADNVT221 | R5: Kế toán | S5: =VLOOKUP(D5, 'Mail+SDT'!A341:C2456, 2, 0) -> 24C4102H1701@students.hou.edu.vn | T5: =VLOOKUP(D5, 'Mail+SDT'!$A$2:$C$2117, 3, 0) -> 763715789 | U5: DNVT | V5: Trường Trung cấp Vạn Tường | W5: ADNVT221 | X5: Kế toán | Z5: Trường Trung cấp Vạn Tường | AA5: Trực tuyến | AB5: HT | AC5: HT | AD5: CBKL1 | AG5: {=_xludf.XLOOKUP(D5,'Mail+SDT'!A:A,'Mail+SDT'!B:B)} -> #NAME? | AH5: {=_xludf.XLOOKUP(D5,'Mail+SDT'!A:A,'Mail+SDT'!C:C)} -> #NAME? | AI5: {=_xludf.XLOOKUP(D5,'ETK 3.2026'!I:I,'ETK 3.2026'!AF:AF)} -> #NAME?
A6: =ROW()-1 -> 5 | B6: Trangnt | C6: Sangpn | D6: anhkh002 | E6: 2118/2022/QĐ-ĐHM | F6: 30/06/2022 | G6: =(YEAR(H6)-YEAR(F6))*12 + MONTH(H6)-MONTH(F6) -> 72 | H6: 30/06/2028 | I6: =IF((H6-TODAY())<=0,"Kết thúc ĐT","Thời gian ĐT còn lại "&(H6-TODAY())&" ngày") -> Thời gian ĐT còn lại 828 ngày | J6: 22C7102H2780 | K6: Kiều Hà Anh | L6: Kiều Hà | M6: Anh | N6: 03/08/1995 | O6: Nữ | P6: 17 | Q6: FDNVT417 | R6: Ngôn ngữ Anh | S6: =VLOOKUP(D6, 'Mail+SDT'!A288:C2403, 2, 0) -> kieuhaanh.153@gmail.com | T6: =VLOOKUP(D6, 'Mail+SDT'!$A$2:$C$2117, 3, 0) -> 917307873 | U6: DNVT | V6: Trường Trung cấp Vạn Tường | W6: FDNVT417 | X6: Ngôn ngữ Anh | Z6: Trường Trung cấp Vạn Tường | AA6: Trực tuyến | AB6: HT | AC6: HT | AD6: HT | AG6: {=_xludf.XLOOKUP(D6,'Mail+SDT'!A:A,'Mail+SDT'!B:B)} -> #NAME? | AH6: {=_xludf.XLOOKUP(D6,'Mail+SDT'!A:A,'Mail+SDT'!C:C)} -> #NAME? | AI6: {=_xludf.XLOOKUP(D6,'ETK 3.2026'!I:I,'ETK 3.2026'!Z:Z)} -> #NAME?
A7: =ROW()-1 -> 6 | B7: Trangnt | C7: Sangpn | D7: anhlt040 | E7: 839/2024/QĐ-ĐHM | F7: 08/03/2024 | G7: =(YEAR(H7)-YEAR(F7))*12 + MONTH(H7)-MONTH(F7) -> 72 | H7: 08/03/2030 | I7: =IF((H7-TODAY())<=0,"Kết thúc ĐT","Thời gian ĐT còn lại "&(H7-TODAY())&" ngày") -> Thời gian ĐT còn lại 1444 ngày | J7: 24C4502H1026 | K7: Lê Tuấn Anh | L7: Lê Tuấn | M7: Anh | N7: 11/12/1996 | O7: Nam | P7: 21 | Q7: DDNVT621 | R7: Tài chính - Ngân hàng | S7: =VLOOKUP(D7, 'Mail+SDT'!A581:C2696, 2, 0) -> 24C4502H1026@students.hou.edu.vn | T7: =VLOOKUP(D7, 'Mail+SDT'!$A$2:$C$2117, 3, 0) -> 984572573 | U7: DNVT | V7: Trường Trung cấp Vạn Tường | W7: DDNVT621 | X7: Tài chính - Ngân hàng | Z7: Trường Trung cấp Vạn Tường | AA7: Trực tuyến | AB7: HT | AC7: HT | AD7: CBKL1 | AG7: {=_xludf.XLOOKUP(D7,'Mail+SDT'!A:A,'Mail+SDT'!B:B)} -> #NAME? | AH7: {=_xludf.XLOOKUP(D7,'Mail+SDT'!A:A,'Mail+SDT'!C:C)} -> #NAME? | AI7: {=_xludf.XLOOKUP(D7,'ETK 3.2026'!I:I,'ETK 3.2026'!AF:AF)} -> #NAME?
A8: =ROW()-1 -> 7 | B8: Trangnt | C8: Sangpn | D8: anhlvh002 | E8: 839/2024/QĐ-ĐHM | F8: 08/03/2024 | G8: =(YEAR(H8)-YEAR(F8))*12 + MONTH(H8)-MONTH(F8) -> 72 | H8: 08/03/2030 | I8: =IF((H8-TODAY())<=0,"Kết thúc ĐT","Thời gian ĐT còn lại "&(H8-TODAY())&" ngày") -> Thời gian ĐT còn lại 1444 ngày | J8: 24C4202H1008 | K8: Lương Văn Hồng Anh | L8: Lương Văn Hồng | M8: Anh | N8: 12/12/1983 | O8: Nam | P8: 21 | Q8: BDNVT621 | R8: Quản trị kinh doanh | S8: =VLOOKUP(D8, 'Mail+SDT'!A471:C2586, 2, 0) -> 24C4202H1008@students.hou.edu.vn | T8: =VLOOKUP(D8, 'Mail+SDT'!$A$2:$C$2117, 3, 0) -> 938786192 | U8: DNVT | V8: Trường Trung cấp Vạn Tường | W8: BDNVT621 | X8: Quản trị kinh doanh | Z8: Trường Trung cấp Vạn Tường | AA8: Trực tuyến | AB8: HT | AC8: HT | AD8: CBKL1 | AE8: BTH | AF8: Thiếu QT học phí để QR | AG8: {=_xludf.XLOOKUP(D8,'Mail+SDT'!A:A,'Mail+SDT'!B:B)} -> #NAME? | AH8: {=_xludf.XLOOKUP(D8,'Mail+SDT'!A:A,'Mail+SDT'!C:C)} -> #NAME? | AI8: {=_xludf.XLOOKUP(D8,'ETK 3.2026'!I:I,'ETK 3.2026'!AF:AF)} -> #NAME?
A9: =ROW()-1 -> 8 | B9: Trangnt | C9: Sangpn | D9: anhnd036 | E9: 839/2024/QĐ-ĐHM | F9: 08/03/2024 | G9: =(YEAR(H9)-YEAR(F9))*12 + MONTH(H9)-MONTH(F9) -> 72 | H9: 08/03/2030 | I9: =IF((H9-TODAY())<=0,"Kết thúc ĐT","Thời gian ĐT còn lại "&(H9-TODAY())&" ngày") -> Thời gian ĐT còn lại 1444 ngày | J9: 24C4202H1014 | K9: Nguyễn Duy Anh | L9: Nguyễn Duy | M9: Anh | N9: 16/11/1992 | O9: Nam | P9: 21 | Q9: BDNVT621 | R9: Quản trị kinh doanh | S9: =VLOOKUP(D9, 'Mail+SDT'!A432:C2547, 2, 0) -> 24C4202H1014@students.hou.edu.vn | T9: =VLOOKUP(D9, 'Mail+SDT'!$A$2:$C$2117, 3, 0) -> 965702857 | U9: DNVT | V9: Trường Trung cấp Vạn Tường | W9: BDNVT621 | X9: Quản trị kinh doanh | Z9: Trường Trung cấp Vạn Tường | AA9: Trực tuyến | AB9: HT | AC9: HT | AD9: HT | AG9: {=_xludf.XLOOKUP(D9,'Mail+SDT'!A:A,'Mail+SDT'!B:B)} -> #NAME? | AH9: {=_xludf.XLOOKUP(D9,'Mail+SDT'!A:A,'Mail+SDT'!C:C)} -> #NAME? | AI9: {=_xludf.XLOOKUP(D9,'ETK 3.2026'!I:I,'ETK 3.2026'!AF:AF)} -> #NAME?
A10: =ROW()-1 -> 9 | B10: Trangnt | C10: Sangpn | D10: anhnh054 | E10: 2501/2024/QĐ-ĐHM | F10: 28/06/2024 | G10: =(YEAR(H10)-YEAR(F10))*12 + MONTH(H10)-MONTH(F10) -> 72 | H10: 28/06/2030 | I10: =IF((H10-TODAY())<=0,"Kết thúc ĐT","Thời gian ĐT còn lại "&(H10-TODAY())&" ngày") -> Thời gian ĐT còn lại 1556 ngày | J10: 24C4702H3654 | K10: Nguyễn Hoàng Anh | L10: Nguyễn Hoàng | M10: Anh | N10: 15/05/2000 | O10: Nam | P10: 21 | Q10: NDNVT621 | R10: Thương mại điện tử | S10: =VLOOKUP(D10, 'Mail+SDT'!A613:C2728, 2, 0) -> 24C4702H3654@students.hou.edu.vn | T10: =VLOOKUP(D10, 'Mail+SDT'!$A$2:$C$2117, 3, 0) -> 342604553 | U10: DNVT | V10: Trường Trung cấp Vạn Tường | W10: NDNVT621 | X10: Thương mại điện tử | Z10: Trường Trung cấp Vạn Tường | AA10: Trực tuyến | AB10: HT | AC10: HT | AD10: CBKL1 | AE10: BTH | AF10: Thiếu QT học phí để QR | AG10: {=_xludf.XLOOKUP(D10,'Mail+SDT'!A:A,'Mail+SDT'!B:B)} -> #NAME? | AH10: {=_xludf.XLOOKUP(D10,'Mail+SDT'!A:A,'Mail+SDT'!C:C)} -> #NAME? | AI10: {=_xludf.XLOOKUP(D10,'ETK 3.2026'!I:I,'ETK 3.2026'!AF:AF)} -> #NAME?
A11: =ROW()-1 -> 10 | B11: Trangnt | C11: Quynhtnn | D11: anhnm013 | E11: 1676/2024/QĐ-ĐHM | F11: 03/05/2024 | G11: =(YEAR(H11)-YEAR(F11))*12 + MONTH(H11)-MONTH(F11) -> 72 | H11: 03/05/2030 | I11: =IF((H11-TODAY())<=0,"Kết thúc ĐT","Thời gian ĐT còn lại "&(H11-TODAY())&" ngày") -> Thời gian ĐT còn lại 1500 ngày | J11: 24C1004D2525 | K11: Nguyễn Minh Anh | L11: Nguyễn Minh | M11: Anh | N11: 01/08/1998 | O11: Nam | P11: 21 | Q11: CDNP621 | R11: Công nghệ thông tin | S11: =VLOOKUP(D11, 'Mail+SDT'!A176:C2291, 2, 0) -> 24C1004D2525@students.hou.edu.vn | T11: =VLOOKUP(D11, 'Mail+SDT'!$A$2:$C$2117, 3, 0) -> 788354164 | U11: DNP | V11: Trung tâm Đại học Mở Hà Nội tại Đà Nẵng | W11: CDNP621 | X11: Công nghệ thông tin | Z11: Trung tâm Đại học Mở Hà Nội tại Đà Nẵng | AA11: Trực tuyến | AB11: HT | AC11: HT | AD11: HT | AG11: {=_xludf.XLOOKUP(D11,'Mail+SDT'!A:A,'Mail+SDT'!B:B)} -> #NAME? | AH11: {=_xludf.XLOOKUP(D11,'Mail+SDT'!A:A,'Mail+SDT'!C:C)} -> #NAME? | AI11: {=_xludf.XLOOKUP(D11,'ETK 3.2026'!I:I,'ETK 3.2026'!AF:AF)} -> #NAME?
A12: =ROW()-1 -> 11 | B12: Trangnt | C12: Sangpn | D12: anhnt097 | E12: 980/2022/QĐ-ĐHM | F12: 07/04/2022 | G12: =(YEAR(H12)-YEAR(F12))*12 + MONTH(H12)-MONTH(F12) -> 72 | H12: 07/04/2028 | I12: =IF((H12-TODAY())<=0,"Kết thúc ĐT","Thời gian ĐT còn lại "&(H12-TODAY())&" ngày") -> Thời gian ĐT còn lại 744 ngày | J12: 22C1002H1099 | K12: Nguyễn Tuấn Anh | L12: Nguyễn Tuấn | M12: Anh | N12: 18/04/1999 | O12: Nam | P12: 17 | Q12: CDNVT617 | R12: Công nghệ thông tin | S12: =VLOOKUP(D12, 'Mail+SDT'!A255:C2370, 2, 0) -> anhnguyen199a@gmail.com | T12: =VLOOKUP(D12, 'Mail+SDT'!$A$2:$C$2117, 3, 0) -> 339079133 | U12: DNVT | V12: Trường Trung cấp Vạn Tường | W12: CDNVT617 | X12: Công nghệ thông tin | Z12: Trường Trung cấp Vạn Tường | AA12: Trực tuyến | AB12: HT | AC12: HT | AD12: HT | AG12: {=_xludf.XLOOKUP(D12,'Mail+SDT'!A:A,'Mail+SDT'!B:B)} -> #NAME? | AH12: {=_xludf.XLOOKUP(D12,'Mail+SDT'!A:A,'Mail+SDT'!C:C)} -> #NAME? | AI12: {=_xludf.XLOOKUP(D12,'ETK 3.2026'!I:I,'ETK 3.2026'!Z:Z)} -> #NAME?
A13: =ROW()-1 -> 12 | B13: Trangnt | C13: Sangpn | D13: anhnt138 | E13: 1676/2024/QĐ-ĐHM | F13: 03/05/2024 | G13: =(YEAR(H13)-YEAR(F13))*12 + MONTH(H13)-MONTH(F13) -> 72 | H13: 03/05/2030 | I13: =IF((H13-TODAY())<=0,"Kết thúc ĐT","Thời gian ĐT còn lại "&(H13-TODAY())&" ngày") -> Thời gian ĐT còn lại 1500 ngày | J13: 24C4502H2431 | K13: Huỳnh Nguyễn Thanh Ân | L13: Huỳnh Nguyễn Thanh | M13: Ân | N13: 02/07/1989 | O13: Nam | P13: 21 | Q13: DDNVT621 | R13: Tài chính - Ngân hàng | S13: =VLOOKUP(D13, 'Mail+SDT'!A579:C2694, 2, 0) -> 24C4502H2431@students.hou.edu.vn | T13: =VLOOKUP(D13, 'Mail+SDT'!$A$2:$C$2117, 3, 0) -> 981827999 | U13: DNVT | V13: Trường Trung cấp Vạn Tường | W13: DDNVT621 | X13: Tài chính - Ngân hàng | Z13: Trường Trung cấp Vạn Tường | AA13: Trực tuyến | AB13: HT | AC13: HT | AD13: HT | AG13: {=_xludf.XLOOKUP(D13,'Mail+SDT'!A:A,'Mail+SDT'!B:B)} -> #NAME? | AH13: {=_xludf.XLOOKUP(D13,'Mail+SDT'!A:A,'Mail+SDT'!C:C)} -> #NAME? | AI13: {=_xludf.XLOOKUP(D13,'ETK 3.2026'!I:I,'ETK 3.2026'!AF:AF)} -> #NAME?
A14: =ROW()-1 -> 13 | B14: Trangnt | C14: Quynhtnn | D14: anhntk014 | E14: 2118/2022/QĐ-ĐHM | F14: 30/06/2022 | G14: =(YEAR(H14)-YEAR(F14))*12 + MONTH(H14)-MONTH(F14) -> 72 | H14: 30/06/2028 | I14: =IF((H14-TODAY())<=0,"Kết thúc ĐT","Thời gian ĐT còn lại "&(H14-TODAY())&" ngày") -> Thời gian ĐT còn lại 828 ngày | J14: 22C5004D2866 | K14: Nguyễn Thị Kim Anh | L14: Nguyễn Thị Kim | M14: Anh | N14: 11/02/1995 | O14: Nữ | P14: 17 | Q14: HDNP517 | R14: Luật | S14: =VLOOKUP(D14, 'Mail+SDT'!A79:C2194, 2, 0) -> nguyenkimanhkhct48@gmail.com | T14: =VLOOKUP(D14, 'Mail+SDT'!$A$2:$C$2117, 3, 0) -> 385627009 | U14: DNP | V14: Trung tâm Đại học Mở Hà Nội tại Đà Nẵng | W14: HDNP517 | X14: Luật | Z14: Trung tâm Đại học Mở Hà Nội tại Đà Nẵng | AA14: Trực tuyến | AB14: HT | AC14: HT | AD14: HTCT | AG14: {=_xludf.XLOOKUP(D14,'Mail+SDT'!A:A,'Mail+SDT'!B:B)} -> #NAME? | AH14: {=_xludf.XLOOKUP(D14,'Mail+SDT'!A:A,'Mail+SDT'!C:C)} -> #NAME? | AI14: {=_xludf.XLOOKUP(D14,'ETK 3.2026'!I:I,'ETK 3.2026'!AF:AF)} -> #NAME?
A15: =ROW()-1 -> 14 | B15: Trangnt | C15: Sangpn | D15: anhntn041 | E15: 1492/2022/QĐ-ĐHM | F15: 17/05/2022 | G15: =(YEAR(H15)-YEAR(F15))*12 + MONTH(H15)-MONTH(F15) -> 72 | H15: 17/05/2028 | I15: =IF((H15-TODAY())<=0,"Kết thúc ĐT","Thời gian ĐT còn lại "&(H15-TODAY())&" ngày") -> Thời gian ĐT còn lại 784 ngày | J15: 22C7102H1786 | K15: Nguyễn Thị Ngọc Anh | L15: Nguyễn Thị Ngọc | M15: Anh | N15: 09/06/1992 | O15: Nữ | P15: 17 | Q15: FDNVT617 | R15: Ngôn ngữ Anh | S15: =VLOOKUP(D15, 'Mail+SDT'!A312:C2427, 2, 0) -> janienguyen5480@gmail.com | T15: =VLOOKUP(D15, 'Mail+SDT'!$A$2:$C$2117, 3, 0) -> 359828779 | U15: DNVT | V15: Trường Trung cấp Vạn Tường | W15: FDNVT617 | X15: Ngôn ngữ Anh | Z15: Trường Trung cấp Vạn Tường | AA15: Trực tuyến | AB15: HT | AC15: HT | AD15: HT | AG15: {=_xludf.XLOOKUP(D15,'Mail+SDT'!A:A,'Mail+SDT'!B:B)} -> #NAME? | AH15: {=_xludf.XLOOKUP(D15,'Mail+SDT'!A:A,'Mail+SDT'!C:C)} -> #NAME? | AI15: {=_xludf.XLOOKUP(D15,'ETK 3.2026'!I:I,'ETK 3.2026'!Z:Z)} -> #NAME?
A16: =ROW()-1 -> 15 | B16: Trangnt | C16: Sangpn | D16: anhptp009 | E16: 2205/2024/QĐ-ĐHM | F16: 07/06/2024 | G16: =(YEAR(H16)-YEAR(F16))*12 + MONTH(H16)-MONTH(F16) -> 72 | H16: 07/06/2030 | I16: =IF((H16-TODAY())<=0,"Kết thúc ĐT","Thời gian ĐT còn lại "&(H16-TODAY())&" ngày") -> Thời gian ĐT còn lại 1535 ngày | J16: 24C4202H3171 | K16: Phạm Thị Phương Anh | L16: Phạm Thị Phương | M16: Anh | N16: 31/07/2000 | O16: Nữ | P16: 21 | Q16: BDNVT621 | R16: Quản trị kinh doanh | S16: =VLOOKUP(D16, 'Mail+SDT'!A454:C2569, 2, 0) -> 24C4202H3171@students.hou.edu.vn | T16: =VLOOKUP(D16, 'Mail+SDT'!$A$2:$C$2117, 3, 0) -> 797933442 | U16: DNVT | V16: Trường Trung cấp Vạn Tường | W16: BDNVT621 | X16: Quản trị kinh doanh | Z16: Trường Trung cấp Vạn Tường | AA16: Trực tuyến | AB16: HT | AC16: HT | AD16: CBKL1 | AE16: BTH | AF16: Thiếu QT học phí để QR | AG16: {=_xludf.XLOOKUP(D16,'Mail+SDT'!A:A,'Mail+SDT'!B:B)} -> #NAME? | AH16: {=_xludf.XLOOKUP(D16,'Mail+SDT'!A:A,'Mail+SDT'!C:C)} -> #NAME? | AI16: {=_xludf.XLOOKUP(D16,'ETK 3.2026'!I:I,'ETK 3.2026'!AF:AF)} -> #NAME?
A17: =ROW()-1 -> 16 | B17: Trangnt | C17: Sangpn | D17: anhtt041 | E17: 2118/2022/QĐ-ĐHM | F17: 30/06/2022 | G17: =(YEAR(H17)-YEAR(F17))*12 + MONTH(H17)-MONTH(F17) -> 72 | H17: 30/06/2028 | I17: =IF((H17-TODAY())<=0,"Kết thúc ĐT","Thời gian ĐT còn lại "&(H17-TODAY())&" ngày") -> Thời gian ĐT còn lại 828 ngày | J17: 22C5002H2819 | K17: Trần Tuấn Anh | L17: Trần Tuấn | M17: Anh | N17: 25/08/1988 | O17: Nam | P17: 17 | Q17: HDNVT617 | R17: Luật | S17: =VLOOKUP(D17, 'Mail+SDT'!A335:C2450, 2, 0) -> trantuananh25888@gmail.com | T17: =VLOOKUP(D17, 'Mail+SDT'!$A$2:$C$2117, 3, 0) -> 399907906 | U17: DNVT | V17: Trường Trung cấp Vạn Tường | W17: HDNVT617 | X17: Luật | Z17: Trường Trung cấp Vạn Tường | AA17: Trực tuyến | AB17: HT | AC17: HT | AD17: HT | AF17: TN 3.2026 | AG17: {=_xludf.XLOOKUP(D17,'Mail+SDT'!A:A,'Mail+SDT'!B:B)} -> #NAME? | AH17: {=_xludf.XLOOKUP(D17,'Mail+SDT'!A:A,'Mail+SDT'!C:C)} -> #NAME? | AI17: {=_xludf.XLOOKUP(D17,'ETK 3.2026'!I:I,'ETK 3.2026'!AF:AF)} -> #NAME?
A18: =ROW()-1 -> 17 | B18: Trangnt | C18: Sangpn | D18: anhtth007 | E18: 2118/2022/QĐ-ĐHM | F18: 30/06/2022 | G18: =(YEAR(H18)-YEAR(F18))*12 + MONTH(H18)-MONTH(F18) -> 72 | H18: 30/06/2028 | I18: =IF((H18-TODAY())<=0,"Kết thúc ĐT","Thời gian ĐT còn lại "&(H18-TODAY())&" ngày") -> Thời gian ĐT còn lại 828 ngày | J18: 22C7102H2808 | K18: Trần Thị Hồng Anh | L18: Trần Thị Hồng | M18: Anh | N18: 11/09/1989 | O18: Nữ | P18: 17 | Q18: FDNVT617 | R18: Ngôn ngữ Anh | S18: =VLOOKUP(D18, 'Mail+SDT'!A299:C2414, 2, 0) -> honganh1109@gmail.com | T18: =VLOOKUP(D18, 'Mail+SDT'!$A$2:$C$2117, 3, 0) -> 939499577 | U18: DNVT | V18: Trường Trung cấp Vạn Tường | W18: FDNVT617 | X18: Ngôn ngữ Anh | Z18: Trường Trung cấp Vạn Tường | AA18: Trực tuyến | AB18: HT | AC18: HT | AD18: HT | AG18: {=_xludf.XLOOKUP(D18,'Mail+SDT'!A:A,'Mail+SDT'!B:B)} -> #NAME? | AH18: {=_xludf.XLOOKUP(D18,'Mail+SDT'!A:A,'Mail+SDT'!C:C)} -> #NAME? | AI18: {=_xludf.XLOOKUP(D18,'ETK 3.2026'!I:I,'ETK 3.2026'!AF:AF)} -> #NAME?
A19: =ROW()-1 -> 18 | B19: Trangnt | C19: Sangpn | D19: anhttn012 | E19: 2118/2022/QĐ-ĐHM | F19: 30/06/2022 | G19: =(YEAR(H19)-YEAR(F19))*12 + MONTH(H19)-MONTH(F19) -> 72 | H19: 30/06/2028 | I19: =IF((H19-TODAY())<=0,"Kết thúc ĐT","Thời gian ĐT còn lại "&(H19-TODAY())&" ngày") -> Thời gian ĐT còn lại 828 ngày | J19: 22C4502H2862 | K19: Trương Thị Ngọc Anh | L19: Trương Thị Ngọc | M19: Anh | N19: 30/08/1995 | O19: Nữ | P19: 17 | Q19: DDNVT617 | R19: Tài chính - Ngân hàng | S19: =VLOOKUP(D19, 'Mail+SDT'!A264:C2379, 2, 0) -> ngocanh102109@gmail.com | T19: =VLOOKUP(D19, 'Mail+SDT'!$A$2:$C$2117, 3, 0) -> 968310395 | U19: DNVT | V19: Trường Trung cấp Vạn Tường | W19: DDNVT617 | X19: Tài chính - Ngân hàng | Z19: Trường Trung cấp Vạn Tường | AA19: Trực tuyến | AB19: HT | AC19: HT | AD19: HT | AF19: TN 3.2026 | AG19: {=_xludf.XLOOKUP(D19,'Mail+SDT'!A:A,'Mail+SDT'!B:B)} -> #NAME? | AH19: {=_xludf.XLOOKUP(D19,'Mail+SDT'!A:A,'Mail+SDT'!C:C)} -> #NAME? | AI19: {=_xludf.XLOOKUP(D19,'ETK 3.2026'!I:I,'ETK 3.2026'!AF:AF)} -> #NAME?
A20: =ROW()-1 -> 19 | B20: Trangnt | C20: Sangpn | D20: anhttp012 | E20: 1301/2024/QĐ-ĐHM | F20: 05/04/2024 | G20: =(YEAR(H20)-YEAR(F20))*12 + MONTH(H20)-MONTH(F20) -> 72 | H20: 05/04/2030 | I20: =IF((H20-TODAY())<=0,"Kết thúc ĐT","Thời gian ĐT còn lại "&(H20-TODAY())&" ngày") -> Thời gian ĐT còn lại 1472 ngày | J20: 24C4702H1717 | K20: Trần Thị Phương Anh | L20: Trần Thị Phương | M20: Anh | N20: 10/09/1996 | O20: Nữ | P20: 21 | Q20: NDNVT621 | R20: Thương mại điện tử | S20: =VLOOKUP(D20, 'Mail+SDT'!A616:C2731, 2, 0) -> 24C4702H1717@students.hou.edu.vn | T20: =VLOOKUP(D20, 'Mail+SDT'!$A$2:$C$2117, 3, 0) -> 7022119496 | U20: DNVT | V20: Trường Trung cấp Vạn Tường | W20: NDNVT621 | X20: Thương mại điện tử | Z20: Trường Trung cấp Vạn Tường | AA20: Trực tuyến | AB20: HT | AC20: HT | AD20: CBKL1 | AG20: {=_xludf.XLOOKUP(D20,'Mail+SDT'!A:A,'Mail+SDT'!B:B)} -> #NAME? | AH20: {=_xludf.XLOOKUP(D20,'Mail+SDT'!A:A,'Mail+SDT'!C:C)} -> #NAME? | AI20: {=_xludf.XLOOKUP(D20,'ETK 3.2026'!I:I,'ETK 3.2026'!AF:AF)} -> #NAME?
A21: =ROW()-1 -> 20 | B21: Trangnt | C21: Sangpn | D21: anhttt011 | E21: 1301/2024/QĐ-ĐHM | F21: 05/04/2024 | G21: =(YEAR(H21)-YEAR(F21))*12 + MONTH(H21)-MONTH(F21) -> 72 | H21: 05/04/2030 | I21: =IF((H21-TODAY())<=0,"Kết thúc ĐT","Thời gian ĐT còn lại "&(H21-TODAY())&" ngày") -> Thời gian ĐT còn lại 1472 ngày | J21: 24C4202H1685 | K21: Trần Thị Tú Anh | L21: Trần Thị Tú | M21: Anh | N21: 15/07/1990 | O21: Nữ | P21: 21 | Q21: BDNVT421 | R21: Quản trị kinh doanh | S21: =VLOOKUP(D21, 'Mail+SDT'!A412:C2527, 2, 0) -> 24C4202H1685@students.hou.edu.vn | T21: =VLOOKUP(D21, 'Mail+SDT'!$A$2:$C$2117, 3, 0) -> 973689642 | U21: DNVT | V21: Trường Trung cấp Vạn Tường | W21: BDNVT421 | X21: Quản trị kinh doanh | Z21: Trường Trung cấp Vạn Tường | AA21: Trực tuyến | AB21: HT | AC21: HT | AD21: HT | AG21: {=_xludf.XLOOKUP(D21,'Mail+SDT'!A:A,'Mail+SDT'!B:B)} -> #NAME? | AH21: {=_xludf.XLOOKUP(D21,'Mail+SDT'!A:A,'Mail+SDT'!C:C)} -> #NAME? | AI21: {=_xludf.XLOOKUP(D21,'ETK 3.2026'!I:I,'ETK 3.2026'!AF:AF)} -> #NAME?
A22: =ROW()-1 -> 21 | B22: Trangnt | C22: Sangpn | D22: anhttv014 | E22: 1492/2022/QĐ-ĐHM | F22: 17/05/2022 | G22: =(YEAR(H22)-YEAR(F22))*12 + MONTH(H22)-MONTH(F22) -> 72 | H22: 17/05/2028 | I22: =IF((H22-TODAY())<=0,"Kết thúc ĐT","Thời gian ĐT còn lại "&(H22-TODAY())&" ngày") -> Thời gian ĐT còn lại 784 ngày | J22: 22C7102H1806 | K22: Trịnh Thị Vân Anh | L22: Trịnh Thị Vân | M22: Anh | N22: 15/05/1997 | O22: Nữ | P22: 17 | Q22: FDNVT617 | R22: Ngôn ngữ Anh | S22: =VLOOKUP(D22, 'Mail+SDT'!A311:C2426, 2, 0) -> trang051597@gmail.com | T22: =VLOOKUP(D22, 'Mail+SDT'!$A$2:$C$2117, 3, 0) -> 964067039 | U22: DNVT | V22: Trường Trung cấp Vạn Tường | W22: FDNVT617 | X22: Ngôn ngữ Anh | Z22: Trường Trung cấp Vạn Tường | AA22: Trực tuyến | AB22: HT | AC22: HT | AD22: HT | AF22: TN 3.2026 | AG22: {=_xludf.XLOOKUP(D22,'Mail+SDT'!A:A,'Mail+SDT'!B:B)} -> #NAME? | AH22: {=_xludf.XLOOKUP(D22,'Mail+SDT'!A:A,'Mail+SDT'!C:C)} -> #NAME? | AI22: {=_xludf.XLOOKUP(D22,'ETK 3.2026'!I:I,'ETK 3.2026'!AF:AF)} -> #NAME?
A23: =ROW()-1 -> 22 | B23: Trangnt | C23: Quynhtnn | D23: anhvtn006 | E23: 593/2022/QĐ-ĐHM | F23: 04/03/2022 | G23: =(YEAR(H23)-YEAR(F23))*12 + MONTH(H23)-MONTH(F23) -> 72 | H23: 04/03/2028 | I23: =IF((H23-TODAY())<=0,"Kết thúc ĐT","Thời gian ĐT còn lại "&(H23-TODAY())&" ngày") -> Thời gian ĐT còn lại 710 ngày | J23: 22C4104D0243 | K23: Võ Thị Ngọc Anh | L23: Võ Thị Ngọc | M23: Anh | N23: 19/12/1995 | O23: Nữ | P23: 17 | Q23: ADNP417 | R23: Kế toán | S23: =VLOOKUP(D23, 'Mail+SDT'!A22:C2137, 2, 0) -> ngocanh.vo1912@gmail.com | T23: =VLOOKUP(D23, 'Mail+SDT'!$A$2:$C$2117, 3, 0) -> 973700618 | U23: DNP | V23: Trung tâm Đại học Mở Hà Nội tại Đà Nẵng | W23: ADNP417 | X23: Kế toán | Z23: Trung tâm Đại học Mở Hà Nội tại Đà Nẵng | AA23: Trực tuyến | AB23: HT | AC23: HT | AD23: HT | AG23: {=_xludf.XLOOKUP(D23,'Mail+SDT'!A:A,'Mail+SDT'!B:B)} -> #NAME? | AH23: {=_xludf.XLOOKUP(D23,'Mail+SDT'!A:A,'Mail+SDT'!C:C)} -> #NAME? | AI23: {=_xludf.XLOOKUP(D23,'ETK 3.2026'!I:I,'ETK 3.2026'!Z:Z)} -> #NAME?
A24: =ROW()-1 -> 23 | B24: Trangnt | C24: Sangpn | D24: anhvv009 | E24: 2118/2022/QĐ-ĐHM | F24: 30/06/2022 | G24: =(YEAR(H24)-YEAR(F24))*12 + MONTH(H24)-MONTH(F24) -> 72 | H24: 30/06/2028 | I24: =IF((H24-TODAY())<=0,"Kết thúc ĐT","Thời gian ĐT còn lại "&(H24-TODAY())&" ngày") -> Thời gian ĐT còn lại 828 ngày | J24: 22C5002H2830 | K24: Võ Vân Anh | L24: Võ Vân | M24: Anh | N24: 08/10/2003 | O24: Nữ | P24: 17 | Q24: HDNVT617 | R24: Luật | S24: =VLOOKUP(D24, 'Mail+SDT'!A337:C2452, 2, 0) -> vananh0810tb@gmail.com | T24: =VLOOKUP(D24, 'Mail+SDT'!$A$2:$C$2117, 3, 0) -> 862781857 | U24: DNVT | V24: Trường Trung cấp Vạn Tường | W24: HDNVT617 | X24: Luật | Z24: Trường Trung cấp Vạn Tường | AA24: Trực tuyến | AB24: HT | AC24: HT | AD24: HT | AG24: {=_xludf.XLOOKUP(D24,'Mail+SDT'!A:A,'Mail+SDT'!B:B)} -> #NAME? | AH24: {=_xludf.XLOOKUP(D24,'Mail+SDT'!A:A,'Mail+SDT'!C:C)} -> #NAME? | AI24: {=_xludf.XLOOKUP(D24,'ETK 3.2026'!I:I,'ETK 3.2026'!Z:Z)} -> #NAME?
A25: =ROW()-1 -> 24 | B25: Trangnt | C25: Sangpn | D25: anhvv012 | E25: 2501/2024/QĐ-ĐHM | F25: 28/06/2024 | G25: =(YEAR(H25)-YEAR(F25))*12 + MONTH(H25)-MONTH(F25) -> 72 | H25: 28/06/2030 | I25: =IF((H25-TODAY())<=0,"Kết thúc ĐT","Thời gian ĐT còn lại "&(H25-TODAY())&" ngày") -> Thời gian ĐT còn lại 1556 ngày | J25: 24C4202H3565 | K25: Võ Vân Anh | L25: Võ Vân | M25: Anh | N25: 05/05/1998 | O25: Nữ | P25: 21 | Q25: BDNVT621 | R25: Quản trị kinh doanh | S25: =VLOOKUP(D25, 'Mail+SDT'!A451:C2566, 2, 0) -> 24C4202H3565@students.hou.edu.vn | T25: =VLOOKUP(D25, 'Mail+SDT'!$A$2:$C$2117, 3, 0) -> 985884513 | U25: DNVT | V25: Trường Trung cấp Vạn Tường | W25: BDNVT621 | X25: Quản trị kinh doanh | Z25: Trường Trung cấp Vạn Tường | AA25: Trực tuyến | AB25: HT | AC25: HT | AD25: CBKL1 | AE25: BTH | AF25: Thiếu QT học phí để QR | AG25: {=_xludf.XLOOKUP(D25,'Mail+SDT'!A:A,'Mail+SDT'!B:B)} -> #NAME? | AH25: {=_xludf.XLOOKUP(D25,'Mail+SDT'!A:A,'Mail+SDT'!C:C)} -> #NAME? | AI25: {=_xludf.XLOOKUP(D25,'ETK 3.2026'!I:I,'ETK 3.2026'!AF:AF)} -> #NAME?
A26: =ROW()-1 -> 25 | B26: Trangnt | C26: Quynhtnn | D26: anntt017 | E26: 2983/2024/QĐ-ĐHM | F26: 26/07/2024 | G26: =(YEAR(H26)-YEAR(F26))*12 + MONTH(H26)-MONTH(F26) -> 72 | H26: 26/07/2030 | I26: =IF((H26-TODAY())<=0,"Kết thúc ĐT","Thời gian ĐT còn lại "&(H26-TODAY())&" ngày") -> Thời gian ĐT còn lại 1584 ngày | J26: 24C1004D4405 | K26: Nguyễn Thiên Thuận An | L26: Nguyễn Thiên Thuận | M26: An | N26: 08/05/1996 | O26: Nữ | P26: 21 | Q26: CDNP321 | R26: Công nghệ thông tin | S26: =VLOOKUP(D26, 'Mail+SDT'!A163:C2278, 2, 0) -> 24C1004D4405@students.hou.edu.vn | T26: =VLOOKUP(D26, 'Mail+SDT'!$A$2:$C$2117, 3, 0) -> 338740898 | U26: DNP | V26: Trung tâm Đại học Mở Hà Nội tại Đà Nẵng | W26: CDNP321 | X26: Công nghệ thông tin | Z26: Trung tâm Đại học Mở Hà Nội tại Đà Nẵng | AA26: Trực tuyến | AB26: HT | AC26: HT | AD26: CBKL1 | AG26: {=_xludf.XLOOKUP(D26,'Mail+SDT'!A:A,'Mail+SDT'!B:B)} -> #NAME? | AH26: {=_xludf.XLOOKUP(D26,'Mail+SDT'!A:A,'Mail+SDT'!C:C)} -> #NAME? | AI26: {=_xludf.XLOOKUP(D26,'ETK 3.2026'!I:I,'ETK 3.2026'!AF:AF)} -> #NAME?
A27: =ROW()-1 -> 26 | B27: Trangnt | C27: Sangpn | D27: annv014 | E27: 2205/2024/QĐ-ĐHM | F27: 07/06/2024 | G27: =(YEAR(H27)-YEAR(F27))*12 + MONTH(H27)-MONTH(F27) -> 72 | H27: 07/06/2030 | I27: =IF((H27-TODAY())<=0,"Kết thúc ĐT","Thời gian ĐT còn lại "&(H27-TODAY())&" ngày") -> Thời gian ĐT còn lại 1535 ngày | J27: 24C4502H3261 | K27: Nguyễn Văn An | L27: Nguyễn Văn | M27: An | N27: 25/03/1993 | O27: Nam | P27: 21 | Q27: DDNVT621 | R27: Tài chính - Ngân hàng | S27: =VLOOKUP(D27, 'Mail+SDT'!A593:C2708, 2, 0) -> 24C4502H3261@students.hou.edu.vn | T27: =VLOOKUP(D27, 'Mail+SDT'!$A$2:$C$2117, 3, 0) -> 978935845 | U27: DNVT | V27: Trường Trung cấp Vạn Tường | W27: DDNVT621 | X27: Tài chính - Ngân hàng | Z27: Trường Trung cấp Vạn Tường | AA27: Trực tuyến | AB27: HT | AC27: HT | AD27: HT | AG27: {=_xludf.XLOOKUP(D27,'Mail+SDT'!A:A,'Mail+SDT'!B:B)} -> #NAME? | AH27: {=_xludf.XLOOKUP(D27,'Mail+SDT'!A:A,'Mail+SDT'!C:C)} -> #NAME? | AI27: {=_xludf.XLOOKUP(D27,'ETK 3.2026'!I:I,'ETK 3.2026'!AF:AF)} -> #NAME?
A28: =ROW()-1 -> 27 | B28: Trangnt | C28: Sangpn | D28: anptv | E28: 1676/2024/QĐ-ĐHM | F28: 03/05/2024 | G28: =(YEAR(H28)-YEAR(F28))*12 + MONTH(H28)-MONTH(F28) -> 72 | H28: 03/05/2030 | I28: =IF((H28-TODAY())<=0,"Kết thúc ĐT","Thời gian ĐT còn lại "&(H28-TODAY())&" ngày") -> Thời gian ĐT còn lại 1500 ngày | J28: 24C4202H2427 | K28: Phan Thị Vĩnh An | L28: Phan Thị Vĩnh | M28: An | N28: 13/07/2005 | O28: Nữ | P28: 21 | Q28: BDNVT621 | R28: Quản trị kinh doanh | S28: =VLOOKUP(D28, 'Mail+SDT'!A466:C2581, 2, 0) -> 24C4202H2427@students.hou.edu.vn | T28: =VLOOKUP(D28, 'Mail+SDT'!$A$2:$C$2117, 3, 0) -> 828409986 | U28: DNVT | V28: Trường Trung cấp Vạn Tường | W28: BDNVT621 | X28: Quản trị kinh doanh | Z28: Trường Trung cấp Vạn Tường | AA28: Trực tuyến | AB28: HT | AC28: HT | AD28: HT | AG28: {=_xludf.XLOOKUP(D28,'Mail+SDT'!A:A,'Mail+SDT'!B:B)} -> #NAME? | AH28: {=_xludf.XLOOKUP(D28,'Mail+SDT'!A:A,'Mail+SDT'!C:C)} -> #NAME? | AI28: {=_xludf.XLOOKUP(D28,'ETK 3.2026'!I:I,'ETK 3.2026'!AF:AF)} -> #NAME?
A29: =ROW()-1 -> 28 | B29: Trangnt | C29: Quynhtnn | D29: antn002 | E29: 2118/2022/QĐ-ĐHM | F29: 30/06/2022 | G29: =(YEAR(H29)-YEAR(F29))*12 + MONTH(H29)-MONTH(F29) -> 72 | H29: 30/06/2028 | I29: =IF((H29-TODAY())<=0,"Kết thúc ĐT","Thời gian ĐT còn lại "&(H29-TODAY())&" ngày") -> Thời gian ĐT còn lại 828 ngày | J29: 22C5104D2873 | K29: Trần Ngọc An | L29: Trần Ngọc | M29: An | N29: 12/06/1987 | O29: Nam | P29: 17 | Q29: EDNP617 | R29: Luật kinh tế | S29: =VLOOKUP(D29, 'Mail+SDT'!A63:C2178, 2, 0) -> ngocanqn87@gmail.com | T29: =VLOOKUP(D29, 'Mail+SDT'!$A$2:$C$2117, 3, 0) -> 905295983 | U29: DNP | V29: Trung tâm Đại học Mở Hà Nội tại Đà Nẵng | W29: EDNP617 | X29: Luật kinh tế | Z29: Trung tâm Đại học Mở Hà Nội tại Đà Nẵng | AA29: Trực tuyến | AB29: HT | AC29: HT | AD29: HT | AF29: TN 3.2026 | AG29: {=_xludf.XLOOKUP(D29,'Mail+SDT'!A:A,'Mail+SDT'!B:B)} -> #NAME? | AH29: {=_xludf.XLOOKUP(D29,'Mail+SDT'!A:A,'Mail+SDT'!C:C)} -> #NAME? | AI29: {=_xludf.XLOOKUP(D29,'ETK 3.2026'!I:I,'ETK 3.2026'!AF:AF)} -> #NAME?
A30: =ROW()-1 -> 29 | B30: Trangnt | C30: Quynhtnn | D30: baobtg | E30: 4768/2023/QĐ-ĐHM | F30: 15/12/2023 | G30: =(YEAR(H30)-YEAR(F30))*12 + MONTH(H30)-MONTH(F30) -> 72 | H30: 15/12/2029 | I30: =IF((H30-TODAY())<=0,"Kết thúc ĐT","Thời gian ĐT còn lại "&(H30-TODAY())&" ngày") -> Thời gian ĐT còn lại 1361 ngày | J30: 23C1004D5964 | K30: Bùi Trà Gia Bảo | L30: Bùi Trà Gia | M30: Bảo | N30: 20/07/1998 | O30: Nam | P30: 21 | Q30: CDNP621 | R30: Công nghệ thông tin | S30: =VLOOKUP(D30, 'Mail+SDT'!A179:C2294, 2, 0) -> 23C1004D5964@students.hou.edu.vn | T30: =VLOOKUP(D30, 'Mail+SDT'!$A$2:$C$2117, 3, 0) -> 855454911 | U30: DNP | V30: Trung tâm Đại học Mở Hà Nội tại Đà Nẵng | W30: CDNP621 | X30: Công nghệ thông tin | Z30: Trung tâm Đại học Mở Hà Nội tại Đà Nẵng | AA30: Trực tuyến | AB30: HT | AC30: HT | AD30: HT | AG30: {=_xludf.XLOOKUP(D30,'Mail+SDT'!A:A,'Mail+SDT'!B:B)} -> #NAME? | AH30: {=_xludf.XLOOKUP(D30,'Mail+SDT'!A:A,'Mail+SDT'!C:C)} -> #NAME? | AI30: {=_xludf.XLOOKUP(D30,'ETK 3.2026'!I:I,'ETK 3.2026'!AF:AF)} -> #NAME?
A31: =ROW()-1 -> 30 | B31: Trangnt | C31: Sangpn | D31: baodg002 | E31: 1676/2024/QĐ-ĐHM | F31: 03/05/2024 | G31: =(YEAR(H31)-YEAR(F31))*12 + MONTH(H31)-MONTH(F31) -> 72 | H31: 03/05/2030 | I31: =IF((H31-TODAY())<=0,"Kết thúc ĐT","Thời gian ĐT còn lại "&(H31-TODAY())&" ngày") -> Thời gian ĐT còn lại 1500 ngày | J31: 24C1002H2398 | K31: Dương Gia Bảo | L31: Dương Gia | M31: Bảo | N31: 14/04/2002 | O31: Nam | P31: 21 | Q31: CDNVT621 | R31: Công nghệ thông tin | S31: =VLOOKUP(D31, 'Mail+SDT'!A544:C2659, 2, 0) -> 24C1002H2398@students.hou.edu.vn | T31: =VLOOKUP(D31, 'Mail+SDT'!$A$2:$C$2117, 3, 0) -> 981701321 | U31: DNVT | V31: Trường Trung cấp Vạn Tường | W31: CDNVT621 | X31: Công nghệ thông tin | Z31: Trường Trung cấp Vạn Tường | AA31: Trực tuyến | AB31: HT | AC31: HT | AD31: HT | AG31: {=_xludf.XLOOKUP(D31,'Mail+SDT'!A:A,'Mail+SDT'!B:B)} -> #NAME? | AH31: {=_xludf.XLOOKUP(D31,'Mail+SDT'!A:A,'Mail+SDT'!C:C)} -> #NAME? | AI31: {=_xludf.XLOOKUP(D31,'ETK 3.2026'!I:I,'ETK 3.2026'!AF:AF)} -> #NAME?
A32: =ROW()-1 -> 31 | B32: Trangnt | C32: Sangpn | D32: baodq004 | E32: 2205/2024/QĐ-ĐHM | F32: 07/06/2024 | G32: =(YEAR(H32)-YEAR(F32))*12 + MONTH(H32)-MONTH(F32) -> 72 | H32: 07/06/2030 | I32: =IF((H32-TODAY())<=0,"Kết thúc ĐT","Thời gian ĐT còn lại "&(H32-TODAY())&" ngày") -> Thời gian ĐT còn lại 1535 ngày | J32: 24C4102H3179 | K32: Đào Quốc Bảo | L32: Đào Quốc | M32: Bảo | N32: 26/02/1991 | O32: Nam | P32: 21 | Q32: ADNVT521 | R32: Kế toán | S32: =VLOOKUP(D32, 'Mail+SDT'!A357:C2472, 2, 0) -> 24C4102H3179@students.hou.edu.vn | T32: =VLOOKUP(D32, 'Mail+SDT'!$A$2:$C$2117, 3, 0) -> 399688474 | U32: DNVT | V32: Trường Trung cấp Vạn Tường | W32: ADNVT521 | X32: Kế toán | Z32: Trường Trung cấp Vạn Tường | AA32: Trực tuyến | AB32: HT | AC32: HT | AD32: HT | AG32: {=_xludf.XLOOKUP(D32,'Mail+SDT'!A:A,'Mail+SDT'!B:B)} -> #NAME? | AH32: {=_xludf.XLOOKUP(D32,'Mail+SDT'!A:A,'Mail+SDT'!C:C)} -> #NAME? | AI32: {=_xludf.XLOOKUP(D32,'ETK 3.2026'!I:I,'ETK 3.2026'!AF:AF)} -> #NAME?
A33: =ROW()-1 -> 32 | B33: Trangnt | C33: Quynhtnn | D33: baodt005 | E33: 2501/2024/QĐ-ĐHM | F33: 28/06/2024 | G33: =(YEAR(H33)-YEAR(F33))*12 + MONTH(H33)-MONTH(F33) -> 72 | H33: 28/06/2030 | I33: =IF((H33-TODAY())<=0,"Kết thúc ĐT","Thời gian ĐT còn lại "&(H33-TODAY())&" ngày") -> Thời gian ĐT còn lại 1556 ngày | J33: 24C4204D3684 | K33: Dương Thiên Bão | L33: Dương Thiên | M33: Bão | N33: 14/02/1995 | O33: Nam | P33: 21 | Q33: BDNP621 | R33: Quản trị kinh doanh | S33: =VLOOKUP(D33, 'Mail+SDT'!A152:C2267, 2, 0) -> 24C4204D3684@students.hou.edu.vn | T33: =VLOOKUP(D33, 'Mail+SDT'!$A$2:$C$2117, 3, 0) -> 944834979 | U33: DNP | V33: Trung tâm Đại học Mở Hà Nội tại Đà Nẵng | W33: BDNP621 | X33: Quản trị kinh doanh | Z33: Trung tâm Đại học Mở Hà Nội tại Đà Nẵng | AA33: Trực tuyến | AB33: HT | AC33: HT | AD33: HT | AG33: {=_xludf.XLOOKUP(D33,'Mail+SDT'!A:A,'Mail+SDT'!B:B)} -> #NAME? | AH33: {=_xludf.XLOOKUP(D33,'Mail+SDT'!A:A,'Mail+SDT'!C:C)} -> #NAME? | AI33: {=_xludf.XLOOKUP(D33,'ETK 3.2026'!I:I,'ETK 3.2026'!AF:AF)} -> #NAME?
A34: =ROW()-1 -> 33 | B34: Trangnt | C34: Sangpn | D34: baolq005 | E34: 2661/2024/QĐ-ĐHM | F34: 02/07/2024 | G34: =(YEAR(H34)-YEAR(F34))*12 + MONTH(H34)-MONTH(F34) -> 72 | H34: 02/07/2030 | I34: =IF((H34-TODAY())<=0,"Kết thúc ĐT","Thời gian ĐT còn lại "&(H34-TODAY())&" ngày") -> Thời gian ĐT còn lại 1560 ngày | J34: 24C1002H3977 | K34: Lê Quốc Bảo | L34: Lê Quốc | M34: Bảo | N34: 27/05/2001 | O34: Nam | P34: 21 | Q34: CDNVT621 | R34: Công nghệ thông tin | S34: =VLOOKUP(D34, 'Mail+SDT'!A528:C2643, 2, 0) -> 24C1002H3977@students.hou.edu.vn | T34: =VLOOKUP(D34, 'Mail+SDT'!$A$2:$C$2117, 3, 0) -> 345550916 | U34: DNVT | V34: Trường Trung cấp Vạn Tường | W34: CDNVT621 | X34: Công nghệ thông tin | Z34: Trường Trung cấp Vạn Tường | AA34: Trực tuyến | AB34: HT | AC34: HT | AD34: CBKL1 | AG34: {=_xludf.XLOOKUP(D34,'Mail+SDT'!A:A,'Mail+SDT'!B:B)} -> #NAME? | AH34: {=_xludf.XLOOKUP(D34,'Mail+SDT'!A:A,'Mail+SDT'!C:C)} -> #NAME? | AI34: {=_xludf.XLOOKUP(D34,'ETK 3.2026'!I:I,'ETK 3.2026'!AF:AF)} -> #NAME?
A35: =ROW()-1 -> 34 | B35: Trangnt | C35: Sangpn | D35: baonpn | E35: 2205/2024/QĐ-ĐHM | F35: 07/06/2024 | G35: =(YEAR(H35)-YEAR(F35))*12 + MONTH(H35)-MONTH(F35) -> 72 | H35: 07/06/2030 | I35: =IF((H35-TODAY())<=0,"Kết thúc ĐT","Thời gian ĐT còn lại "&(H35-TODAY())&" ngày") -> Thời gian ĐT còn lại 1535 ngày | J35: 24C4202H3158 | K35: Nguyễn Phúc Nguyên Bảo | L35: Nguyễn Phúc Nguyên | M35: Bảo | N35: 20/12/2001 | O35: Nam | P35: 21 | Q35: BDNVT621 | R35: Quản trị kinh doanh | S35: =VLOOKUP(D35, 'Mail+SDT'!A465:C2580, 2, 0) -> 24C4202H3158@students.hou.edu.vn | T35: =VLOOKUP(D35, 'Mail+SDT'!$A$2:$C$2117, 3, 0) -> 969600220 | U35: DNVT | V35: Trường Trung cấp Vạn Tường | W35: BDNVT621 | X35: Quản trị kinh doanh | Z35: Trường Trung cấp Vạn Tường | AA35: Trực tuyến | AB35: HT | AC35: HT | AD35: HT | AG35: {=_xludf.XLOOKUP(D35,'Mail+SDT'!A:A,'Mail+SDT'!B:B)} -> #NAME? | AH35: {=_xludf.XLOOKUP(D35,'Mail+SDT'!A:A,'Mail+SDT'!C:C)} -> #NAME? | AI35: {=_xludf.XLOOKUP(D35,'ETK 3.2026'!I:I,'ETK 3.2026'!AF:AF)} -> #NAME?
A36: =ROW()-1 -> 35 | B36: Trangnt | C36: Quynhtnn | D36: baont005 | E36: 833/2020/QĐ-ĐHM | F36: 10/03/2020 | G36: =(YEAR(H36)-YEAR(F36))*12 + MONTH(H36)-MONTH(F36) -> 96 | H36: 10/03/2028 | I36: =IF((H36-TODAY())<=0,"Kết thúc ĐT","Thời gian ĐT còn lại "&(H36-TODAY())&" ngày") -> Thời gian ĐT còn lại 716 ngày | J36: 20C-51-55.0-00720 | K36: Nguyễn Thế Bảo | L36: Nguyễn Thế | M36: Bảo | N36: 17/08/1996 | O36: Nam | P36: 13 | Q36: EDNP513 | R36: Luật kinh tế | S36: =VLOOKUP(D36, 'Mail+SDT'!A17:C2132, 2, 0) -> nguyenthebao1708@gmail.com | T36: =VLOOKUP(D36, 'Mail+SDT'!$A$2:$C$2117, 3, 0) -> 0 | U36: DNP | V36: Trung tâm Đại học Mở Hà Nội tại Đà Nẵng | W36: EDNP513 | X36: Luật kinh tế | Z36: Trung tâm Đại học Mở Hà Nội tại Đà Nẵng | AA36: Trực tuyến | AB36: HT | AC36: HT | AD36: HT | AF36: NỢ MÔN THI GHÉP THÁNG 4 TRẢ NỢ_TN 6.2026 | AG36: {=_xludf.XLOOKUP(D36,'Mail+SDT'!A:A,'Mail+SDT'!B:B)} -> #NAME? | AH36: {=_xludf.XLOOKUP(D36,'Mail+SDT'!A:A,'Mail+SDT'!C:C)} -> #NAME? | AI36: {=_xludf.XLOOKUP(D36,'ETK 3.2026'!I:I,'ETK 3.2026'!Z:Z)} -> #NAME?
A37: =ROW()-1 -> 36 | B37: Trangnt | C37: Quynhtnn | D37: benntc | E37: 980/2022/QĐ-ĐHM | F37: 07/04/2022 | G37: =(YEAR(H37)-YEAR(F37))*12 + MONTH(H37)-MONTH(F37) -> 72 | H37: 07/04/2028 | I37: =IF((H37-TODAY())<=0,"Kết thúc ĐT","Thời gian ĐT còn lại "&(H37-TODAY())&" ngày") -> Thời gian ĐT còn lại 744 ngày | J37: 22C7104D1171 | K37: Nguyễn Thanh Chí Bền | L37: Nguyễn Thanh Chí | M37: Bền | N37: 05/11/1997 | O37: Nam | P37: 17 | Q37: FDNP617 | R37: Ngôn ngữ Anh | S37: =VLOOKUP(D37, 'Mail+SDT'!A69:C2184, 2, 0) -> chiben262@gmail.com | T37: =VLOOKUP(D37, 'Mail+SDT'!$A$2:$C$2117, 3, 0) -> 905405041 | U37: DNP | V37: Trung tâm Đại học Mở Hà Nội tại Đà Nẵng | W37: FDNP617 | X37: Ngôn ngữ Anh | Z37: Trung tâm Đại học Mở Hà Nội tại Đà Nẵng | AA37: Trực tuyến | AB37: HT | AC37: HT | AD37: HT | AG37: {=_xludf.XLOOKUP(D37,'Mail+SDT'!A:A,'Mail+SDT'!B:B)} -> #NAME? | AH37: {=_xludf.XLOOKUP(D37,'Mail+SDT'!A:A,'Mail+SDT'!C:C)} -> #NAME? | AI37: {=_xludf.XLOOKUP(D37,'ETK 3.2026'!I:I,'ETK 3.2026'!Z:Z)} -> #NAME?
A38: =ROW()-1 -> 37 | B38: Trangnt | C38: Sangpn | D38: bienpq002 | E38: 2501/2024/QĐ-ĐHM | F38: 28/06/2024 | G38: =(YEAR(H38)-YEAR(F38))*12 + MONTH(H38)-MONTH(F38) -> 72 | H38: 28/06/2030 | I38: =IF((H38-TODAY())<=0,"Kết thúc ĐT","Thời gian ĐT còn lại "&(H38-TODAY())&" ngày") -> Thời gian ĐT còn lại 1556 ngày | J38: 24C1002H3653 | K38: Phan Quốc Biên | L38: Phan Quốc | M38: Biên | N38: 02/02/1990 | O38: Nam | P38: 21 | Q38: CDNVT621 | R38: Công nghệ thông tin | S38: =VLOOKUP(D38, 'Mail+SDT'!A553:C2668, 2, 0) -> 24C1002H3653@students.hou.edu.vn | T38: =VLOOKUP(D38, 'Mail+SDT'!$A$2:$C$2117, 3, 0) -> 357232232 | U38: DNVT | V38: Trường Trung cấp Vạn Tường | W38: CDNVT621 | X38: Công nghệ thông tin | Z38: Trường Trung cấp Vạn Tường | AA38: Trực tuyến | AB38: HT | AC38: HT | AD38: CBKL1 | AE38: BTH | AF38: Thiếu QT học phí để QR | AG38: {=_xludf.XLOOKUP(D38,'Mail+SDT'!A:A,'Mail+SDT'!B:B)} -> #NAME? | AH38: {=_xludf.XLOOKUP(D38,'Mail+SDT'!A:A,'Mail+SDT'!C:C)} -> #NAME? | AI38: {=_xludf.XLOOKUP(D38,'ETK 3.2026'!I:I,'ETK 3.2026'!AF:AF)} -> #NAME?
A39: =ROW()-1 -> 38 | B39: Trangnt | C39: Quynhtnn | D39: binhdv004 | E39: 1379/2024/QĐ-ĐHM | F39: 12/04/2024 | G39: =(YEAR(H39)-YEAR(F39))*12 + MONTH(H39)-MONTH(F39) -> 72 | H39: 12/04/2030 | I39: =IF((H39-TODAY())<=0,"Kết thúc ĐT","Thời gian ĐT còn lại "&(H39-TODAY())&" ngày") -> Thời gian ĐT còn lại 1479 ngày | J39: 24C1004D1882 | K39: Đồng Văn Bính | L39: Đồng Văn | M39: Bính | N39: 01/02/1989 | O39: Nam | P39: 21 | Q39: CDNP521 | R39: Công nghệ thông tin | S39: =VLOOKUP(D39, 'Mail+SDT'!A169:C2284, 2, 0) -> 24C1004D1882@students.hou.edu.vn | T39: =VLOOKUP(D39, 'Mail+SDT'!$A$2:$C$2117, 3, 0) -> 963757800 | U39: DNP | V39: Trung tâm Đại học Mở Hà Nội tại Đà Nẵng | W39: CDNP521 | X39: Công nghệ thông tin | Z39: Trung tâm Đại học Mở Hà Nội tại Đà Nẵng | AA39: Trực tuyến | AB39: HT | AC39: HT | AD39: CBKL1 | AG39: {=_xludf.XLOOKUP(D39,'Mail+SDT'!A:A,'Mail+SDT'!B:B)} -> #NAME? | AH39: {=_xludf.XLOOKUP(D39,'Mail+SDT'!A:A,'Mail+SDT'!C:C)} -> #NAME? | AI39: {=_xludf.XLOOKUP(D39,'ETK 3.2026'!I:I,'ETK 3.2026'!AF:AF)} -> #NAME?
A40: =ROW()-1 -> 39 | B40: Trangnt | C40: Sangpn | D40: binhpd004 | E40: 2661/2024/QĐ-ĐHM | F40: 02/07/2024 | G40: =(YEAR(H40)-YEAR(F40))*12 + MONTH(H40)-MONTH(F40) -> 72 | H40: 02/07/2030 | I40: =IF((H40-TODAY())<=0,"Kết thúc ĐT","Thời gian ĐT còn lại "&(H40-TODAY())&" ngày") -> Thời gian ĐT còn lại 1560 ngày | J40: 24C4502H4034 | K40: Phan Đức Bình | L40: Phan Đức | M40: Bình | N40: 24/06/1997 | O40: Nam | P40: 21 | Q40: DDNVT621 | R40: Tài chính - Ngân hàng | S40: =VLOOKUP(D40, 'Mail+SDT'!A589:C2704, 2, 0) -> 24C4502H4034@students.hou.edu.vn | T40: =VLOOKUP(D40, 'Mail+SDT'!$A$2:$C$2117, 3, 0) -> 355474692 | U40: DNVT | V40: Trường Trung cấp Vạn Tường | W40: DDNVT621 | X40: Tài chính - Ngân hàng | Z40: Trường Trung cấp Vạn Tường | AA40: Trực tuyến | AB40: HT | AC40: HT | AD40: CBKL1 | AE40: BTH | AF40: Thiếu QT học phí để QR | AG40: {=_xludf.XLOOKUP(D40,'Mail+SDT'!A:A,'Mail+SDT'!B:B)} -> #NAME? | AH40: {=_xludf.XLOOKUP(D40,'Mail+SDT'!A:A,'Mail+SDT'!C:C)} -> #NAME? | AI40: {=_xludf.XLOOKUP(D40,'ETK 3.2026'!I:I,'ETK 3.2026'!AF:AF)} -> #NAME?
A41: =ROW()-1 -> 40 | B41: Trangnt | C41: Quynhtnn | D41: binhpt012 | E41: 980/2022/QĐ-ĐHM | F41: 07/04/2022 | G41: =(YEAR(H41)-YEAR(F41))*12 + MONTH(H41)-MONTH(F41) -> 72 | H41: 07/04/2028 | I41: =IF((H41-TODAY())<=0,"Kết thúc ĐT","Thời gian ĐT còn lại "&(H41-TODAY())&" ngày") -> Thời gian ĐT còn lại 744 ngày | J41: 22C4102E1165 | K41: Phan Thị Bình | L41: Phan Thị | M41: Bình | N41: 10/02/1989 | O41: Nữ | P41: 17 | Q41: ADNP517 | R41: Kế toán | S41: =VLOOKUP(D41, 'Mail+SDT'!A19:C2134, 2, 0) -> binh.phan0289@gmail.com | T41: =VLOOKUP(D41, 'Mail+SDT'!$A$2:$C$2117, 3, 0) -> 905912022 | U41: DNP | V41: Trung tâm Đại học Mở Hà Nội tại Đà Nẵng | W41: ADNP517 | X41: Kế toán | Z41: Trung tâm Đại học Mở Hà Nội tại Đà Nẵng | AA41: Trực tuyến | AB41: HT | AC41: HT | AD41: HTCT | AG41: {=_xludf.XLOOKUP(D41,'Mail+SDT'!A:A,'Mail+SDT'!B:B)} -> #NAME? | AH41: {=_xludf.XLOOKUP(D41,'Mail+SDT'!A:A,'Mail+SDT'!C:C)} -> #NAME? | AI41: {=_xludf.XLOOKUP(D41,'ETK 3.2026'!I:I,'ETK 3.2026'!AF:AF)} -> #NAME?
A42: =ROW()-1 -> 41 | B42: Trangnt | C42: Sangpn | D42: binhtv008 | E42: 2205/2024/QĐ-ĐHM | F42: 07/06/2024 | G42: =(YEAR(H42)-YEAR(F42))*12 + MONTH(H42)-MONTH(F42) -> 72 | H42: 07/06/2030 | I42: =IF((H42-TODAY())<=0,"Kết thúc ĐT","Thời gian ĐT còn lại "&(H42-TODAY())&" ngày") -> Thời gian ĐT còn lại 1535 ngày | J42: 24C4702H3274 | K42: Trần Văn Bình | L42: Trần Văn | M42: Bình | N42: 19/10/1980 | O42: Nam | P42: 21 | Q42: NDNVT621 | R42: Thương mại điện tử | S42: =VLOOKUP(D42, 'Mail+SDT'!A618:C2733, 2, 0) -> 24C4702H3274@students.hou.edu.vn | T42: =VLOOKUP(D42, 'Mail+SDT'!$A$2:$C$2117, 3, 0) -> 917333346 | U42: DNVT | V42: Trường Trung cấp Vạn Tường | W42: NDNVT621 | X42: Thương mại điện tử | Z42: Trường Trung cấp Vạn Tường | AA42: Trực tuyến | AB42: HT | AC42: HT | AD42: CBKL1 | AG42: {=_xludf.XLOOKUP(D42,'Mail+SDT'!A:A,'Mail+SDT'!B:B)} -> #NAME? | AH42: {=_xludf.XLOOKUP(D42,'Mail+SDT'!A:A,'Mail+SDT'!C:C)} -> #NAME? | AI42: {=_xludf.XLOOKUP(D42,'ETK 3.2026'!I:I,'ETK 3.2026'!AF:AF)} -> #NAME?
A43: =ROW()-1 -> 42 | B43: Trangnt | C43: Quynhtnn | D43: chaultn | E43: 1676/2024/QĐ-ĐHM | F43: 03/05/2024 | G43: =(YEAR(H43)-YEAR(F43))*12 + MONTH(H43)-MONTH(F43) -> 72 | H43: 03/05/2030 | I43: =IF((H43-TODAY())<=0,"Kết thúc ĐT","Thời gian ĐT còn lại "&(H43-TODAY())&" ngày") -> Thời gian ĐT còn lại 1500 ngày | J43: 24C1004D2524 | K43: Lê Thị Ngọc Châu | L43: Lê Thị Ngọc | M43: Châu | N43: 10/08/1996 | O43: Nữ | P43: 21 | Q43: CDNP621 | R43: Công nghệ thông tin | S43: =VLOOKUP(D43, 'Mail+SDT'!A173:C2288, 2, 0) -> 24C1004D2524@students.hou.edu.vn | T43: =VLOOKUP(D43, 'Mail+SDT'!$A$2:$C$2117, 3, 0) -> 366178903 | U43: DNP | V43: Trung tâm Đại học Mở Hà Nội tại Đà Nẵng | W43: CDNP621 | X43: Công nghệ thông tin | Z43: Trung tâm Đại học Mở Hà Nội tại Đà Nẵng | AA43: Trực tuyến | AB43: HT | AC43: HT | AD43: HT | AG43: {=_xludf.XLOOKUP(D43,'Mail+SDT'!A:A,'Mail+SDT'!B:B)} -> #NAME? | AH43: {=_xludf.XLOOKUP(D43,'Mail+SDT'!A:A,'Mail+SDT'!C:C)} -> #NAME? | AI43: {=_xludf.XLOOKUP(D43,'ETK 3.2026'!I:I,'ETK 3.2026'!AF:AF)} -> #NAME?
A44: =ROW()-1 -> 43 | B44: Trangnt | C44: Sangpn | D44: chauqn | E44: 2205/2024/QĐ-ĐHM | F44: 07/06/2024 | G44: =(YEAR(H44)-YEAR(F44))*12 + MONTH(H44)-MONTH(F44) -> 72 | H44: 07/06/2030 | I44: =IF((H44-TODAY())<=0,"Kết thúc ĐT","Thời gian ĐT còn lại "&(H44-TODAY())&" ngày") -> Thời gian ĐT còn lại 1535 ngày | J44: 24C4202H3169 | K44: Quách Ngọc Châu | L44: Quách Ngọc | M44: Châu | N44: 15/09/1985 | O44: Nữ | P44: 21 | Q44: BDNVT621 | R44: Quản trị kinh doanh | S44: =VLOOKUP(D44, 'Mail+SDT'!A468:C2583, 2, 0) -> 24C4202H3169@students.hou.edu.vn | T44: =VLOOKUP(D44, 'Mail+SDT'!$A$2:$C$2117, 3, 0) -> 909512179 | U44: DNVT | V44: Trường Trung cấp Vạn Tường | W44: BDNVT621 | X44: Quản trị kinh doanh | Z44: Trường Trung cấp Vạn Tường | AA44: Trực tuyến | AB44: HT | AC44: HT | AD44: CBKL1 | AE44: BTH | AF44: Thiếu QT học phí để QR | AG44: {=_xludf.XLOOKUP(D44,'Mail+SDT'!A:A,'Mail+SDT'!B:B)} -> #NAME? | AH44: {=_xludf.XLOOKUP(D44,'Mail+SDT'!A:A,'Mail+SDT'!C:C)} -> #NAME? | AI44: {=_xludf.XLOOKUP(D44,'ETK 3.2026'!I:I,'ETK 3.2026'!AF:AF)} -> #NAME?
A45: =ROW()-1 -> 44 | B45: Trangnt | C45: Quynhtnn | D45: chibb | E45: 1676/2024/QĐ-ĐHM | F45: 03/05/2024 | G45: =(YEAR(H45)-YEAR(F45))*12 + MONTH(H45)-MONTH(F45) -> 72 | H45: 03/05/2030 | I45: =IF((H45-TODAY())<=0,"Kết thúc ĐT","Thời gian ĐT còn lại "&(H45-TODAY())&" ngày") -> Thời gian ĐT còn lại 1500 ngày | J45: 24C1002H2402 | K45: Bùi Bá Chí | L45: Bùi Bá | M45: Chí | N45: 27/06/1999 | O45: Nam | P45: 21 | Q45: CDNP621 | R45: Công nghệ thông tin | S45: =VLOOKUP(D45, 'Mail+SDT'!A203:C2318, 2, 0) -> 24C1002H2402@students.hou.edu.vn | T45: =VLOOKUP(D45, 'Mail+SDT'!$A$2:$C$2117, 3, 0) -> 989106512 | U45: DNP | V45: Trung tâm Đại học Mở Hà Nội tại Đà Nẵng | W45: CDNP621 | X45: Công nghệ thông tin | Z45: Trung tâm Đại học Mở Hà Nội tại Đà Nẵng | AA45: Trực tuyến | AB45: HT | AC45: HT | AD45: HT | AG45: {=_xludf.XLOOKUP(D45,'Mail+SDT'!A:A,'Mail+SDT'!B:B)} -> #NAME? | AH45: {=_xludf.XLOOKUP(D45,'Mail+SDT'!A:A,'Mail+SDT'!C:C)} -> #NAME? | AI45: {=_xludf.XLOOKUP(D45,'ETK 3.2026'!I:I,'ETK 3.2026'!AF:AF)} -> #NAME?
A46: =ROW()-1 -> 45 | B46: Trangnt | C46: Quynhtnn | D46: chienmv | E46: 1379/2024/QĐ-ĐHM | F46: 12/04/2024 | G46: =(YEAR(H46)-YEAR(F46))*12 + MONTH(H46)-MONTH(F46) -> 72 | H46: 12/04/2030 | I46: =IF((H46-TODAY())<=0,"Kết thúc ĐT","Thời gian ĐT còn lại "&(H46-TODAY())&" ngày") -> Thời gian ĐT còn lại 1479 ngày | J46: 24C4504D1906 | K46: Mai Văn Chiến | L46: Mai Văn | M46: Chiến | N46: 17/06/1992 | O46: Nam | P46: 21 | Q46: DDNP421 | R46: Tài chính - Ngân hàng | S46: =VLOOKUP(D46, 'Mail+SDT'!A188:C2303, 2, 0) -> 24C4504D1906@students.hou.edu.vn | T46: =VLOOKUP(D46, 'Mail+SDT'!$A$2:$C$2117, 3, 0) -> 942808022 | U46: DNP | V46: Trung tâm Đại học Mở Hà Nội tại Đà Nẵng | W46: DDNP421 | X46: Tài chính - Ngân hàng | Z46: Trung tâm Đại học Mở Hà Nội tại Đà Nẵng | AA46: Trực tuyến | AB46: HT | AC46: HT | AD46: HT | AG46: {=_xludf.XLOOKUP(D46,'Mail+SDT'!A:A,'Mail+SDT'!B:B)} -> #NAME? | AH46: {=_xludf.XLOOKUP(D46,'Mail+SDT'!A:A,'Mail+SDT'!C:C)} -> #NAME? | AI46: {=_xludf.XLOOKUP(D46,'ETK 3.2026'!I:I,'ETK 3.2026'!AF:AF)} -> #NAME?
A47: =ROW()-1 -> 46 | B47: Trangnt | C47: Sangpn | D47: chiennv007 | E47: 1492/2022/QĐ-ĐHM | F47: 17/05/2022 | G47: =(YEAR(H47)-YEAR(F47))*12 + MONTH(H47)-MONTH(F47) -> 72 | H47: 17/05/2028 | I47: =IF((H47-TODAY())<=0,"Kết thúc ĐT","Thời gian ĐT còn lại "&(H47-TODAY())&" ngày") -> Thời gian ĐT còn lại 784 ngày | J47: 22C5002H1827 | K47: Nguyễn Văn Chiến | L47: Nguyễn Văn | M47: Chiến | N47: 08/07/1994 | O47: Nam | P47: 17 | Q47: HDNVT617 | R47: Luật | S47: =VLOOKUP(D47, 'Mail+SDT'!A338:C2453, 2, 0) -> chiennguyen1268994@gmail.com | T47: =VLOOKUP(D47, 'Mail+SDT'!$A$2:$C$2117, 3, 0) -> 901268994 | U47: DNVT | V47: Trường Trung cấp Vạn Tường | W47: HDNVT617 | X47: Luật | Z47: Trường Trung cấp Vạn Tường | AA47: Trực tuyến | AB47: HT | AC47: HT | AD47: HT | AF47: TN 3.2026 | AG47: {=_xludf.XLOOKUP(D47,'Mail+SDT'!A:A,'Mail+SDT'!B:B)} -> #NAME? | AH47: {=_xludf.XLOOKUP(D47,'Mail+SDT'!A:A,'Mail+SDT'!C:C)} -> #NAME? | AI47: {=_xludf.XLOOKUP(D47,'ETK 3.2026'!I:I,'ETK 3.2026'!AF:AF)} -> #NAME?
A48: =ROW()-1 -> 47 | B48: Trangnt | C48: Sangpn | D48: chinhtd003 | E48: 2205/2024/QĐ-ĐHM | F48: 07/06/2024 | G48: =(YEAR(H48)-YEAR(F48))*12 + MONTH(H48)-MONTH(F48) -> 72 | H48: 07/06/2030 | I48: =IF((H48-TODAY())<=0,"Kết thúc ĐT","Thời gian ĐT còn lại "&(H48-TODAY())&" ngày") -> Thời gian ĐT còn lại 1535 ngày | J48: 24C4202H3164 | K48: Trương Đức Chính | L48: Trương Đức | M48: Chính | N48: 01/08/1996 | O48: Nam | P48: 21 | Q48: BDNVT621 | R48: Quản trị kinh doanh | S48: =VLOOKUP(D48, 'Mail+SDT'!A464:C2579, 2, 0) -> 24C4202H3164@students.hou.edu.vn | T48: =VLOOKUP(D48, 'Mail+SDT'!$A$2:$C$2117, 3, 0) -> 352613903 | U48: DNVT | V48: Trường Trung cấp Vạn Tường | W48: BDNVT621 | X48: Quản trị kinh doanh | Z48: Trường Trung cấp Vạn Tường | AA48: Trực tuyến | AB48: HT | AC48: HT | AD48: HT | AG48: {=_xludf.XLOOKUP(D48,'Mail+SDT'!A:A,'Mail+SDT'!B:B)} -> #NAME? | AH48: {=_xludf.XLOOKUP(D48,'Mail+SDT'!A:A,'Mail+SDT'!C:C)} -> #NAME? | AI48: {=_xludf.XLOOKUP(D48,'ETK 3.2026'!I:I,'ETK 3.2026'!AF:AF)} -> #NAME?
A49: =ROW()-1 -> 48 | B49: Trangnt | C49: Quynhtnn | D49: chinhtv005 | E49: 2205/2024/QĐ-ĐHM | F49: 07/06/2024 | G49: =(YEAR(H49)-YEAR(F49))*12 + MONTH(H49)-MONTH(F49) -> 72 | H49: 07/06/2030 | I49: =IF((H49-TODAY())<=0,"Kết thúc ĐT","Thời gian ĐT còn lại "&(H49-TODAY())&" ngày") -> Thời gian ĐT còn lại 1535 ngày | J49: 24C4204D3347 | K49: Trần Văn Chính | L49: Trần Văn | M49: Chính | N49: 16/03/1998 | O49: Nam | P49: 21 | Q49: BDNP621 | R49: Quản trị kinh doanh | S49: =VLOOKUP(D49, 'Mail+SDT'!A155:C2270, 2, 0) -> 24C4204D3347@students.hou.edu.vn | T49: =VLOOKUP(D49, 'Mail+SDT'!$A$2:$C$2117, 3, 0) -> 905809246 | U49: DNP | V49: Trung tâm Đại học Mở Hà Nội tại Đà Nẵng | W49: BDNP621 | X49: Quản trị kinh doanh | Z49: Trung tâm Đại học Mở Hà Nội tại Đà Nẵng | AA49: Trực tuyến | AB49: HT | AC49: HT | AD49: HT | AG49: {=_xludf.XLOOKUP(D49,'Mail+SDT'!A:A,'Mail+SDT'!B:B)} -> #NAME? | AH49: {=_xludf.XLOOKUP(D49,'Mail+SDT'!A:A,'Mail+SDT'!C:C)} -> #NAME? | AI49: {=_xludf.XLOOKUP(D49,'ETK 3.2026'!I:I,'ETK 3.2026'!AF:AF)} -> #NAME?
A50: =ROW()-1 -> 49 | B50: Trangnt | C50: Sangpn | D50: chitdt | E50: 1492/2022/QĐ-ĐHM | F50: 17/05/2022 | G50: =(YEAR(H50)-YEAR(F50))*12 + MONTH(H50)-MONTH(F50) -> 72 | H50: 17/05/2028 | I50: =IF((H50-TODAY())<=0,"Kết thúc ĐT","Thời gian ĐT còn lại "&(H50-TODAY())&" ngày") -> Thời gian ĐT còn lại 784 ngày | J50: 22C1002H1731 | K50: Trần Dương Thiện Chí | L50: Trần Dương Thiện | M50: Chí | N50: 14/10/1989 | O50: Nam | P50: 17 | Q50: CDNVT117 | R50: Công nghệ thông tin | S50: =VLOOKUP(D50, 'Mail+SDT'!A248:C2363, 2, 0) -> thienchihl@gmail.com | T50: =VLOOKUP(D50, 'Mail+SDT'!$A$2:$C$2117, 3, 0) -> 915970990 | U50: DNVT | V50: Trường Trung cấp Vạn Tường | W50: CDNVT117 | X50: Công nghệ thông tin | Z50: Trường Trung cấp Vạn Tường | AA50: Trực tuyến | AB50: HT | AC50: HT | AD50: HTCT | AG50: {=_xludf.XLOOKUP(D50,'Mail+SDT'!A:A,'Mail+SDT'!B:B)} -> #NAME? | AH50: {=_xludf.XLOOKUP(D50,'Mail+SDT'!A:A,'Mail+SDT'!C:C)} -> #NAME? | AI50: {=_xludf.XLOOKUP(D50,'ETK 3.2026'!I:I,'ETK 3.2026'!AF:AF)} -> #NAME?
A51: =ROW()-1 -> 50 | B51: Trangnt | C51: Sangpn | D51: chivtk003 | E51: 1301/2024/QĐ-ĐHM | F51: 05/04/2024 | G51: =(YEAR(H51)-YEAR(F51))*12 + MONTH(H51)-MONTH(F51) -> 72 | H51: 05/04/2030 | I51: =IF((H51-TODAY())<=0,"Kết thúc ĐT","Thời gian ĐT còn lại "&(H51-TODAY())&" ngày") -> Thời gian ĐT còn lại 1472 ngày | J51: 24C4702H1711 | K51: Vương Thị Kim Chi | L51: Vương Thị Kim | M51: Chi | N51: 03/10/1999 | O51: Nữ | P51: 21 | Q51: NDNVT621 | R51: Thương mại điện tử | S51: =VLOOKUP(D51, 'Mail+SDT'!A617:C2732, 2, 0) -> 24C4702H1711@students.hou.edu.vn | T51: =VLOOKUP(D51, 'Mail+SDT'!$A$2:$C$2117, 3, 0) -> 777987937 | U51: DNVT | V51: Trường Trung cấp Vạn Tường | W51: NDNVT621 | X51: Thương mại điện tử | Z51: Trường Trung cấp Vạn Tường | AA51: Trực tuyến | AB51: HT | AC51: HT | AD51: HT | AG51: {=_xludf.XLOOKUP(D51,'Mail+SDT'!A:A,'Mail+SDT'!B:B)} -> #NAME? | AH51: {=_xludf.XLOOKUP(D51,'Mail+SDT'!A:A,'Mail+SDT'!C:C)} -> #NAME? | AI51: {=_xludf.XLOOKUP(D51,'ETK 3.2026'!I:I,'ETK 3.2026'!AF:AF)} -> #NAME?
A52: =ROW()-1 -> 51 | B52: Trangnt | C52: Sangpn | D52: chucnt003 | E52: 2118/2022/QĐ-ĐHM | F52: 30/06/2022 | G52: =(YEAR(H52)-YEAR(F52))*12 + MONTH(H52)-MONTH(F52) -> 72 | H52: 30/06/2028 | I52: =IF((H52-TODAY())<=0,"Kết thúc ĐT","Thời gian ĐT còn lại "&(H52-TODAY())&" ngày") -> Thời gian ĐT còn lại 828 ngày | J52: 22C4102H2731 | K52: Nguyễn Thị Chúc | L52: Nguyễn Thị | M52: Chúc | N52: 24/06/2000 | O52: Nữ | P52: 17 | Q52: ADNVT617 | R52: Kế toán | S52: =VLOOKUP(D52, 'Mail+SDT'!A217:C2332, 2, 0) -> 1854070018chuc@ou.edu.vn | T52: =VLOOKUP(D52, 'Mail+SDT'!$A$2:$C$2117, 3, 0) -> 867027249 | U52: DNVT | V52: Trường Trung cấp Vạn Tường | W52: ADNVT617 | X52: Kế toán | Z52: Trường Trung cấp Vạn Tường | AA52: Trực tuyến | AB52: HT | AC52: HT | AD52: HT | AG52: {=_xludf.XLOOKUP(D52,'Mail+SDT'!A:A,'Mail+SDT'!B:B)} -> #NAME? | AH52: {=_xludf.XLOOKUP(D52,'Mail+SDT'!A:A,'Mail+SDT'!C:C)} -> #NAME? | AI52: {=_xludf.XLOOKUP(D52,'ETK 3.2026'!I:I,'ETK 3.2026'!AF:AF)} -> #NAME?
A53: =ROW()-1 -> 52 | B53: Trangnt | C53: Sangpn | D53: chungnv011 | E53: 2983/2024/QĐ-ĐHM | F53: 26/07/2024 | G53: =(YEAR(H53)-YEAR(F53))*12 + MONTH(H53)-MONTH(F53) -> 72 | H53: 26/07/2030 | I53: =IF((H53-TODAY())<=0,"Kết thúc ĐT","Thời gian ĐT còn lại "&(H53-TODAY())&" ngày") -> Thời gian ĐT còn lại 1584 ngày | J53: 24C1002H4349 | K53: Nguyễn Văn Chung | L53: Nguyễn Văn | M53: Chung | N53: 21/08/1993 | O53: Nam | P53: 21 | Q53: CDNVT621 | R53: Công nghệ thông tin | S53: =VLOOKUP(D53, 'Mail+SDT'!A522:C2637, 2, 0) -> 24C1002H4349@students.hou.edu.vn | T53: =VLOOKUP(D53, 'Mail+SDT'!$A$2:$C$2117, 3, 0) -> 975982464 | U53: DNVT | V53: Trường Trung cấp Vạn Tường | W53: CDNVT621 | X53: Công nghệ thông tin | Z53: Trường Trung cấp Vạn Tường | AA53: Trực tuyến | AB53: HT | AC53: HT | AD53: CBKL1 | AG53: {=_xludf.XLOOKUP(D53,'Mail+SDT'!A:A,'Mail+SDT'!B:B)} -> #NAME? | AH53: {=_xludf.XLOOKUP(D53,'Mail+SDT'!A:A,'Mail+SDT'!C:C)} -> #NAME? | AI53: {=_xludf.XLOOKUP(D53,'ETK 3.2026'!I:I,'ETK 3.2026'!AF:AF)} -> #NAME?
A54: =ROW()-1 -> 53 | B54: Trangnt | C54: Sangpn | D54: chuonghk | E54: 1676/2024/QĐ-ĐHM | F54: 03/05/2024 | G54: =(YEAR(H54)-YEAR(F54))*12 + MONTH(H54)-MONTH(F54) -> 72 | H54: 03/05/2030 | I54: =IF((H54-TODAY())<=0,"Kết thúc ĐT","Thời gian ĐT còn lại "&(H54-TODAY())&" ngày") -> Thời gian ĐT còn lại 1500 ngày | J54: 24C1002H2400 | K54: Huỳnh Kim Chương | L54: Huỳnh Kim | M54: Chương | N54: 02/01/1992 | O54: Nam | P54: 21 | Q54: CDNVT621 | R54: Công nghệ thông tin | S54: =VLOOKUP(D54, 'Mail+SDT'!A539:C2654, 2, 0) -> 24C1002H2400@students.hou.edu.vn | T54: =VLOOKUP(D54, 'Mail+SDT'!$A$2:$C$2117, 3, 0) -> 987509209 | U54: DNVT | V54: Trường Trung cấp Vạn Tường | W54: CDNVT621 | X54: Công nghệ thông tin | Z54: Trường Trung cấp Vạn Tường | AA54: Trực tuyến | AB54: HT | AC54: HT | AD54: CBKL1 | AE54: BTH | AF54: Thiếu QT học phí để QR | AG54: {=_xludf.XLOOKUP(D54,'Mail+SDT'!A:A,'Mail+SDT'!B:B)} -> #NAME? | AH54: {=_xludf.XLOOKUP(D54,'Mail+SDT'!A:A,'Mail+SDT'!C:C)} -> #NAME? | AI54: {=_xludf.XLOOKUP(D54,'ETK 3.2026'!I:I,'ETK 3.2026'!AF:AF)} -> #NAME?
A55: =ROW()-1 -> 54 | B55: Trangnt | C55: Sangpn | D55: congnhl | E55: 2501/2024/QĐ-ĐHM | F55: 28/06/2024 | G55: =(YEAR(H55)-YEAR(F55))*12 + MONTH(H55)-MONTH(F55) -> 72 | H55: 28/06/2030 | I55: =IF((H55-TODAY())<=0,"Kết thúc ĐT","Thời gian ĐT còn lại "&(H55-TODAY())&" ngày") -> Thời gian ĐT còn lại 1556 ngày | J55: 24C1002H3644 | K55: Nguyễn Hoàng Lê Công | L55: Nguyễn Hoàng Lê | M55: Công | N55: 29/03/1998 | O55: Nam | P55: 21 | Q55: CDNVT621 | R55: Công nghệ thông tin | S55: =VLOOKUP(D55, 'Mail+SDT'!A521:C2636, 2, 0) -> 24C1002H3644@students.hou.edu.vn | T55: =VLOOKUP(D55, 'Mail+SDT'!$A$2:$C$2117, 3, 0) -> 344291357 | U55: DNVT | V55: Trường Trung cấp Vạn Tường | W55: CDNVT621 | X55: Công nghệ thông tin | Z55: Trường Trung cấp Vạn Tường | AA55: Trực tuyến | AB55: HT | AC55: HT | AD55: HT | AG55: {=_xludf.XLOOKUP(D55,'Mail+SDT'!A:A,'Mail+SDT'!B:B)} -> #NAME? | AH55: {=_xludf.XLOOKUP(D55,'Mail+SDT'!A:A,'Mail+SDT'!C:C)} -> #NAME? | AI55: {=_xludf.XLOOKUP(D55,'ETK 3.2026'!I:I,'ETK 3.2026'!AF:AF)} -> #NAME?
A56: =ROW()-1 -> 55 | B56: Trangnt | C56: Sangpn | D56: cuchtk003 | E56: 2205/2024/QĐ-ĐHM | F56: 07/06/2024 | G56: =(YEAR(H56)-YEAR(F56))*12 + MONTH(H56)-MONTH(F56) -> 72 | H56: 07/06/2030 | I56: =IF((H56-TODAY())<=0,"Kết thúc ĐT","Thời gian ĐT còn lại "&(H56-TODAY())&" ngày") -> Thời gian ĐT còn lại 1535 ngày | J56: 24C4102H3175 | K56: Huỳnh Thị Kim Cúc | L56: Huỳnh Thị Kim | M56: Cúc | N56: 16/07/1982 | O56: Nữ | P56: 21 | Q56: ADNVT421 | R56: Kế toán | S56: =VLOOKUP(D56, 'Mail+SDT'!A349:C2464, 2, 0) -> 24C4102H3175@students.hou.edu.vn | T56: =VLOOKUP(D56, 'Mail+SDT'!$A$2:$C$2117, 3, 0) -> 348084999 | U56: DNVT | V56: Trường Trung cấp Vạn Tường | W56: ADNVT421 | X56: Kế toán | Z56: Trường Trung cấp Vạn Tường | AA56: Trực tuyến | AB56: HT | AC56: HT | AD56: HT | AG56: {=_xludf.XLOOKUP(D56,'Mail+SDT'!A:A,'Mail+SDT'!B:B)} -> #NAME? | AH56: {=_xludf.XLOOKUP(D56,'Mail+SDT'!A:A,'Mail+SDT'!C:C)} -> #NAME? | AI56: {=_xludf.XLOOKUP(D56,'ETK 3.2026'!I:I,'ETK 3.2026'!AF:AF)} -> #NAME?
A57: =ROW()-1 -> 56 | B57: Trangnt | C57: Quynhtnn | D57: cucvtk002 | E57: 2501/2024/QĐ-ĐHM | F57: 28/06/2024 | G57: =(YEAR(H57)-YEAR(F57))*12 + MONTH(H57)-MONTH(F57) -> 72 | H57: 28/06/2030 | I57: =IF((H57-TODAY())<=0,"Kết thúc ĐT","Thời gian ĐT còn lại "&(H57-TODAY())&" ngày") -> Thời gian ĐT còn lại 1556 ngày | J57: 24C4104D3679 | K57: Vũ Thị Kim Cúc | L57: Vũ Thị Kim | M57: Cúc | N57: 10/04/1985 | O57: Nữ | P57: 21 | Q57: ADNP121 | R57: Kế toán | S57: =VLOOKUP(D57, 'Mail+SDT'!A86:C2201, 2, 0) -> 24C4104D3679@students.hou.edu.vn | T57: =VLOOKUP(D57, 'Mail+SDT'!$A$2:$C$2117, 3, 0) -> 905207234 | U57: DNP | V57: Trung tâm Đại học Mở Hà Nội tại Đà Nẵng | W57: ADNP121 | X57: Kế toán | Z57: Trung tâm Đại học Mở Hà Nội tại Đà Nẵng | AA57: Trực tuyến | AB57: HT | AC57: HT | AD57: HT | AG57: {=_xludf.XLOOKUP(D57,'Mail+SDT'!A:A,'Mail+SDT'!B:B)} -> #NAME? | AH57: {=_xludf.XLOOKUP(D57,'Mail+SDT'!A:A,'Mail+SDT'!C:C)} -> #NAME? | AI57: {=_xludf.XLOOKUP(D57,'ETK 3.2026'!I:I,'ETK 3.2026'!AF:AF)} -> #NAME?
A58: =ROW()-1 -> 57 | B58: Trangnt | C58: Sangpn | D58: cuongdh004 | E58: 2118/2022/QĐ-ĐHM | F58: 30/06/2022 | G58: =(YEAR(H58)-YEAR(F58))*12 + MONTH(H58)-MONTH(F58) -> 72 | H58: 30/06/2028 | I58: =IF((H58-TODAY())<=0,"Kết thúc ĐT","Thời gian ĐT còn lại "&(H58-TODAY())&" ngày") -> Thời gian ĐT còn lại 828 ngày | J58: 22C4102H2737 | K58: Đặng Hữu Cường | L58: Đặng Hữu | M58: Cường | N58: 17/12/1992 | O58: Nam | P58: 17 | Q58: ADNVT617 | R58: Kế toán | S58: =VLOOKUP(D58, 'Mail+SDT'!A212:C2327, 2, 0) -> cuongdang@orico.vn | T58: =VLOOKUP(D58, 'Mail+SDT'!$A$2:$C$2117, 3, 0) -> 961445448 | U58: DNVT | V58: Trường Trung cấp Vạn Tường | W58: ADNVT617 | X58: Kế toán | Z58: Trường Trung cấp Vạn Tường | AA58: Trực tuyến | AB58: HT | AC58: HT | AD58: HT | AF58: TN 3.2026 | AG58: {=_xludf.XLOOKUP(D58,'Mail+SDT'!A:A,'Mail+SDT'!B:B)} -> #NAME? | AH58: {=_xludf.XLOOKUP(D58,'Mail+SDT'!A:A,'Mail+SDT'!C:C)} -> #NAME? | AI58: {=_xludf.XLOOKUP(D58,'ETK 3.2026'!I:I,'ETK 3.2026'!AF:AF)} -> #NAME?
A59: =ROW()-1 -> 58 | B59: Trangnt | C59: Sangpn | D59: cuongnm022 | E59: 1676/2024/QĐ-ĐHM | F59: 03/05/2024 | G59: =(YEAR(H59)-YEAR(F59))*12 + MONTH(H59)-MONTH(F59) -> 72 | H59: 03/05/2030 | I59: =IF((H59-TODAY())<=0,"Kết thúc ĐT","Thời gian ĐT còn lại "&(H59-TODAY())&" ngày") -> Thời gian ĐT còn lại 1500 ngày | J59: 24C4202H2419 | K59: Nguyễn Mạnh Cường | L59: Nguyễn Mạnh | M59: Cường | N59: 30/06/1997 | O59: Nam | P59: 21 | Q59: BDNVT321 | R59: Quản trị kinh doanh | S59: =VLOOKUP(D59, 'Mail+SDT'!A390:C2505, 2, 0) -> 24C4202H2419@students.hou.edu.vn | T59: =VLOOKUP(D59, 'Mail+SDT'!$A$2:$C$2117, 3, 0) -> 767157129 | U59: DNVT | V59: Trường Trung cấp Vạn Tường | W59: BDNVT321 | X59: Quản trị kinh doanh | Z59: Trường Trung cấp Vạn Tường | AA59: Trực tuyến | AB59: HT | AC59: HT | AD59: HT | AG59: {=_xludf.XLOOKUP(D59,'Mail+SDT'!A:A,'Mail+SDT'!B:B)} -> #NAME? | AH59: {=_xludf.XLOOKUP(D59,'Mail+SDT'!A:A,'Mail+SDT'!C:C)} -> #NAME? | AI59: {=_xludf.XLOOKUP(D59,'ETK 3.2026'!I:I,'ETK 3.2026'!AF:AF)} -> #NAME?
A60: =ROW()-1 -> 59 | B60: Trangnt | C60: Sangpn | D60: cuongnm024 | E60: 2501/2024/QĐ-ĐHM | F60: 28/06/2024 | G60: =(YEAR(H60)-YEAR(F60))*12 + MONTH(H60)-MONTH(F60) -> 72 | H60: 28/06/2030 | I60: =IF((H60-TODAY())<=0,"Kết thúc ĐT","Thời gian ĐT còn lại "&(H60-TODAY())&" ngày") -> Thời gian ĐT còn lại 1556 ngày | J60: 24C4202H3572 | K60: Nguyễn Mạnh Cường | L60: Nguyễn Mạnh | M60: Cường | N60: 11/05/2003 | O60: Nam | P60: 21 | Q60: BDNVT621 | R60: Quản trị kinh doanh | S60: =VLOOKUP(D60, 'Mail+SDT'!A450:C2565, 2, 0) -> 24C4202H3572@students.hou.edu.vn | T60: =VLOOKUP(D60, 'Mail+SDT'!$A$2:$C$2117, 3, 0) -> 972578491 | U60: DNVT | V60: Trường Trung cấp Vạn Tường | W60: BDNVT621 | X60: Quản trị kinh doanh | Z60: Trường Trung cấp Vạn Tường | AA60: Trực tuyến | AB60: HT | AC60: HT | AD60: HT | AG60: {=_xludf.XLOOKUP(D60,'Mail+SDT'!A:A,'Mail+SDT'!B:B)} -> #NAME? | AH60: {=_xludf.XLOOKUP(D60,'Mail+SDT'!A:A,'Mail+SDT'!C:C)} -> #NAME? | AI60: {=_xludf.XLOOKUP(D60,'ETK 3.2026'!I:I,'ETK 3.2026'!AF:AF)} -> #NAME?
A61: =ROW()-1 -> 60 | B61: Trangnt | C61: Sangpn | D61: cuongnv038 | E61: 839/2024/QĐ-ĐHM | F61: 08/03/2024 | G61: =(YEAR(H61)-YEAR(F61))*12 + MONTH(H61)-MONTH(F61) -> 72 | H61: 08/03/2030 | I61: =IF((H61-TODAY())<=0,"Kết thúc ĐT","Thời gian ĐT còn lại "&(H61-TODAY())&" ngày") -> Thời gian ĐT còn lại 1444 ngày | J61: 24C4502H1027 | K61: Nguyễn Văn Cường | L61: Nguyễn Văn | M61: Cường | N61: 24/08/1993 | O61: Nam | P61: 21 | Q61: DDNVT621 | R61: Tài chính - Ngân hàng | S61: =VLOOKUP(D61, 'Mail+SDT'!A580:C2695, 2, 0) -> 24C4502H1027@students.hou.edu.vn | T61: =VLOOKUP(D61, 'Mail+SDT'!$A$2:$C$2117, 3, 0) -> 981513515 | U61: DNVT | V61: Trường Trung cấp Vạn Tường | W61: DDNVT621 | X61: Tài chính - Ngân hàng | Z61: Trường Trung cấp Vạn Tường | AA61: Trực tuyến | AB61: HT | AC61: HT | AD61: HT | AG61: {=_xludf.XLOOKUP(D61,'Mail+SDT'!A:A,'Mail+SDT'!B:B)} -> #NAME? | AH61: {=_xludf.XLOOKUP(D61,'Mail+SDT'!A:A,'Mail+SDT'!C:C)} -> #NAME? | AI61: {=_xludf.XLOOKUP(D61,'ETK 3.2026'!I:I,'ETK 3.2026'!AF:AF)} -> #NAME?
A62: =ROW()-1 -> 61 | B62: Trangnt | C62: Sangpn | D62: dangpt003 | E62: 2205/2024/QĐ-ĐHM | F62: 07/06/2024 | G62: =(YEAR(H62)-YEAR(F62))*12 + MONTH(H62)-MONTH(F62) -> 72 | H62: 07/06/2030 | I62: =IF((H62-TODAY())<=0,"Kết thúc ĐT","Thời gian ĐT còn lại "&(H62-TODAY())&" ngày") -> Thời gian ĐT còn lại 1535 ngày | J62: 24C1002H3252 | K62: Phạm Tấn Dăng | L62: Phạm Tấn | M62: Dăng | N62: 26/10/1987 | O62: Nam | P62: 21 | Q62: CDNVT621 | R62: Công nghệ thông tin | S62: =VLOOKUP(D62, 'Mail+SDT'!A531:C2646, 2, 0) -> 24C1002H3252@students.hou.edu.vn | T62: =VLOOKUP(D62, 'Mail+SDT'!$A$2:$C$2117, 3, 0) -> 902667048 | U62: DNVT | V62: Trường Trung cấp Vạn Tường | W62: CDNVT621 | X62: Công nghệ thông tin | Z62: Trường Trung cấp Vạn Tường | AA62: Trực tuyến | AB62: HT | AC62: HT | AD62: HT | AG62: {=_xludf.XLOOKUP(D62,'Mail+SDT'!A:A,'Mail+SDT'!B:B)} -> #NAME? | AH62: {=_xludf.XLOOKUP(D62,'Mail+SDT'!A:A,'Mail+SDT'!C:C)} -> #NAME? | AI62: {=_xludf.XLOOKUP(D62,'ETK 3.2026'!I:I,'ETK 3.2026'!AF:AF)} -> #NAME?
A63: =ROW()-1 -> 62 | B63: Trangnt | C63: Sangpn | D63: danhh | E63: 2118/2022/QĐ-ĐHM | F63: 30/06/2022 | G63: =(YEAR(H63)-YEAR(F63))*12 + MONTH(H63)-MONTH(F63) -> 72 | H63: 30/06/2028 | I63: =IF((H63-TODAY())<=0,"Kết thúc ĐT","Thời gian ĐT còn lại "&(H63-TODAY())&" ngày") -> Thời gian ĐT còn lại 828 ngày | J63: 22C4202H2752 | K63: Huỳnh Hương Dân | L63: Huỳnh Hương | M63: Dân | N63: 20/04/1992 | O63: Nữ | P63: 17 | Q63: BDNVT617 | R63: Quản trị kinh doanh | S63: =VLOOKUP(D63, 'Mail+SDT'!A239:C2354, 2, 0) -> bao.huynhho7272@yahoo.com.vn | T63: =VLOOKUP(D63, 'Mail+SDT'!$A$2:$C$2117, 3, 0) -> 907635384 | U63: DNVT | V63: Trường Trung cấp Vạn Tường | W63: BDNVT517 | X63: Quản trị kinh doanh | Z63: Trường Trung cấp Vạn Tường | AA63: Trực tuyến | AB63: HT | AC63: HT | AD63: BL | AG63: {=_xludf.XLOOKUP(D63,'Mail+SDT'!A:A,'Mail+SDT'!B:B)} -> #NAME? | AH63: {=_xludf.XLOOKUP(D63,'Mail+SDT'!A:A,'Mail+SDT'!C:C)} -> #NAME? | AI63: {=_xludf.XLOOKUP(D63,'ETK 3.2026'!I:I,'ETK 3.2026'!AF:AF)} -> #NAME?
A64: =ROW()-1 -> 63 | B64: Trangnt | C64: Sangpn | D64: danhnt006 | E64: 839/2024/QĐ-ĐHM | F64: 08/03/2024 | G64: =(YEAR(H64)-YEAR(F64))*12 + MONTH(H64)-MONTH(F64) -> 72 | H64: 08/03/2030 | I64: =IF((H64-TODAY())<=0,"Kết thúc ĐT","Thời gian ĐT còn lại "&(H64-TODAY())&" ngày") -> Thời gian ĐT còn lại 1444 ngày | J64: 24C4502H1023 | K64: Nguyễn Thành Danh | L64: Nguyễn Thành | M64: Danh | N64: 18/01/2000 | O64: Nam | P64: 21 | Q64: DDNVT621 | R64: Tài chính - Ngân hàng | S64: =VLOOKUP(D64, 'Mail+SDT'!A577:C2692, 2, 0) -> 24C4502H1023@students.hou.edu.vn | T64: =VLOOKUP(D64, 'Mail+SDT'!$A$2:$C$2117, 3, 0) -> 941365473 | U64: DNVT | V64: Trường Trung cấp Vạn Tường | W64: DDNVT621 | X64: Tài chính - Ngân hàng | Z64: Trường Trung cấp Vạn Tường | AA64: Trực tuyến | AB64: HT | AC64: HT | AD64: HT | AG64: {=_xludf.XLOOKUP(D64,'Mail+SDT'!A:A,'Mail+SDT'!B:B)} -> #NAME? | AH64: {=_xludf.XLOOKUP(D64,'Mail+SDT'!A:A,'Mail+SDT'!C:C)} -> #NAME? | AI64: {=_xludf.XLOOKUP(D64,'ETK 3.2026'!I:I,'ETK 3.2026'!AF:AF)} -> #NAME?
A65: =ROW()-1 -> 64 | B65: Trangnt | C65: Quynhtnn | D65: danht | E65: 2070/2022/QĐ-ĐHM | F65: 27/06/2022 | G65: =(YEAR(H65)-YEAR(F65))*12 + MONTH(H65)-MONTH(F65) -> 72 | H65: 27/06/2028 | I65: =IF((H65-TODAY())<=0,"Kết thúc ĐT","Thời gian ĐT còn lại "&(H65-TODAY())&" ngày") -> Thời gian ĐT còn lại 825 ngày | J65: 22C4104D2637 | K65: Hồ Thị Đan | L65: Hồ Thị | M65: Đan | N65: 06/12/1982 | O65: Nữ | P65: 17 | Q65: ADNP517 | R65: Kế toán | S65: =VLOOKUP(D65, 'Mail+SDT'!A26:C2141, 2, 0) -> hothidan1982danang@gmail.com | T65: =VLOOKUP(D65, 'Mail+SDT'!$A$2:$C$2117, 3, 0) -> 913691023 | U65: DNP | V65: Trung tâm Đại học Mở Hà Nội tại Đà Nẵng | W65: ADNP517 | X65: Kế toán | Z65: Trung tâm Đại học Mở Hà Nội tại Đà Nẵng | AA65: Trực tuyến | AB65: HT | AC65: HT | AD65: HTCT | AG65: {=_xludf.XLOOKUP(D65,'Mail+SDT'!A:A,'Mail+SDT'!B:B)} -> #NAME? | AH65: {=_xludf.XLOOKUP(D65,'Mail+SDT'!A:A,'Mail+SDT'!C:C)} -> #NAME? | AI65: {=_xludf.XLOOKUP(D65,'ETK 3.2026'!I:I,'ETK 3.2026'!AF:AF)} -> #NAME?
A66: =ROW()-1 -> 65 | B66: Trangnt | C66: Sangpn | D66: danpt002 | E66: 839/2024/QĐ-ĐHM | F66: 08/03/2024 | G66: =(YEAR(H66)-YEAR(F66))*12 + MONTH(H66)-MONTH(F66) -> 72 | H66: 08/03/2030 | I66: =IF((H66-TODAY())<=0,"Kết thúc ĐT","Thời gian ĐT còn lại "&(H66-TODAY())&" ngày") -> Thời gian ĐT còn lại 1444 ngày | J66: 24C4202H1017 | K66: Phạm Trúc Đan | L66: Phạm Trúc | M66: Đan | N66: 04/07/2005 | O66: Nữ | P66: 21 | Q66: BDNVT621 | R66: Quản trị kinh doanh | S66: =VLOOKUP(D66, 'Mail+SDT'!A488:C2603, 2, 0) -> 24C4202H1017@students.hou.edu.vn | T66: =VLOOKUP(D66, 'Mail+SDT'!$A$2:$C$2117, 3, 0) -> 982761411 | U66: DNVT | V66: Trường Trung cấp Vạn Tường | W66: BDNVT621 | X66: Quản trị kinh doanh | Z66: Trường Trung cấp Vạn Tường | AA66: Trực tuyến | AB66: HT | AC66: HT | AD66: HT | AG66: {=_xludf.XLOOKUP(D66,'Mail+SDT'!A:A,'Mail+SDT'!B:B)} -> #NAME? | AH66: {=_xludf.XLOOKUP(D66,'Mail+SDT'!A:A,'Mail+SDT'!C:C)} -> #NAME? | AI66: {=_xludf.XLOOKUP(D66,'ETK 3.2026'!I:I,'ETK 3.2026'!AF:AF)} -> #NAME?
A67: =ROW()-1 -> 66 | B67: Trangnt | C67: Sangpn | D67: danva002 | E67: 2081/2024/QĐ-ĐHM | F67: 31/05/2024 | G67: =(YEAR(H67)-YEAR(F67))*12 + MONTH(H67)-MONTH(F67) -> 72 | H67: 31/05/2030 | I67: =IF((H67-TODAY())<=0,"Kết thúc ĐT","Thời gian ĐT còn lại "&(H67-TODAY())&" ngày") -> Thời gian ĐT còn lại 1528 ngày | J67: 24C4501S3071 | K67: Vũ Anh Dân | L67: Vũ Anh | M67: Dân | N67: 10/07/1996 | O67: Nam | P67: 21 | Q67: DDNVT521 | R67: Tài chính - Ngân hàng | S67: =VLOOKUP(D67, 'Mail+SDT'!A571:C2686, 2, 0) -> 24C4501S3071@students.hou.edu.vn | T67: =VLOOKUP(D67, 'Mail+SDT'!$A$2:$C$2117, 3, 0) -> 965167635 | U67: DNVT | V67: Trường Trung cấp Vạn Tường | W67: DDNVT521 | X67: Tài chính - Ngân hàng | Z67: Trường Trung cấp Vạn Tường | AA67: Trực tuyến | AB67: HT | AC67: CL | AD67: HT | AG67: {=_xludf.XLOOKUP(D67,'Mail+SDT'!A:A,'Mail+SDT'!B:B)} -> #NAME? | AH67: {=_xludf.XLOOKUP(D67,'Mail+SDT'!A:A,'Mail+SDT'!C:C)} -> #NAME? | AI67: {=_xludf.XLOOKUP(D67,'ETK 3.2026'!I:I,'ETK 3.2026'!AF:AF)} -> #NAME?
A68: =ROW()-1 -> 67 | B68: Trangnt | C68: Sangpn | D68: daodth002 | E68: 1492/2022/QĐ-ĐHM | F68: 17/05/2022 | G68: =(YEAR(H68)-YEAR(F68))*12 + MONTH(H68)-MONTH(F68) -> 72 | H68: 17/05/2028 | I68: =IF((H68-TODAY())<=0,"Kết thúc ĐT","Thời gian ĐT còn lại "&(H68-TODAY())&" ngày") -> Thời gian ĐT còn lại 784 ngày | J68: 22C7102H1804 | K68: Đàm Thị Hồng Đào | L68: Đàm Thị Hồng | M68: Đào | N68: 07/10/1990 | O68: Nữ | P68: 17 | Q68: FDNVT617 | R68: Ngôn ngữ Anh | S68: =VLOOKUP(D68, 'Mail+SDT'!A313:C2428, 2, 0) -> damhongdao1990@gmail.com | T68: =VLOOKUP(D68, 'Mail+SDT'!$A$2:$C$2117, 3, 0) -> 935802080 | U68: DNVT | V68: Trường Trung cấp Vạn Tường | W68: FDNVT617 | X68: Ngôn ngữ Anh | Z68: Trường Trung cấp Vạn Tường | AA68: Trực tuyến | AB68: HT | AC68: HT | AD68: HT | AF68: TN 3.2026 | AG68: {=_xludf.XLOOKUP(D68,'Mail+SDT'!A:A,'Mail+SDT'!B:B)} -> #NAME? | AH68: {=_xludf.XLOOKUP(D68,'Mail+SDT'!A:A,'Mail+SDT'!C:C)} -> #NAME? | AI68: {=_xludf.XLOOKUP(D68,'ETK 3.2026'!I:I,'ETK 3.2026'!AF:AF)} -> #NAME?
A69: =ROW()-1 -> 68 | B69: Trangnt | C69: Sangpn | D69: daopt002 | E69: 2205/2024/QĐ-ĐHM | F69: 07/06/2024 | G69: =(YEAR(H69)-YEAR(F69))*12 + MONTH(H69)-MONTH(F69) -> 72 | H69: 07/06/2030 | I69: =IF((H69-TODAY())<=0,"Kết thúc ĐT","Thời gian ĐT còn lại "&(H69-TODAY())&" ngày") -> Thời gian ĐT còn lại 1535 ngày | J69: 24C4102H3177 | K69: Phạm Thị Đào | L69: Phạm Thị | M69: Đào | N69: 19/04/1985 | O69: Nữ | P69: 21 | Q69: ADNVT621 | R69: Kế toán | S69: =VLOOKUP(D69, 'Mail+SDT'!A375:C2490, 2, 0) -> 24C4102H3177@students.hou.edu.vn | T69: =VLOOKUP(D69, 'Mail+SDT'!$A$2:$C$2117, 3, 0) -> 968965424 | U69: DNVT | V69: Trường Trung cấp Vạn Tường | W69: ADNVT621 | X69: Kế toán | Z69: Trường Trung cấp Vạn Tường | AA69: Trực tuyến | AB69: HT | AC69: HT | AD69: HT | AG69: {=_xludf.XLOOKUP(D69,'Mail+SDT'!A:A,'Mail+SDT'!B:B)} -> #NAME? | AH69: {=_xludf.XLOOKUP(D69,'Mail+SDT'!A:A,'Mail+SDT'!C:C)} -> #NAME? | AI69: {=_xludf.XLOOKUP(D69,'ETK 3.2026'!I:I,'ETK 3.2026'!AF:AF)} -> #NAME?
A70: =ROW()-1 -> 69 | B70: Trangnt | C70: Sangpn | D70: datcv002 | E70: 2661/2024/QĐ-ĐHM | F70: 02/07/2024 | G70: =(YEAR(H70)-YEAR(F70))*12 + MONTH(H70)-MONTH(F70) -> 72 | H70: 02/07/2030 | I70: =IF((H70-TODAY())<=0,"Kết thúc ĐT","Thời gian ĐT còn lại "&(H70-TODAY())&" ngày") -> Thời gian ĐT còn lại 1560 ngày | J70: 24C4502H4037 | K70: Cù Văn Đạt | L70: Cù Văn | M70: Đạt | N70: 04/02/1998 | O70: Nam | P70: 21 | Q70: DDNVT621 | R70: Tài chính - Ngân hàng | S70: =VLOOKUP(D70, 'Mail+SDT'!A574:C2689, 2, 0) -> 24C4502H4037@students.hou.edu.vn | T70: =VLOOKUP(D70, 'Mail+SDT'!$A$2:$C$2117, 3, 0) -> 362879878 | U70: DNVT | V70: Trường Trung cấp Vạn Tường | W70: DDNVT621 | X70: Tài chính - Ngân hàng | Z70: Trường Trung cấp Vạn Tường | AA70: Trực tuyến | AB70: HT | AC70: HT | AD70: HT | AG70: {=_xludf.XLOOKUP(D70,'Mail+SDT'!A:A,'Mail+SDT'!B:B)} -> #NAME? | AH70: {=_xludf.XLOOKUP(D70,'Mail+SDT'!A:A,'Mail+SDT'!C:C)} -> #NAME? | AI70: {=_xludf.XLOOKUP(D70,'ETK 3.2026'!I:I,'ETK 3.2026'!AF:AF)} -> #NAME?
A71: =ROW()-1 -> 70 | B71: Trangnt | C71: Sangpn | D71: datdt012 | E71: 1301/2024/QĐ-ĐHM | F71: 05/04/2024 | G71: =(YEAR(H71)-YEAR(F71))*12 + MONTH(H71)-MONTH(F71) -> 72 | H71: 05/04/2030 | I71: =IF((H71-TODAY())<=0,"Kết thúc ĐT","Thời gian ĐT còn lại "&(H71-TODAY())&" ngày") -> Thời gian ĐT còn lại 1472 ngày | J71: 24C4202H1688 | K71: Đào Tấn Đạt | L71: Đào Tấn | M71: Đạt | N71: 16/11/1998 | O71: Nam | P71: 21 | Q71: BDNVT621 | R71: Quản trị kinh doanh | S71: =VLOOKUP(D71, 'Mail+SDT'!A474:C2589, 2, 0) -> 24C4202H1688@students.hou.edu.vn | T71: =VLOOKUP(D71, 'Mail+SDT'!$A$2:$C$2117, 3, 0) -> 901161198 | U71: DNVT | V71: Trường Trung cấp Vạn Tường | W71: BDNVT621 | X71: Quản trị kinh doanh | Z71: Trường Trung cấp Vạn Tường | AA71: Trực tuyến | AB71: HT | AC71: HT | AD71: HT | AG71: {=_xludf.XLOOKUP(D71,'Mail+SDT'!A:A,'Mail+SDT'!B:B)} -> #NAME? | AH71: {=_xludf.XLOOKUP(D71,'Mail+SDT'!A:A,'Mail+SDT'!C:C)} -> #NAME? | AI71: {=_xludf.XLOOKUP(D71,'ETK 3.2026'!I:I,'ETK 3.2026'!AF:AF)} -> #NAME?
A72: =ROW()-1 -> 71 | B72: Trangnt | C72: Quynhtnn | D72: datnc004 | E72: 1379/2024/QĐ-ĐHM | F72: 12/04/2024 | G72: =(YEAR(H72)-YEAR(F72))*12 + MONTH(H72)-MONTH(F72) -> 72 | H72: 12/04/2030 | I72: =IF((H72-TODAY())<=0,"Kết thúc ĐT","Thời gian ĐT còn lại "&(H72-TODAY())&" ngày") -> Thời gian ĐT còn lại 1479 ngày | J72: 24C4204D1890 | K72: Nguyễn Công Đạt | L72: Nguyễn Công | M72: Đạt | N72: 09/03/2003 | O72: Nam | P72: 21 | Q72: BDNP521 | R72: Quản trị kinh doanh | S72: =VLOOKUP(D72, 'Mail+SDT'!A133:C2248, 2, 0) -> 24C4204D1890@students.hou.edu.vn | T72: =VLOOKUP(D72, 'Mail+SDT'!$A$2:$C$2117, 3, 0) -> 344839255 | U72: DNP | V72: Trung tâm Đại học Mở Hà Nội tại Đà Nẵng | W72: BDNP521 | X72: Quản trị kinh doanh | Z72: Trung tâm Đại học Mở Hà Nội tại Đà Nẵng | AA72: Trực tuyến | AB72: HT | AC72: HT | AD72: HT | AG72: {=_xludf.XLOOKUP(D72,'Mail+SDT'!A:A,'Mail+SDT'!B:B)} -> #NAME? | AH72: {=_xludf.XLOOKUP(D72,'Mail+SDT'!A:A,'Mail+SDT'!C:C)} -> #NAME? | AI72: {=_xludf.XLOOKUP(D72,'ETK 3.2026'!I:I,'ETK 3.2026'!AF:AF)} -> #NAME?
A73: =ROW()-1 -> 72 | B73: Trangnt | C73: Sangpn | D73: datnv014 | E73: 839/2024/QĐ-ĐHM | F73: 08/03/2024 | G73: =(YEAR(H73)-YEAR(F73))*12 + MONTH(H73)-MONTH(F73) -> 72 | H73: 08/03/2030 | I73: =IF((H73-TODAY())<=0,"Kết thúc ĐT","Thời gian ĐT còn lại "&(H73-TODAY())&" ngày") -> Thời gian ĐT còn lại 1444 ngày | J73: 24C4202H1011 | K73: Nguyễn Văn Đạt | L73: Nguyễn Văn | M73: Đạt | N73: 17/07/1996 | O73: Nam | P73: 21 | Q73: BDNVT621 | R73: Quản trị kinh doanh | S73: =VLOOKUP(D73, 'Mail+SDT'!A433:C2548, 2, 0) -> 24C4202H1011@students.hou.edu.vn | T73: =VLOOKUP(D73, 'Mail+SDT'!$A$2:$C$2117, 3, 0) -> 328651188 | U73: DNVT | V73: Trường Trung cấp Vạn Tường | W73: BDNVT621 | X73: Quản trị kinh doanh | Z73: Trường Trung cấp Vạn Tường | AA73: Trực tuyến | AB73: HT | AC73: HT | AD73: HT | AG73: {=_xludf.XLOOKUP(D73,'Mail+SDT'!A:A,'Mail+SDT'!B:B)} -> #NAME? | AH73: {=_xludf.XLOOKUP(D73,'Mail+SDT'!A:A,'Mail+SDT'!C:C)} -> #NAME? | AI73: {=_xludf.XLOOKUP(D73,'ETK 3.2026'!I:I,'ETK 3.2026'!AF:AF)} -> #NAME?
A74: =ROW()-1 -> 73 | B74: Trangnt | C74: Sangpn | D74: diemntn002 | E74: 2118/2022/QĐ-ĐHM | F74: 30/06/2022 | G74: =(YEAR(H74)-YEAR(F74))*12 + MONTH(H74)-MONTH(F74) -> 72 | H74: 30/06/2028 | I74: =IF((H74-TODAY())<=0,"Kết thúc ĐT","Thời gian ĐT còn lại "&(H74-TODAY())&" ngày") -> Thời gian ĐT còn lại 828 ngày | J74: 22C7102H2788 | K74: Nguyễn Thị Ngọc Diễm | L74: Nguyễn Thị Ngọc | M74: Diễm | N74: 14/01/1982 | O74: Nữ | P74: 17 | Q74: FDNVT217 | R74: Ngôn ngữ Anh | S74: =VLOOKUP(D74, 'Mail+SDT'!A278:C2393, 2, 0) -> csdiemnguyen@gmail.com | T74: =VLOOKUP(D74, 'Mail+SDT'!$A$2:$C$2117, 3, 0) -> 983880196 | U74: DNVT | V74: Trường Trung cấp Vạn Tường | W74: FDNVT217 | X74: Ngôn ngữ Anh | Z74: Trường Trung cấp Vạn Tường | AA74: Trực tuyến | AB74: HT | AC74: HT | AD74: HT | AG74: {=_xludf.XLOOKUP(D74,'Mail+SDT'!A:A,'Mail+SDT'!B:B)} -> #NAME? | AH74: {=_xludf.XLOOKUP(D74,'Mail+SDT'!A:A,'Mail+SDT'!C:C)} -> #NAME? | AI74: {=_xludf.XLOOKUP(D74,'ETK 3.2026'!I:I,'ETK 3.2026'!AF:AF)} -> #NAME?
A75: =ROW()-1 -> 74 | B75: Trangnt | C75: Sangpn | D75: diepnt008 | E75: 839/2024/QĐ-ĐHM | F75: 08/03/2024 | G75: =(YEAR(H75)-YEAR(F75))*12 + MONTH(H75)-MONTH(F75) -> 72 | H75: 08/03/2030 | I75: =IF((H75-TODAY())<=0,"Kết thúc ĐT","Thời gian ĐT còn lại "&(H75-TODAY())&" ngày") -> Thời gian ĐT còn lại 1444 ngày | J75: 24C4202H1015 | K75: Nguyễn Thanh Điệp | L75: Nguyễn Thanh | M75: Điệp | N75: 11/04/1991 | O75: Nam | P75: 21 | Q75: BDNVT621 | R75: Quản trị kinh doanh | S75: =VLOOKUP(D75, 'Mail+SDT'!A483:C2598, 2, 0) -> 24C4202H1015@students.hou.edu.vn | T75: =VLOOKUP(D75, 'Mail+SDT'!$A$2:$C$2117, 3, 0) -> 784868109 | U75: DNVT | V75: Trường Trung cấp Vạn Tường | W75: BDNVT621 | X75: Quản trị kinh doanh | Z75: Trường Trung cấp Vạn Tường | AA75: Trực tuyến | AB75: HT | AC75: HT | AD75: HT | AG75: {=_xludf.XLOOKUP(D75,'Mail+SDT'!A:A,'Mail+SDT'!B:B)} -> #NAME? | AH75: {=_xludf.XLOOKUP(D75,'Mail+SDT'!A:A,'Mail+SDT'!C:C)} -> #NAME? | AI75: {=_xludf.XLOOKUP(D75,'ETK 3.2026'!I:I,'ETK 3.2026'!AF:AF)} -> #NAME?
A76: =ROW()-1 -> 75 | B76: Trangnt | C76: Sangpn | D76: dieuvt003 | E76: 839/2024/QĐ-ĐHM | F76: 08/03/2024 | G76: =(YEAR(H76)-YEAR(F76))*12 + MONTH(H76)-MONTH(F76) -> 72 | H76: 08/03/2030 | I76: =IF((H76-TODAY())<=0,"Kết thúc ĐT","Thời gian ĐT còn lại "&(H76-TODAY())&" ngày") -> Thời gian ĐT còn lại 1444 ngày | J76: 24C4102H1004 | K76: Văn Thị Diệu | L76: Văn Thị | M76: Diệu | N76: 01/04/1982 | O76: Nữ | P76: 21 | Q76: ADNVT621 | R76: Kế toán | S76: =VLOOKUP(D76, 'Mail+SDT'!A360:C2475, 2, 0) -> 24C4102H1004@students.hou.edu.vn | T76: =VLOOKUP(D76, 'Mail+SDT'!$A$2:$C$2117, 3, 0) -> 975178044 | U76: DNVT | V76: Trường Trung cấp Vạn Tường | W76: ADNVT621 | X76: Kế toán | Z76: Trường Trung cấp Vạn Tường | AA76: Trực tuyến | AB76: HT | AC76: HT | AD76: CBKL1 | AE76: BTH | AF76: Thiếu QT học phí để QR | AG76: {=_xludf.XLOOKUP(D76,'Mail+SDT'!A:A,'Mail+SDT'!B:B)} -> #NAME? | AH76: {=_xludf.XLOOKUP(D76,'Mail+SDT'!A:A,'Mail+SDT'!C:C)} -> #NAME? | AI76: {=_xludf.XLOOKUP(D76,'ETK 3.2026'!I:I,'ETK 3.2026'!AF:AF)} -> #NAME?
A77: =ROW()-1 -> 76 | B77: Trangnt | C77: Sangpn | D77: dieuvtt | E77: 2205/2024/QĐ-ĐHM | F77: 07/06/2024 | G77: =(YEAR(H77)-YEAR(F77))*12 + MONTH(H77)-MONTH(F77) -> 72 | H77: 07/06/2030 | I77: =IF((H77-TODAY())<=0,"Kết thúc ĐT","Thời gian ĐT còn lại "&(H77-TODAY())&" ngày") -> Thời gian ĐT còn lại 1535 ngày | J77: 24C4102H3172 | K77: Võ Thị Thúy Diệu | L77: Võ Thị Thúy | M77: Diệu | N77: 19/11/1992 | O77: Nữ | P77: 21 | Q77: ADNVT621 | R77: Kế toán | S77: =VLOOKUP(D77, 'Mail+SDT'!A385:C2500, 2, 0) -> 24C4102H3172@students.hou.edu.vn | T77: =VLOOKUP(D77, 'Mail+SDT'!$A$2:$C$2117, 3, 0) -> 975045399 | U77: DNVT | V77: Trường Trung cấp Vạn Tường | W77: ADNVT621 | X77: Kế toán | Z77: Trường Trung cấp Vạn Tường | AA77: Trực tuyến | AB77: HT | AC77: HT | AD77: CBKL1 | AE77: BTH | AF77: Thiếu QT học phí để QR | AG77: {=_xludf.XLOOKUP(D77,'Mail+SDT'!A:A,'Mail+SDT'!B:B)} -> #NAME? | AH77: {=_xludf.XLOOKUP(D77,'Mail+SDT'!A:A,'Mail+SDT'!C:C)} -> #NAME? | AI77: {=_xludf.XLOOKUP(D77,'ETK 3.2026'!I:I,'ETK 3.2026'!AF:AF)} -> #NAME?
A78: =ROW()-1 -> 77 | B78: Trangnt | C78: Sangpn | D78: dihd | E78: 2118/2022/QĐ-ĐHM | F78: 30/06/2022 | G78: =(YEAR(H78)-YEAR(F78))*12 + MONTH(H78)-MONTH(F78) -> 72 | H78: 30/06/2028 | I78: =IF((H78-TODAY())<=0,"Kết thúc ĐT","Thời gian ĐT còn lại "&(H78-TODAY())&" ngày") -> Thời gian ĐT còn lại 828 ngày | J78: 22C4202H2766 | K78: Hồ Đình Di | L78: Hồ Đình | M78: Di | N78: 09/07/1995 | O78: Nam | P78: 17 | Q78: EDNVT617 | R78: Luật kinh tế | S78: =VLOOKUP(D78, 'Mail+SDT'!A221:C2336, 2, 0) -> di.hodinh@gmail.com | T78: =VLOOKUP(D78, 'Mail+SDT'!$A$2:$C$2117, 3, 0) -> 984919178 | U78: DNVT | V78: Trường Trung cấp Vạn Tường | W78: EDNVT617 | X78: Luật kinh tế | Z78: Trường Trung cấp Vạn Tường | AA78: Trực tuyến | AB78: HT | AC78: HT | AD78: HT | AG78: {=_xludf.XLOOKUP(D78,'Mail+SDT'!A:A,'Mail+SDT'!B:B)} -> #NAME? | AH78: {=_xludf.XLOOKUP(D78,'Mail+SDT'!A:A,'Mail+SDT'!C:C)} -> #NAME? | AI78: {=_xludf.XLOOKUP(D78,'ETK 3.2026'!I:I,'ETK 3.2026'!Z:Z)} -> #NAME?
A79: =ROW()-1 -> 78 | B79: Trangnt | C79: Sangpn | D79: dinhtn | E79: 2118/2022/QĐ-ĐHM | F79: 30/06/2022 | G79: =(YEAR(H79)-YEAR(F79))*12 + MONTH(H79)-MONTH(F79) -> 72 | H79: 30/06/2028 | I79: =IF((H79-TODAY())<=0,"Kết thúc ĐT","Thời gian ĐT còn lại "&(H79-TODAY())&" ngày") -> Thời gian ĐT còn lại 828 ngày | J79: 22C5102H2842 | K79: Từ Ngọc Đình | L79: Từ Ngọc | M79: Đình | N79: 18/07/1995 | O79: Nữ | P79: 17 | Q79: EDNVT417 | R79: Luật kinh tế | S79: =VLOOKUP(D79, 'Mail+SDT'!A267:C2382, 2, 0) -> tsuiyukying888@gmail.com | T79: =VLOOKUP(D79, 'Mail+SDT'!$A$2:$C$2117, 3, 0) -> 866113730 | U79: DNVT | V79: Trường Trung cấp Vạn Tường | W79: EDNVT417 | X79: Luật kinh tế | Z79: Trường Trung cấp Vạn Tường | AA79: Trực tuyến | AB79: HT | AC79: HT | AD79: HT | AG79: {=_xludf.XLOOKUP(D79,'Mail+SDT'!A:A,'Mail+SDT'!B:B)} -> #NAME? | AH79: {=_xludf.XLOOKUP(D79,'Mail+SDT'!A:A,'Mail+SDT'!C:C)} -> #NAME? | AI79: {=_xludf.XLOOKUP(D79,'ETK 3.2026'!I:I,'ETK 3.2026'!AF:AF)} -> #NAME?
A80: =ROW()-1 -> 79 | B80: Trangnt | C80: Sangpn | D80: donglv002 | E80: 2118/2022/QĐ-ĐHM | F80: 30/06/2022 | G80: =(YEAR(H80)-YEAR(F80))*12 + MONTH(H80)-MONTH(F80) -> 72 | H80: 30/06/2028 | I80: =IF((H80-TODAY())<=0,"Kết thúc ĐT","Thời gian ĐT còn lại "&(H80-TODAY())&" ngày") -> Thời gian ĐT còn lại 828 ngày | J80: 22C4202H2756 | K80: Lý Văn Đông | L80: Lý Văn | M80: Đông | N80: 05/07/1996 | O80: Nam | P80: 17 | Q80: BDNVT617 | R80: Quản trị kinh doanh | S80: =VLOOKUP(D80, 'Mail+SDT'!A230:C2345, 2, 0) -> vandonghdu@gmail.com | T80: =VLOOKUP(D80, 'Mail+SDT'!$A$2:$C$2117, 3, 0) -> 352521032 | U80: DNVT | V80: Trường Trung cấp Vạn Tường | W80: BDNVT617 | X80: Quản trị kinh doanh | Z80: Trường Trung cấp Vạn Tường | AA80: Trực tuyến | AB80: HT | AC80: HT | AD80: HT | AF80: TN 3.2026 | AG80: {=_xludf.XLOOKUP(D80,'Mail+SDT'!A:A,'Mail+SDT'!B:B)} -> #NAME? | AH80: {=_xludf.XLOOKUP(D80,'Mail+SDT'!A:A,'Mail+SDT'!C:C)} -> #NAME? | AI80: {=_xludf.XLOOKUP(D80,'ETK 3.2026'!I:I,'ETK 3.2026'!AF:AF)} -> #NAME?
A81: =ROW()-1 -> 80 | B81: Trangnt | C81: Sangpn | D81: donnt | E81: 1301/2024/QĐ-ĐHM | F81: 05/04/2024 | G81: =(YEAR(H81)-YEAR(F81))*12 + MONTH(H81)-MONTH(F81) -> 72 | H81: 05/04/2030 | I81: =IF((H81-TODAY())<=0,"Kết thúc ĐT","Thời gian ĐT còn lại "&(H81-TODAY())&" ngày") -> Thời gian ĐT còn lại 1472 ngày | J81: 24C1002H1676 | K81: Nguyễn Thành Đôn | L81: Nguyễn Thành | M81: Đôn | N81: 14/06/2003 | O81: Nam | P81: 21 | Q81: CDNVT621 | R81: Công nghệ thông tin | S81: =VLOOKUP(D81, 'Mail+SDT'!A543:C2658, 2, 0) -> 24C1002H1676@students.hou.edu.vn | T81: =VLOOKUP(D81, 'Mail+SDT'!$A$2:$C$2117, 3, 0) -> 774581363 | U81: DNVT | V81: Trường Trung cấp Vạn Tường | W81: CDNVT621 | X81: Công nghệ thông tin | Z81: Trường Trung cấp Vạn Tường | AA81: Trực tuyến | AB81: HT | AC81: HT | AD81: CBKL1 | AE81: BTH | AF81: Thiếu QT học phí để QR | AG81: {=_xludf.XLOOKUP(D81,'Mail+SDT'!A:A,'Mail+SDT'!B:B)} -> #NAME? | AH81: {=_xludf.XLOOKUP(D81,'Mail+SDT'!A:A,'Mail+SDT'!C:C)} -> #NAME? | AI81: {=_xludf.XLOOKUP(D81,'ETK 3.2026'!I:I,'ETK 3.2026'!AF:AF)} -> #NAME?
A82: =ROW()-1 -> 81 | B82: Trangnt | C82: Quynhtnn | D82: ducmd | E82: 2661/2024/QĐ-ĐHM | F82: 02/07/2024 | G82: =(YEAR(H82)-YEAR(F82))*12 + MONTH(H82)-MONTH(F82) -> 72 | H82: 02/07/2030 | I82: =IF((H82-TODAY())<=0,"Kết thúc ĐT","Thời gian ĐT còn lại "&(H82-TODAY())&" ngày") -> Thời gian ĐT còn lại 1560 ngày | J82: 24C4204D4047 | K82: Mai Đình Đức | L82: Mai Đình | M82: Đức | N82: 08/09/1994 | O82: Nam | P82: 21 | Q82: BDNP621 | R82: Quản trị kinh doanh | S82: =VLOOKUP(D82, 'Mail+SDT'!A149:C2264, 2, 0) -> 24C4204D4047@students.hou.edu.vn | T82: =VLOOKUP(D82, 'Mail+SDT'!$A$2:$C$2117, 3, 0) -> 842653456 | U82: DNP | V82: Trung tâm Đại học Mở Hà Nội tại Đà Nẵng | W82: BDNP621 | X82: Quản trị kinh doanh | Z82: Trung tâm Đại học Mở Hà Nội tại Đà Nẵng | AA82: Trực tuyến | AB82: HT | AC82: HT | AD82: HT | AG82: {=_xludf.XLOOKUP(D82,'Mail+SDT'!A:A,'Mail+SDT'!B:B)} -> #NAME? | AH82: {=_xludf.XLOOKUP(D82,'Mail+SDT'!A:A,'Mail+SDT'!C:C)} -> #NAME? | AI82: {=_xludf.XLOOKUP(D82,'ETK 3.2026'!I:I,'ETK 3.2026'!AF:AF)} -> #NAME?
A83: =ROW()-1 -> 82 | B83: Trangnt | C83: Sangpn | D83: ducnq002 | E83: 839/2024/QĐ-ĐHM | F83: 08/03/2024 | G83: =(YEAR(H83)-YEAR(F83))*12 + MONTH(H83)-MONTH(F83) -> 72 | H83: 08/03/2030 | I83: =IF((H83-TODAY())<=0,"Kết thúc ĐT","Thời gian ĐT còn lại "&(H83-TODAY())&" ngày") -> Thời gian ĐT còn lại 1444 ngày | J83: 24C4202H1009 | K83: Nguyễn Quang Đức | L83: Nguyễn Quang | M83: Đức | N83: 18/12/1998 | O83: Nam | P83: 21 | Q83: BDNVT621 | R83: Quản trị kinh doanh | S83: =VLOOKUP(D83, 'Mail+SDT'!A476:C2591, 2, 0) -> 24C4202H1009@students.hou.edu.vn | T83: =VLOOKUP(D83, 'Mail+SDT'!$A$2:$C$2117, 3, 0) -> 949491298 | U83: DNVT | V83: Trường Trung cấp Vạn Tường | W83: BDNVT621 | X83: Quản trị kinh doanh | Z83: Trường Trung cấp Vạn Tường | AA83: Trực tuyến | AB83: HT | AC83: HT | AD83: CBKL1 | AG83: {=_xludf.XLOOKUP(D83,'Mail+SDT'!A:A,'Mail+SDT'!B:B)} -> #NAME? | AH83: {=_xludf.XLOOKUP(D83,'Mail+SDT'!A:A,'Mail+SDT'!C:C)} -> #NAME? | AI83: {=_xludf.XLOOKUP(D83,'ETK 3.2026'!I:I,'ETK 3.2026'!AF:AF)} -> #NAME?
A84: =ROW()-1 -> 83 | B84: Trangnt | C84: Sangpn | D84: ducnt036 | E84: 839/2024/QĐ-ĐHM | F84: 08/03/2024 | G84: =(YEAR(H84)-YEAR(F84))*12 + MONTH(H84)-MONTH(F84) -> 72 | H84: 08/03/2030 | I84: =IF((H84-TODAY())<=0,"Kết thúc ĐT","Thời gian ĐT còn lại "&(H84-TODAY())&" ngày") -> Thời gian ĐT còn lại 1444 ngày | J84: 24C1002H0969 | K84: Nguyễn Thành Đức | L84: Nguyễn Thành | M84: Đức | N84: 26/10/1995 | O84: Nam | P84: 21 | Q84: CDNVT621 | R84: Công nghệ thông tin | S84: =VLOOKUP(D84, 'Mail+SDT'!A542:C2657, 2, 0) -> 24C1002H0969@students.hou.edu.vn | T84: =VLOOKUP(D84, 'Mail+SDT'!$A$2:$C$2117, 3, 0) -> 345378333 | U84: DNVT | V84: Trường Trung cấp Vạn Tường | W84: CDNVT621 | X84: Công nghệ thông tin | Z84: Trường Trung cấp Vạn Tường | AA84: Trực tuyến | AB84: HT | AC84: HT | AD84: CBKL1 | AE84: BTH | AF84: Thiếu QT học phí để QR | AG84: {=_xludf.XLOOKUP(D84,'Mail+SDT'!A:A,'Mail+SDT'!B:B)} -> #NAME? | AH84: {=_xludf.XLOOKUP(D84,'Mail+SDT'!A:A,'Mail+SDT'!C:C)} -> #NAME? | AI84: {=_xludf.XLOOKUP(D84,'ETK 3.2026'!I:I,'ETK 3.2026'!AF:AF)} -> #NAME?
A85: =ROW()-1 -> 84 | B85: Trangnt | C85: Sangpn | D85: ducnv035 | E85: 2205/2024/QĐ-ĐHM | F85: 07/06/2024 | G85: =(YEAR(H85)-YEAR(F85))*12 + MONTH(H85)-MONTH(F85) -> 72 | H85: 07/06/2030 | I85: =IF((H85-TODAY())<=0,"Kết thúc ĐT","Thời gian ĐT còn lại "&(H85-TODAY())&" ngày") -> Thời gian ĐT còn lại 1535 ngày | J85: 24C1002H3253 | K85: Nguyễn Văn Đức | L85: Nguyễn Văn | M85: Đức | N85: 20/11/1997 | O85: Nam | P85: 21 | Q85: CDNVT621 | R85: Công nghệ thông tin | S85: =VLOOKUP(D85, 'Mail+SDT'!A532:C2647, 2, 0) -> 24C1002H3253@students.hou.edu.vn | T85: =VLOOKUP(D85, 'Mail+SDT'!$A$2:$C$2117, 3, 0) -> 379204287 | U85: DNVT | V85: Trường Trung cấp Vạn Tường | W85: CDNVT621 | X85: Công nghệ thông tin | Z85: Trường Trung cấp Vạn Tường | AA85: Trực tuyến | AB85: HT | AC85: HT | AD85: HT | AG85: {=_xludf.XLOOKUP(D85,'Mail+SDT'!A:A,'Mail+SDT'!B:B)} -> #NAME? | AH85: {=_xludf.XLOOKUP(D85,'Mail+SDT'!A:A,'Mail+SDT'!C:C)} -> #NAME? | AI85: {=_xludf.XLOOKUP(D85,'ETK 3.2026'!I:I,'ETK 3.2026'!AF:AF)} -> #NAME?
A86: =ROW()-1 -> 85 | B86: Trangnt | C86: Quynhtnn | D86: dungdlk | E86: 1676/2024/QĐ-ĐHM | F86: 03/05/2024 | G86: =(YEAR(H86)-YEAR(F86))*12 + MONTH(H86)-MONTH(F86) -> 72 | H86: 03/05/2030 | I86: =IF((H86-TODAY())<=0,"Kết thúc ĐT","Thời gian ĐT còn lại "&(H86-TODAY())&" ngày") -> Thời gian ĐT còn lại 1500 ngày | J86: 24C4504D2538 | K86: Đoàn Lê Khánh Dung | L86: Đoàn Lê Khánh | M86: Dung | N86: 26/04/1997 | O86: Nữ | P86: 21 | Q86: DDNP621 | R86: Tài chính - Ngân hàng | S86: =VLOOKUP(D86, 'Mail+SDT'!A190:C2305, 2, 0) -> 24C4504D2538@students.hou.edu.vn | T86: =VLOOKUP(D86, 'Mail+SDT'!$A$2:$C$2117, 3, 0) -> 776368584 | U86: DNP | V86: Trung tâm Đại học Mở Hà Nội tại Đà Nẵng | W86: DDNP621 | X86: Tài chính - Ngân hàng | Z86: Trung tâm Đại học Mở Hà Nội tại Đà Nẵng | AA86: Trực tuyến | AB86: HT | AC86: HT | AD86: HT | AG86: {=_xludf.XLOOKUP(D86,'Mail+SDT'!A:A,'Mail+SDT'!B:B)} -> #NAME? | AH86: {=_xludf.XLOOKUP(D86,'Mail+SDT'!A:A,'Mail+SDT'!C:C)} -> #NAME? | AI86: {=_xludf.XLOOKUP(D86,'ETK 3.2026'!I:I,'ETK 3.2026'!AF:AF)} -> #NAME?
A87: =ROW()-1 -> 86 | B87: Trangnt | C87: Sangpn | D87: dungdtm004 | E87: 2118/2022/QĐ-ĐHM | F87: 30/06/2022 | G87: =(YEAR(H87)-YEAR(F87))*12 + MONTH(H87)-MONTH(F87) -> 72 | H87: 30/06/2028 | I87: =IF((H87-TODAY())<=0,"Kết thúc ĐT","Thời gian ĐT còn lại "&(H87-TODAY())&" ngày") -> Thời gian ĐT còn lại 828 ngày | J87: 22C1002H2719 | K87: Đoàn Thị Mỹ Dung | L87: Đoàn Thị Mỹ | M87: Dung | N87: 20/04/1997 | O87: Nữ | P87: 17 | Q87: CDNVT417 | R87: Công nghệ thông tin | S87: =VLOOKUP(D87, 'Mail+SDT'!A251:C2366, 2, 0) -> dungdoan204@gmail.com | T87: =VLOOKUP(D87, 'Mail+SDT'!$A$2:$C$2117, 3, 0) -> 971660096 | U87: DNVT | V87: Trường Trung cấp Vạn Tường | W87: CDNVT417 | X87: Công nghệ thông tin | Z87: Trường Trung cấp Vạn Tường | AA87: Trực tuyến | AB87: HT | AC87: HT | AD87: CBKL1 | AG87: {=_xludf.XLOOKUP(D87,'Mail+SDT'!A:A,'Mail+SDT'!B:B)} -> #NAME? | AH87: {=_xludf.XLOOKUP(D87,'Mail+SDT'!A:A,'Mail+SDT'!C:C)} -> #NAME? | AI87: {=_xludf.XLOOKUP(D87,'ETK 3.2026'!I:I,'ETK 3.2026'!Z:Z)} -> #NAME?
A88: =ROW()-1 -> 87 | B88: Trangnt | C88: Sangpn | D88: dungdtt012 | E88: 1676/2024/QĐ-ĐHM | F88: 03/05/2024 | G88: =(YEAR(H88)-YEAR(F88))*12 + MONTH(H88)-MONTH(F88) -> 72 | H88: 03/05/2030 | I88: =IF((H88-TODAY())<=0,"Kết thúc ĐT","Thời gian ĐT còn lại "&(H88-TODAY())&" ngày") -> Thời gian ĐT còn lại 1500 ngày | J88: 24C4102H2408 | K88: Dư Thị Thùy Dung | L88: Dư Thị Thùy | M88: Dung | N88: 25/12/1992 | O88: Nữ | P88: 21 | Q88: ADNVT621 | R88: Kế toán | S88: =VLOOKUP(D88, 'Mail+SDT'!A362:C2477, 2, 0) -> 24C4102H2408@students.hou.edu.vn | T88: =VLOOKUP(D88, 'Mail+SDT'!$A$2:$C$2117, 3, 0) -> 336616530 | U88: DNVT | V88: Trường Trung cấp Vạn Tường | W88: ADNVT621 | X88: Kế toán | Z88: Trường Trung cấp Vạn Tường | AA88: Trực tuyến | AB88: HT | AC88: HT | AD88: HT | AG88: {=_xludf.XLOOKUP(D88,'Mail+SDT'!A:A,'Mail+SDT'!B:B)} -> #NAME? | AH88: {=_xludf.XLOOKUP(D88,'Mail+SDT'!A:A,'Mail+SDT'!C:C)} -> #NAME? | AI88: {=_xludf.XLOOKUP(D88,'ETK 3.2026'!I:I,'ETK 3.2026'!AF:AF)} -> #NAME?
A89: =ROW()-1 -> 88 | B89: Trangnt | C89: Sangpn | D89: dungdtt013 | E89: 1676/2024/QĐ-ĐHM | F89: 03/05/2024 | G89: =(YEAR(H89)-YEAR(F89))*12 + MONTH(H89)-MONTH(F89) -> 72 | H89: 03/05/2030 | I89: =IF((H89-TODAY())<=0,"Kết thúc ĐT","Thời gian ĐT còn lại "&(H89-TODAY())&" ngày") -> Thời gian ĐT còn lại 1500 ngày | J89: 24C4102H2405 | K89: Đồng Thị Thuỳ Dung | L89: Đồng Thị Thuỳ | M89: Dung | N89: 10/10/1994 | O89: Nữ | P89: 21 | Q89: ADNVT621 | R89: Kế toán | S89: =VLOOKUP(D89, 'Mail+SDT'!A378:C2493, 2, 0) -> 24C4102H2405@students.hou.edu.vn | T89: =VLOOKUP(D89, 'Mail+SDT'!$A$2:$C$2117, 3, 0) -> 934898428 | U89: DNVT | V89: Trường Trung cấp Vạn Tường | W89: ADNVT621 | X89: Kế toán | Z89: Trường Trung cấp Vạn Tường | AA89: Trực tuyến | AB89: HT | AC89: HT | AD89: HT | AG89: {=_xludf.XLOOKUP(D89,'Mail+SDT'!A:A,'Mail+SDT'!B:B)} -> #NAME? | AH89: {=_xludf.XLOOKUP(D89,'Mail+SDT'!A:A,'Mail+SDT'!C:C)} -> #NAME? | AI89: {=_xludf.XLOOKUP(D89,'ETK 3.2026'!I:I,'ETK 3.2026'!AF:AF)} -> #NAME?
A90: =ROW()-1 -> 89 | B90: Trangnt | C90: Quynhtnn | D90: dunghh002 | E90: 1650/2022/QĐ-ĐHM | F90: 31/05/2022 | G90: =(YEAR(H90)-YEAR(F90))*12 + MONTH(H90)-MONTH(F90) -> 72 | H90: 31/05/2028 | I90: =IF((H90-TODAY())<=0,"Kết thúc ĐT","Thời gian ĐT còn lại "&(H90-TODAY())&" ngày") -> Thời gian ĐT còn lại 798 ngày | J90: 22C5104D2219 | K90: Hồ Hữu Dũng | L90: Hồ Hữu | M90: Dũng | N90: 26/11/1991 | O90: Nam | P90: 17 | Q90: EDNP517 | R90: Luật kinh tế | S90: =VLOOKUP(D90, 'Mail+SDT'!A57:C2172, 2, 0) -> hohuudunge25@gmail.com | T90: =VLOOKUP(D90, 'Mail+SDT'!$A$2:$C$2117, 3, 0) -> 964995374 | U90: DNP | V90: Trung tâm Đại học Mở Hà Nội tại Đà Nẵng | W90: EDNP517 | X90: Luật kinh tế | Z90: Trung tâm Đại học Mở Hà Nội tại Đà Nẵng | AA90: Trực tuyến | AB90: HT | AC90: HT | AD90: HTCT | AG90: {=_xludf.XLOOKUP(D90,'Mail+SDT'!A:A,'Mail+SDT'!B:B)} -> #NAME? | AH90: {=_xludf.XLOOKUP(D90,'Mail+SDT'!A:A,'Mail+SDT'!C:C)} -> #NAME? | AI90: {=_xludf.XLOOKUP(D90,'ETK 3.2026'!I:I,'ETK 3.2026'!AF:AF)} -> #NAME?
A91: =ROW()-1 -> 90 | B91: Trangnt | C91: Quynhtnn | D91: dungltt014 | E91: 1301/2024/QĐ-ĐHM | F91: 05/04/2024 | G91: =(YEAR(H91)-YEAR(F91))*12 + MONTH(H91)-MONTH(F91) -> 72 | H91: 05/04/2030 | I91: =IF((H91-TODAY())<=0,"Kết thúc ĐT","Thời gian ĐT còn lại "&(H91-TODAY())&" ngày") -> Thời gian ĐT còn lại 1472 ngày | J91: 24C4104D1797 | K91: Lê Thị Thùy Dung | L91: Lê Thị Thùy | M91: Dung | N91: 24/06/1993 | O91: Nữ | P91: 21 | Q91: ADNP221 | R91: Kế toán | S91: =VLOOKUP(D91, 'Mail+SDT'!A89:C2204, 2, 0) -> 24C4104D1797@students.hou.edu.vn | T91: =VLOOKUP(D91, 'Mail+SDT'!$A$2:$C$2117, 3, 0) -> 373901903 | U91: DNP | V91: Trung tâm Đại học Mở Hà Nội tại Đà Nẵng | W91: ADNP221 | X91: Kế toán | Z91: Trung tâm Đại học Mở Hà Nội tại Đà Nẵng | AA91: Trực tuyến | AB91: HT | AC91: HT | AD91: HT | AG91: {=_xludf.XLOOKUP(D91,'Mail+SDT'!A:A,'Mail+SDT'!B:B)} -> #NAME? | AH91: {=_xludf.XLOOKUP(D91,'Mail+SDT'!A:A,'Mail+SDT'!C:C)} -> #NAME? | AI91: {=_xludf.XLOOKUP(D91,'ETK 3.2026'!I:I,'ETK 3.2026'!AF:AF)} -> #NAME?
A92: =ROW()-1 -> 91 | B92: Trangnt | C92: Quynhtnn | D92: dungnd014 | E92: 850/2023/QĐ-ĐHM | F92: 09/03/2023 | G92: =(YEAR(H92)-YEAR(F92))*12 + MONTH(H92)-MONTH(F92) -> 72 | H92: 09/03/2029 | I92: =IF((H92-TODAY())<=0,"Kết thúc ĐT","Thời gian ĐT còn lại "&(H92-TODAY())&" ngày") -> Thời gian ĐT còn lại 1080 ngày | J92: 23C4504D0716 | K92: Nguyễn Đức Dũng | L92: Nguyễn Đức | M92: Dũng | N92: 18/11/1999 | O92: Nam | P92: 21 | Q92: DDNP321 | R92: Tài chính - Ngân hàng | S92: =VLOOKUP(D92, 'Mail+SDT'!A185:C2300, 2, 0) -> 23C4504D0716@students.hou.edu.vn | T92: =VLOOKUP(D92, 'Mail+SDT'!$A$2:$C$2117, 3, 0) -> 797893829 | U92: DNP | V92: Trung tâm Đại học Mở Hà Nội tại Đà Nẵng | W92: DDNP321 | X92: Tài chính - Ngân hàng | Z92: Trung tâm Đại học Mở Hà Nội tại Đà Nẵng | AA92: Trực tuyến | AB92: HT | AC92: HT | AD92: HT | AG92: {=_xludf.XLOOKUP(D92,'Mail+SDT'!A:A,'Mail+SDT'!B:B)} -> #NAME? | AH92: {=_xludf.XLOOKUP(D92,'Mail+SDT'!A:A,'Mail+SDT'!C:C)} -> #NAME? | AI92: {=_xludf.XLOOKUP(D92,'ETK 3.2026'!I:I,'ETK 3.2026'!AF:AF)} -> #NAME?
A93: =ROW()-1 -> 92 | B93: Trangnt | C93: Sangpn | D93: dungnt118 | E93: 1301/2024/QĐ-ĐHM | F93: 05/04/2024 | G93: =(YEAR(H93)-YEAR(F93))*12 + MONTH(H93)-MONTH(F93) -> 72 | H93: 05/04/2030 | I93: =IF((H93-TODAY())<=0,"Kết thúc ĐT","Thời gian ĐT còn lại "&(H93-TODAY())&" ngày") -> Thời gian ĐT còn lại 1472 ngày | J93: 24C4702H1716 | K93: Nguyễn Thị Dung | L93: Nguyễn Thị | M93: Dung | N93: 09/11/2001 | O93: Nữ | P93: 21 | Q93: NDNVT621 | R93: Thương mại điện tử | S93: =VLOOKUP(D93, 'Mail+SDT'!A610:C2725, 2, 0) -> 24C4702H1716@students.hou.edu.vn | T93: =VLOOKUP(D93, 'Mail+SDT'!$A$2:$C$2117, 3, 0) -> 961663175 | U93: DNVT | V93: Trường Trung cấp Vạn Tường | W93: NDNVT621 | X93: Thương mại điện tử | Z93: Trường Trung cấp Vạn Tường | AA93: Trực tuyến | AB93: HT | AC93: HT | AD93: HT | AG93: {=_xludf.XLOOKUP(D93,'Mail+SDT'!A:A,'Mail+SDT'!B:B)} -> #NAME? | AH93: {=_xludf.XLOOKUP(D93,'Mail+SDT'!A:A,'Mail+SDT'!C:C)} -> #NAME? | AI93: {=_xludf.XLOOKUP(D93,'ETK 3.2026'!I:I,'ETK 3.2026'!AF:AF)} -> #NAME?
A94: =ROW()-1 -> 93 | B94: Trangnt | C94: Quynhtnn | D94: dungnt122 | E94: 2313/2024/QĐ-ĐHM | F94: 14/06/2024 | G94: =(YEAR(H94)-YEAR(F94))*12 + MONTH(H94)-MONTH(F94) -> 72 | H94: 14/06/2030 | I94: =IF((H94-TODAY())<=0,"Kết thúc ĐT","Thời gian ĐT còn lại "&(H94-TODAY())&" ngày") -> Thời gian ĐT còn lại 1542 ngày | J94: 24C4504D3449 | K94: Nguyễn Thu Dung | L94: Nguyễn Thu | M94: Dung | N94: 06/03/1984 | O94: Nữ | P94: 21 | Q94: DDNP621 | R94: Tài chính - Ngân hàng | S94: =VLOOKUP(D94, 'Mail+SDT'!A193:C2308, 2, 0) -> 24C4504D3449@students.hou.edu.vn | T94: =VLOOKUP(D94, 'Mail+SDT'!$A$2:$C$2117, 3, 0) -> 903552888 | U94: DNP | V94: Trung tâm Đại học Mở Hà Nội tại Đà Nẵng | W94: DDNP621 | X94: Tài chính - Ngân hàng | Z94: Trung tâm Đại học Mở Hà Nội tại Đà Nẵng | AA94: Trực tuyến | AB94: HT | AC94: HT | AD94: HT | AG94: {=_xludf.XLOOKUP(D94,'Mail+SDT'!A:A,'Mail+SDT'!B:B)} -> #NAME? | AH94: {=_xludf.XLOOKUP(D94,'Mail+SDT'!A:A,'Mail+SDT'!C:C)} -> #NAME? | AI94: {=_xludf.XLOOKUP(D94,'ETK 3.2026'!I:I,'ETK 3.2026'!AF:AF)} -> #NAME?
A95: =ROW()-1 -> 94 | B95: Trangnt | C95: Sangpn | D95: dungntm015 | E95: 1301/2024/QĐ-ĐHM | F95: 05/04/2024 | G95: =(YEAR(H95)-YEAR(F95))*12 + MONTH(H95)-MONTH(F95) -> 72 | H95: 05/04/2030 | I95: =IF((H95-TODAY())<=0,"Kết thúc ĐT","Thời gian ĐT còn lại "&(H95-TODAY())&" ngày") -> Thời gian ĐT còn lại 1472 ngày | J95: 24C4202H1690 | K95: Nguyễn Thị Mỹ Dung | L95: Nguyễn Thị Mỹ | M95: Dung | N95: 06/04/1985 | O95: Nữ | P95: 21 | Q95: BDNVT621 | R95: Quản trị kinh doanh | S95: =VLOOKUP(D95, 'Mail+SDT'!A423:C2538, 2, 0) -> 24C4202H1690@students.hou.edu.vn | T95: =VLOOKUP(D95, 'Mail+SDT'!$A$2:$C$2117, 3, 0) -> 931200559 | U95: DNVT | V95: Trường Trung cấp Vạn Tường | W95: BDNVT621 | X95: Quản trị kinh doanh | Z95: Trường Trung cấp Vạn Tường | AA95: Trực tuyến | AB95: HT | AC95: HT | AD95: HT | AE95: CBKL1 | AF95: Thiếu QT học phí để QR | AG95: {=_xludf.XLOOKUP(D95,'Mail+SDT'!A:A,'Mail+SDT'!B:B)} -> #NAME? | AH95: {=_xludf.XLOOKUP(D95,'Mail+SDT'!A:A,'Mail+SDT'!C:C)} -> #NAME? | AI95: {=_xludf.XLOOKUP(D95,'ETK 3.2026'!I:I,'ETK 3.2026'!AF:AF)} -> #NAME?
A96: =ROW()-1 -> 95 | B96: Trangnt | C96: Sangpn | D96: dungnv037 | E96: 980/2022/QĐ-ĐHM | F96: 07/04/2022 | G96: =(YEAR(H96)-YEAR(F96))*12 + MONTH(H96)-MONTH(F96) -> 72 | H96: 07/04/2028 | I96: =IF((H96-TODAY())<=0,"Kết thúc ĐT","Thời gian ĐT còn lại "&(H96-TODAY())&" ngày") -> Thời gian ĐT còn lại 744 ngày | J96: 22C5102H1126 | K96: Nguyễn Văn Dũng | L96: Nguyễn Văn | M96: Dũng | N96: 08/10/1980 | O96: Nam | P96: 17 | Q96: EDNVT617 | R96: Luật kinh tế | S96: =VLOOKUP(D96, 'Mail+SDT'!A271:C2386, 2, 0) -> mrdungdangluu@gmail.com | T96: =VLOOKUP(D96, 'Mail+SDT'!$A$2:$C$2117, 3, 0) -> 913963602 | U96: DNVT | V96: Trường Trung cấp Vạn Tường | W96: EDNVT617 | X96: Luật kinh tế | Z96: Trường Trung cấp Vạn Tường | AA96: Trực tuyến | AB96: HT | AC96: HT | AD96: HT | AG96: {=_xludf.XLOOKUP(D96,'Mail+SDT'!A:A,'Mail+SDT'!B:B)} -> #NAME? | AH96: {=_xludf.XLOOKUP(D96,'Mail+SDT'!A:A,'Mail+SDT'!C:C)} -> #NAME? | AI96: {=_xludf.XLOOKUP(D96,'ETK 3.2026'!I:I,'ETK 3.2026'!Z:Z)} -> #NAME?
A97: =ROW()-1 -> 96 | B97: Trangnt | C97: Quynhtnn | D97: dungnv050 | E97: 1676/2024/QĐ-ĐHM | F97: 03/05/2024 | G97: =(YEAR(H97)-YEAR(F97))*12 + MONTH(H97)-MONTH(F97) -> 72 | H97: 03/05/2030 | I97: =IF((H97-TODAY())<=0,"Kết thúc ĐT","Thời gian ĐT còn lại "&(H97-TODAY())&" ngày") -> Thời gian ĐT còn lại 1500 ngày | J97: 24C1004D2526 | K97: Nguyễn Văn Dung | L97: Nguyễn Văn | M97: Dung | N97: 15/03/1979 | O97: Nam | P97: 21 | Q97: CDNP621 | R97: Công nghệ thông tin | S97: =VLOOKUP(D97, 'Mail+SDT'!A174:C2289, 2, 0) -> 24C1004D2526@students.hou.edu.vn | T97: =VLOOKUP(D97, 'Mail+SDT'!$A$2:$C$2117, 3, 0) -> 979312549 | U97: DNP | V97: Trung tâm Đại học Mở Hà Nội tại Đà Nẵng | W97: CDNP621 | X97: Công nghệ thông tin | Z97: Trung tâm Đại học Mở Hà Nội tại Đà Nẵng | AA97: Trực tuyến | AB97: HT | AC97: HT | AD97: HT | AG97: {=_xludf.XLOOKUP(D97,'Mail+SDT'!A:A,'Mail+SDT'!B:B)} -> #NAME? | AH97: {=_xludf.XLOOKUP(D97,'Mail+SDT'!A:A,'Mail+SDT'!C:C)} -> #NAME? | AI97: {=_xludf.XLOOKUP(D97,'ETK 3.2026'!I:I,'ETK 3.2026'!AF:AF)} -> #NAME?
A98: =ROW()-1 -> 97 | B98: Trangnt | C98: Quynhtnn | D98: dungnvp | E98: 2983/2024/QĐ-ĐHM | F98: 26/07/2024 | G98: =(YEAR(H98)-YEAR(F98))*12 + MONTH(H98)-MONTH(F98) -> 72 | H98: 26/07/2030 | I98: =IF((H98-TODAY())<=0,"Kết thúc ĐT","Thời gian ĐT còn lại "&(H98-TODAY())&" ngày") -> Thời gian ĐT còn lại 1584 ngày | J98: 24C4733D4426 | K98: Nguyễn Vũ Phương Dung | L98: Nguyễn Vũ Phương | M98: Dung | N98: 23/02/2000 | O98: Nữ | P98: 21 | Q98: NDNP321 | R98: Thương mại điện tử | S98: =VLOOKUP(D98, 'Mail+SDT'!A196:C2311, 2, 0) -> 24C4733D4426@students.hou.edu.vn | T98: =VLOOKUP(D98, 'Mail+SDT'!$A$2:$C$2117, 3, 0) -> 376455085 | U98: DNP | V98: Trung tâm Đại học Mở Hà Nội tại Đà Nẵng | W98: NDNP321 | X98: Thương mại điện tử | Z98: Trung tâm Đại học Mở Hà Nội tại Đà Nẵng | AA98: Trực tuyến | AB98: HT | AC98: HT | AD98: HT | AG98: {=_xludf.XLOOKUP(D98,'Mail+SDT'!A:A,'Mail+SDT'!B:B)} -> #NAME? | AH98: {=_xludf.XLOOKUP(D98,'Mail+SDT'!A:A,'Mail+SDT'!C:C)} -> #NAME? | AI98: {=_xludf.XLOOKUP(D98,'ETK 3.2026'!I:I,'ETK 3.2026'!AF:AF)} -> #NAME?
A99: =ROW()-1 -> 98 | B99: Trangnt | C99: Sangpn | D99: dungttp003 | E99: 1492/2022/QĐ-ĐHM | F99: 17/05/2022 | G99: =(YEAR(H99)-YEAR(F99))*12 + MONTH(H99)-MONTH(F99) -> 72 | H99: 17/05/2028 | I99: =IF((H99-TODAY())<=0,"Kết thúc ĐT","Thời gian ĐT còn lại "&(H99-TODAY())&" ngày") -> Thời gian ĐT còn lại 784 ngày | J99: 22C7102H1801 | K99: Tô Thị Phương Dung | L99: Tô Thị Phương | M99: Dung | N99: 17/10/1995 | O99: Nữ | P99: 17 | Q99: FDNVT417 | R99: Ngôn ngữ Anh | S99: =VLOOKUP(D99, 'Mail+SDT'!A283:C2398, 2, 0) -> phuongdung1710vn@gmail.com | T99: =VLOOKUP(D99, 'Mail+SDT'!$A$2:$C$2117, 3, 0) -> 367293717 | U99: DNVT | V99: Trường Trung cấp Vạn Tường | W99: FDNVT417 | X99: Ngôn ngữ Anh | Z99: Trường Trung cấp Vạn Tường | AA99: Trực tuyến | AB99: HT | AC99: HT | AD99: HTCT | AG99: {=_xludf.XLOOKUP(D99,'Mail+SDT'!A:A,'Mail+SDT'!B:B)} -> #NAME? | AH99: {=_xludf.XLOOKUP(D99,'Mail+SDT'!A:A,'Mail+SDT'!C:C)} -> #NAME? | AI99: {=_xludf.XLOOKUP(D99,'ETK 3.2026'!I:I,'ETK 3.2026'!AF:AF)} -> #NAME?
A100: =ROW()-1 -> 99 | B100: Trangnt | C100: Quynhtnn | D100: dungtv026 | E100: 1379/2024/QĐ-ĐHM | F100: 12/04/2024 | G100: =(YEAR(H100)-YEAR(F100))*12 + MONTH(H100)-MONTH(F100) -> 72 | H100: 12/04/2030 | I100: =IF((H100-TODAY())<=0,"Kết thúc ĐT","Thời gian ĐT còn lại "&(H100-TODAY())&" ngày") -> Thời gian ĐT còn lại 1479 ngày | J100: 24C4204D1888 | K100: Trần Văn Dung | L100: Trần Văn | M100: Dung | N100: 25/12/1990 | O100: Nam | P100: 21 | Q100: BDNP421 | R100: Quản trị kinh doanh | S100: =VLOOKUP(D100, 'Mail+SDT'!A126:C2241, 2, 0) -> 24C4204D1888@students.hou.edu.vn | T100: =VLOOKUP(D100, 'Mail+SDT'!$A$2:$C$2117, 3, 0) -> 966460679 | U100: DNP | V100: Trung tâm Đại học Mở Hà Nội tại Đà Nẵng | W100: BDNP421 | X100: Quản trị kinh doanh | Z100: Trung tâm Đại học Mở Hà Nội tại Đà Nẵng | AA100: Trực tuyến | AB100: HT | AC100: HT | AD100: HT | AG100: {=_xludf.XLOOKUP(D100,'Mail+SDT'!A:A,'Mail+SDT'!B:B)} -> #NAME? | AH100: {=_xludf.XLOOKUP(D100,'Mail+SDT'!A:A,'Mail+SDT'!C:C)} -> #NAME? | AI100: {=_xludf.XLOOKUP(D100,'ETK 3.2026'!I:I,'ETK 3.2026'!AF:AF)} -> #NAME?
...

Sheet ETK 3.2026
A1: STT | B1: Giáo vụ | C1: QLSV | D1: Trạm | E1: Khoá | F1: Ngành | G1: Mã sinh viên | H1: Lớp | I1: Tài khoản | J1: Họ | K1: Tên | L1: Ngày sinh | M1: Giới tính | N1: Thẩm định bằng | O1: Trạng thái xét CN T12/25 | P1: THÔNG TIN NHẬP HỌC | Q1: THỜI GIAN KẾT THÚC CHƯƠNG TRÌNH ĐÀO TẠO | U1: Loại TN | V1: Đợt xét ETK200 | W1: QLSV phản hồi nguyện vọng | X1: QLSV lấy nguyện vọng xét TN của SV | Y1: Điểm toàn khóa | Z1: Ghi chú điểm toàn khóa | AA1: Phản hồi của QLSV về điểm | AB1: Số tiền phải Tuy thu SV | AC1: QLSV điền chứng từ Truy thu | AF1: QLSV xác nhận chốt DS dự kiến đủ ĐK TN | AG1: SV đăng ký trên hệ thống | AH1: Quản lý | AI1: Ghi chú
P2: Thời gian QĐ đầu vào | Q2: Số TC MM | R2: Tháng học theo QĐ | S2: Thời gian TN theo QĐ | T2: TG chờ TN (số tháng) | AC2: Số tiền nộp | AD2: Số tham chiếu trên sao kê | AE2: Ngày nộp
A4: =IF(L4="","",COUNTA($L4:L$5)) -> 2 | B4: Hoangnm | C4: Khanhntk | D4: DNAV | E4: 17 | F4: A | G4: 22C4102E2243 | H4: ADNAV617 | I4: hiendtb | J4: Đoàn Thị Bích | K4: Hiền | L4: 30461 | M4: Nữ | N4: Hợp lệ | O4: HT | P4: 44712 | Q4: 0 | R4: 36 | S4: 45808 | T4: 0 | U4: A | V4: T3.26 | X4: Có nguyện vọng | Y4: Đã HTCT | AF4: Dự kiến đủ điều kiện | AH4: ĐN
A5: =IF(L5="","",COUNTA($L5:L$5)) -> 1 | B5: Hoangnm | C5: Khanhntk | D5: DNAV | E5: 17 | F5: B | G5: 22C4202E0249 | H5: BDNAV617 | I5: huongntt061 | J5: Nguyễn Thị Thanh | K5: Hương | L5: 34756 | M5: Nữ | N5: Hợp lệ | O5: HT | P5: 44624 | Q5: 0 | R5: 36 | S5: 45720 | T5: 0 | U5: A | V5: T3.26 | X5: Có nguyện vọng | Y5: Đã HTCT | AF5: Dự kiến đủ điều kiện | AH5: ĐN
A6: =IF(L6="","",COUNTA($L6:L$5)) -> 2 | B6: Hoangnm | C6: Khanhntk | D6: DNAV | E6: 17 | F6: B | G6: 22C4202E2239 | H6: BDNAV617 | I6: thuannd008 | J6: Nguyễn Đức | K6: Thuận | L6: 32597 | M6: Nam | N6: Hợp lệ | O6: HT | P6: 44712 | Q6: 0 | R6: 36 | S6: 45808 | T6: 0 | U6: A | V6: T3.26 | X6: Có nguyện vọng | Y6: Đã HTCT | AF6: Dự kiến đủ điều kiện | AH6: ĐN
A7: =IF(L7="","",COUNTA($L7:L$5)) -> 3 | B7: Hoangnm | C7: Khanhntk | D7: DNAV | E7: 17 | F7: B | G7: 22C4202E2884 | H7: BDNAV617 | I7: tranghp002 | J7: Huỳnh Phước | K7: Trạng | L7: 35907 | M7: Nam | N7: Chưa TĐB | O7: HT | P7: 44742 | Q7: 0 | R7: 36 | S7: 45838 | T7: 0 | U7: A | V7: T3.26 | X7: Có nguyện vọng | Y7: Đã HTCT | AF7: Dự kiến đủ điều kiện | AH7: ĐN
A8: =IF(L8="","",COUNTA($L8:L$5)) -> 4 | B8: Hoangnm | C8: Khanhntk | D8: DNAV | E8: 17 | F8: F | G8: 22C7102E2247 | H8: FDNAV617 | I8: tiendtt003 | J8: Dương Thị Thủy | K8: Tiên | L8: 31478 | M8: Nữ | N8: Hợp lệ | O8: HT | P8: 44712 | Q8: 0 | R8: 36 | S8: 45808 | T8: 0 | U8: A | V8: T3.26 | X8: Có nguyện vọng | Y8: Đã HTCT | AF8: Dự kiến đủ điều kiện | AH8: ĐN
A9: =IF(L9="","",COUNTA($L9:L$5)) -> 5 | B9: Hoangnm | C9: Khanhntk | D9: DNAV | E9: 17 | F9: H | G9: 22C5002E1847 | H9: HDNAV617 | I9: aunh | J9: Nguyễn Hải | K9: Âu | L9: 34629 | M9: Nam | N9: Hợp lệ | O9: HT | P9: 44698 | Q9: 0 | R9: 36 | S9: 45794 | T9: 0 | U9: A | V9: T3.26 | X9: Có nguyện vọng | Y9: Đã HTCT | AF9: Dự kiến đủ điều kiện | AH9: ĐN
A10: =IF(L10="","",COUNTA($L10:L$5)) -> 6 | B10: Hoangnm | C10: Khanhntk | D10: DNAV | E10: 17 | F10: H | G10: 22C5002E2248 | H10: HDNAV617 | I10: dinhpq002 | J10: Phạm Quang | K10: Định | L10: 30010 | M10: Nam | N10: Hợp lệ | O10: HT | P10: 44712 | Q10: 0 | R10: 36 | S10: 45808 | T10: 0 | U10: A | V10: T3.26 | X10: Có nguyện vọng | Y10: Nợ môn_Không TN | Z10: EL14 | AF10: Không đủ điều kiện | AH10: ĐN
A11: =IF(L11="","",COUNTA($L11:L$5)) -> 7 | B11: Hoangnm | C11: Khanhntk | D11: DNAV | E11: 17 | F11: H | G11: 22C5002E2249 | H11: HDNAV617 | I11: ducpnm | J11: Phú Nguyễn Minh | K11: Đức | L11: 34186 | M11: Nam | N11: Hợp lệ | O11: HT | P11: 44712 | Q11: 0 | R11: 36 | S11: 45808 | T11: 0 | U11: A | V11: T3.26 | X11: Có nguyện vọng | Y11: Đã HTCT | AF11: Dự kiến đủ điều kiện | AH11: ĐN
A12: =IF(L12="","",COUNTA($L12:L$5)) -> 8 | B12: Hoangnm | C12: Khanhntk | D12: DNAV | E12: 17 | F12: H | G12: 22C5002E0490 | H12: HDNAV417 | I12: nguyetltt | J12: Lê Thị Thu | K12: Nguyệt | L12: 35409 | M12: Nữ | N12: Chưa TĐB | O12: HT | P12: 44641 | Q12: 20 | R12: 30 | S12: 45556 | T12: 0 | U12: A | V12: KH CŨ | X12: Có nguyện vọng | Y12: Nợ môn_Không TN | Z12: Nợ nhiều | AF12: Không đủ điều kiện | AH12: ĐN
A13: =IF(L13="","",COUNTA($L13:L$5)) -> 9 | B13: Hoangnm | C13: Khanhntk | D13: DNCN | E13: 17 | F13: H | G13: 22C5002J1029 | H13: HDNCN617 | I13: sondk | J13: Đào Kim | K13: Sơn | L13: 34692 | M13: Nam | N13: Hợp lệ | O13: HT | P13: 44650 | Q13: 0 | R13: 36 | S13: 45746 | T13: 0 | U13: A | V13: T3.26 | X13: Có nguyện vọng | Y13: Đã HTCT | AF13: Dự kiến đủ điều kiện | AH13: ĐN
A14: =IF(L14="","",COUNTA($L14:L$5)) -> 10 | B14: Hoangnm | C14: Khanhntk | D14: QB | E14: 18 | F14: F | G14: 22C7131D5099 | H14: FQB318 | I14: huyenttt013 | J14: Trần Thị Thúy | K14: Huyền | L14: 36469 | M14: Nữ | N14: Hợp lệ | O14: HT | P14: 44865 | Q14: 16 | R14: 31 | S14: 45808 | T14: 0 | U14: A | V14: KH CŨ | X14: Có nguyện vọng | Y14: Nợ môn_Không TN | Z14: EN56,EN48,EN37 | AF14: Không đủ điều kiện | AH14: ELC
A15: =IF(L15="","",COUNTA($L15:L$5)) -> 11 | B15: Hungnc | C15: Khanhntk | D15: DNDH | E15: 17 | F15: H | G15: 22C5036D2268 | H15: HDNDH617 | I15: hoailv | J15: Lê Văn | K15: Hoài | L15: 33455 | M15: Nam | N15: Chưa TĐB | O15: HT | P15: 44712 | R15: 36 | S15: 45808 | T15: 0 | U15: A | V15: T3.26 | X15: Có nguyện vọng | Y15: Đã HTCT | AF15: Dự kiến đủ điều kiện | AH15: ĐN
A16: =IF(L16="","",COUNTA($L16:L$5)) -> 12 | B16: Hungnc | C16: Khanhntk | D16: DNDH | E16: 17 | F16: H | G16: 22C5036D2893 | H16: HDNDH617 | I16: quynhnh003 | J16: Nguyễn Hữu | K16: Quỳnh | L16: 31769 | M16: Nam | N16: Chưa TĐB | O16: HT | P16: 44742 | R16: 36 | S16: 45838 | T16: 0 | U16: A | V16: T3.26 | X16: Có nguyện vọng | Y16: Nợ môn_Không TN | AF16: Không đủ điều kiện | AH16: ĐN
A17: =IF(L17="","",COUNTA($L17:L$5)) -> 13 | B17: Hungnc | C17: Khanhntk | D17: DNKH | E17: 17 | F17: B | G17: 22C4241E1235 | H17: BDNKH217 | I17: namdx | J17: Đặng Xuân | K17: Nam | L17: 29146 | M17: Nam | N17: Chờ hoàn thiện | O17: HTCT | P17: 44658 | Q17: 40 | R17: 24 | S17: 45419 | T17: 0 | U17: A | V17: KH CŨ | X17: Có nguyện vọng | Y17: Đã HTCT | AF17: Dự kiến đủ điều kiện | AH17: ĐN
A18: =IF(L18="","",COUNTA($L18:L$5)) -> 14 | B18: Hungnc | C18: Khanhntk | D18: DNKH | E18: 17 | F18: C | G18: 22C1041E1037 | H18: CDNKH617 | I18: namvh011 | J18: Võ Hùng | K18: Nam | L18: 34354 | M18: Nam | N18: Hợp lệ | O18: HT | P18: 44650 | R18: 36 | S18: 45746 | T18: 0 | U18: A | V18: T3.26 | X18: Có nguyện vọng | Y18: Đã HTCT | AF18: Dự kiến đủ điều kiện | AH18: ĐN
A19: =IF(L19="","",COUNTA($L19:L$5)) -> 15 | B19: Hungnc | C19: Khanhntk | D19: DNKH | E19: 17 | F19: C | G19: 22C1041E1039 | H19: CDNKH617 | I19: trinhnv003 | J19: Nguyễn Văn | K19: Trình | L19: 30857 | M19: Nam | N19: Hợp lệ | O19: HT | P19: 44650 | R19: 36 | S19: 45746 | T19: 0 | U19: A | V19: T3.26 | X19: Có nguyện vọng | Y19: Đã HTCT | AF19: Dự kiến đủ điều kiện | AH19: ĐN
A20: =IF(L20="","",COUNTA($L20:L$5)) -> 16 | B20: Hungnc | C20: Khanhntk | D20: DNKH | E20: 17 | F20: F | G20: 22C7141E3380 | H20: FDNKH617 | I20: trungnqa | J20: Nguyễn Quốc Anh | K20: Trung | L20: 27582 | M20: Nam | N20: Hợp lệ | O20: HT | P20: 44778 | R20: 36 | S20: 45874 | T20: 0 | U20: A | V20: T3.26 | X20: Có nguyện vọng | Y20: Đã HTCT | AF20: Dự kiến đủ điều kiện | AH20: ĐN
A21: =IF(L21="","",COUNTA($L21:L$5)) -> 17 | B21: Hungnc | C21: Khanhntk | D21: DNNT | E21: 17 | F21: B | G21: 22C4245D2356 | H21: BDNNT517 | I21: tuanqm | J21: Quảng Minh | K21: Tuấn | L21: 35539 | M21: Nam | N21: Hợp lệ | O21: HT | P21: 44715 | R21: 36 | S21: 45811 | T21: 0 | U21: A | V21: KH CŨ | X21: Có nguyện vọng | Y21: Đã HTCT | AF21: Dự kiến đủ điều kiện | AH21: ĐN
A22: =IF(L22="","",COUNTA($L22:L$5)) -> 18 | B22: Hungnc | C22: Khanhntk | D22: SG | E22: 17 | F22: A | G22: 22C4102D0458 | H22: ASG517 | I22: oanhdtk009 | J22: Đinh Thị Kim | K22: Oanh | L22: 35609 | M22: Nữ | N22: Chưa TĐB | O22: HT | P22: 44641 | R22: 36 | S22: 45737 | T22: 0 | U22: A | V22: KH CŨ | X22: Có nguyện vọng | Y22: Nợ môn_Không TN | Z22: AC11,EG09.3 | AF22: Không đủ điều kiện | AH22: ELC
A23: =IF(L23="","",COUNTA($L23:L$5)) -> 19 | B23: Hungnc | C23: Khanhntk | D23: SG | E23: 17 | F23: B | G23: 22C4202D3285 | H23: BSG617 | I23: hanhnt049 | J23: Nguyễn Thị | K23: Hạnh | L23: 33440 | M23: Nữ | N23: Hợp lệ | O23: HT | P23: 44771 | R23: 36 | S23: 45867 | T23: 0 | U23: A | V23: T3.26 | X23: Có nguyện vọng | Y23: Đã HTCT | AF23: Dự kiến đủ điều kiện | AH23: ELC
A24: =IF(L24="","",COUNTA($L24:L$5)) -> 20 | B24: Hungnc | C24: Khanhntk | D24: SG | E24: 17 | F24: C | G24: 21C-10-48.1-01465 | H24: CSG117 | I24: trungpnh | J24: Phan Nguyễn Hoài | K24: Trung | L24: 35694 | M24: Nam | N24: Chưa TĐB | O24: HT | P24: 44292 | Q24: 0 | R24: 43 | S24: 45602 | T24: 0 | U24: A | V24: KH CŨ | X24: Có nguyện vọng | Y24: Nợ môn_Không TN | Z24: EG43,IT11,IT59,IT60 | AF24: Không đủ điều kiện | AH24: ELC
A25: =IF(L25="","",COUNTA($L25:L$5)) -> 21 | B25: Hungnc | C25: Khanhntk | D25: SG | E25: 17 | F25: F | G25: 22C7102D3182 | H25: FSG517 | I25: mopt003 | J25: Phạm Thị | K25: Mơ | L25: 33742 | M25: Nữ | N25: Chưa TĐB | O25: HT | P25: 44753 | Q25: 13 | R25: 32 | S25: 45727 | T25: 0 | U25: A | V25: KH CŨ | X25: Có nguyện vọng | Y25: Nợ môn_Không TN | AF25: Không đủ điều kiện | AH25: ELC
A26: =IF(L26="","",COUNTA($L26:L$5)) -> 22 | B26: Hungnc | C26: Khanhntk | D26: SG | E26: 17 | F26: G | G26: 22C4602D2961 | H26: GSG317 | I26: hana | J26: Ngô An | K26: Hạ | L26: 28485 | M26: Nam | N26: Chưa TĐB | O26: HT | P26: 44748 | Q26: 24 | R26: 35 | S26: 45814 | T26: 0 | U26: A | V26: KH CŨ | X26: Có nguyện vọng | Y26: Nợ môn_Không TN | AF26: Không đủ điều kiện | AH26: ELC
A27: =IF(L27="","",COUNTA($L27:L$5)) -> 23 | B27: Hungnc | C27: Khanhntk | D27: SG | E27: 18 | F27: B | G27: 22C4202D4749 | H27: BSG418 | I27: khoant002 | J27: Nguyễn Tấn | K27: Khoa | L27: 31050 | M27: Nam | N27: Hợp lệ | O27: HT | P27: 44841 | Q27: 11 | R27: 33 | S27: 45845 | T27: 0 | U27: A | V27: T3.26 | X27: Có nguyện vọng | Y27: Đã HTCT | AF27: Dự kiến đủ điều kiện | AH27: ELC
A28: =IF(L28="","",COUNTA($L28:L$5)) -> 24 | B28: Hungnc | C28: Khanhntk | D28: SG | E28: 18 | F28: B | G28: 22C4202D5718 | H28: BSG418 | I28: thaitm | J28: Trương Minh | K28: Thái | L28: 33103 | M28: Nam | N28: Hợp lệ | O28: HT | P28: 44918 | Q28: 17 | R28: 31 | S28: 45861 | T28: 0 | U28: A | V28: T3.26 | X28: Có nguyện vọng | Y28: Nợ môn_Không TN | AF28: Không đủ điều kiện | AH28: ELC
A29: =IF(L29="","",COUNTA($L29:L$5)) -> 25 | B29: Hungnc | C29: Khanhntk | D29: SG | E29: 18 | F29: C | G29: 22C1002D5596 | H29: CSG418 | I29: duynt012 | J29: Nguyễn Thanh | K29: Duy | L29: 36365 | M29: Nam | N29: Hợp lệ | O29: HT | P29: 44908 | Q29: 11 | R29: 33 | S29: 45913 | T29: 0 | U29: A | V29: T3.26 | X29: Có nguyện vọng | Y29: Nợ môn_Không TN | AF29: Không đủ điều kiện | AH29: ELC
A30: =IF(L30="","",COUNTA($L30:L$5)) -> 26 | B30: Hungnc | C30: Khanhntk | D30: SG | E30: 18 | F30: C | G30: 22C1002D4729 | H30: CSG418 | I30: minhhn003 | J30: Hoàng Ngọc | K30: Minh | L30: 33644 | M30: Nam | N30: Hợp lệ | O30: HT | P30: 44841 | Q30: 10 | R30: 33 | S30: 45845 | T30: 0 | U30: A | V30: T3.26 | X30: Có nguyện vọng | Y30: Nợ môn_Không TN | Z30: IT40,IT43 | AF30: Không đủ điều kiện | AH30: ELC
A31: =IF(L31="","",COUNTA($L31:L$5)) -> 27 | B31: Hungnc | C31: Khanhntk | D31: SG | E31: 18 | F31: D | G31: 22C4502D2962 | H31: DSG418 | I31: thamtq | J31: Trương Quế | K31: Thắm | L31: 32874 | M31: Nữ | N31: Hợp lệ | O31: HT | P31: 44748 | R31: 36 | S31: 45844 | T31: 0 | U31: A | V31: T3.26 | X31: Có nguyện vọng | Y31: Đã HTCT | AF31: Dự kiến đủ điều kiện | AH31: ELC
A32: =IF(L32="","",COUNTA($L32:L$5)) -> 28 | B32: Hungnc | C32: Khanhntk | D32: SG | E32: 18 | F32: F | G32: 19C-71-48.1-02646 | H32: FSG118 | I32: cuongtt002 | J32: Trần Tuấn | K32: Cường | L32: 28591 | M32: Nam | N32: Hợp lệ | O32: HT | P32: 43706 | Q32: 0 | R32: 36 | S32: 44802 | T32: 0 | U32: A | V32: KH CŨ | X32: Có nguyện vọng | Y32: Nợ môn_Không TN | AF32: Không đủ điều kiện | AH32: ELC
A33: =IF(L33="","",COUNTA($L33:L$5)) -> 29 | B33: Hungnc | C33: Khanhntk | D33: SG | E33: 18 | F33: F | G33: 22C7102D5592 | H33: FSG418 | I33: nghianm004 | J33: Nguyễn Minh | K33: Nghĩa | L33: 30740 | M33: Nữ | N33: Hợp lệ | O33: HT | P33: 44908 | Q33: 11 | R33: 33 | S33: 45913 | T33: 0 | U33: A | V33: T3.26 | X33: Có nguyện vọng | Y33: Nợ môn_Không TN | Z33: EN39 | AF33: Không đủ điều kiện | AH33: ELC
A34: =IF(L34="","",COUNTA($L34:L$5)) -> 30 | B34: Hungnc | C34: Khanhntk | D34: SG | E34: 18 | F34: F | G34: 23C7101G0012 | H34: FSG418 | I34: phuongnv015 | J34: Nguyễn Văn | K34: Phương | L34: 30801 | M34: Nam | N34: Chưa TĐB | O34: HT | P34: 44967 | Q34: 18 | R34: 31 | S34: 45904 | T34: 0 | U34: A | V34: T3.26 | X34: Có nguyện vọng | Y34: Nợ môn_Không TN | Z34: EN39 | AF34: Không đủ điều kiện | AH34: ELC
A35: =IF(L35="","",COUNTA($L35:L$5)) -> 31 | B35: Hungnc | C35: Khanhntk | D35: SG | E35: 18 | F35: H | G35: 21C-50-48.1-04223 | H35: HSG418 | I35: hungdt004 | J35: Đinh Thái | K35: Hùng | L35: 30713 | M35: Nam | N35: Hợp lệ | O35: HT | P35: 44379 | R35: 36 | S35: 45475 | T35: 0 | U35: A | V35: T3.26 | X35: Có nguyện vọng | Y35: Nợ môn_Không TN | AF35: Không đủ điều kiện | AH35: ELC
A36: =IF(L36="","",COUNTA($L36:L$5)) -> 32 | B36: Hungnc | C36: Khanhntk | D36: SG | E36: 18 | F36: H | G36: 23C5002D0025 | H36: HSG418 | I36: nangcms | J36: Chau Meas Som | K36: Nang | L36: 33100 | M36: Nam | N36: Hợp lệ | O36: HT | P36: 44967 | R36: 36 | S36: 46057 | T36: 0 | U36: A | V36: T3.26 | X36: Có nguyện vọng | Y36: Nợ môn_Không TN | AF36: Không đủ điều kiện | AH36: ELC
A37: =IF(L37="","",COUNTA($L37:L$5)) -> 33 | B37: Hungnc | C37: Khanhntk | D37: SG | E37: 18 | F37: H | G37: 22C5002D4743 | H37: HSG418 | I37: yenbk | J37: Bùi Kim | K37: Yến | L37: 30966 | M37: Nữ | N37: Hợp lệ | O37: HT | P37: 44841 | Q37: 11 | R37: 33 | S37: 45845 | T37: 0 | U37: A | V37: T3.26 | X37: Có nguyện vọng | Y37: Đã HTCT | AF37: Dự kiến đủ điều kiện | AH37: ELC
A38: =IF(L38="","",COUNTA($L38:L$5)) -> 34 | B38: Hungnc | C38: Khanhntk | D38: SG | E38: 19 | F38: B | G38: 23C4202D1332 | H38: BSG219 | I38: trangbtt006 | J38: Bùi Thị Thu | K38: Trang | L38: 34211 | M38: Nữ | N38: Hợp lệ | O38: HT | P38: 45016 | Q38: 20 | R38: 30 | S38: 45904 | T38: 0 | U38: A | V38: T3.26 | X38: Có nguyện vọng | Y38: Đã HTCT | AF38: Dự kiến đủ điều kiện | AH38: ELC
A39: =IF(L39="","",COUNTA($L39:L$5)) -> 35 | B39: Hungnc | C39: Khanhntk | D39: SG | E39: 19 | F39: C | G39: 23C1002D1398 | H39: CSG219 | I39: duyntm | J39: Nguyễn Trần Minh | K39: Duy | L39: 35431 | M39: Nam | N39: Hợp lệ | O39: HT | P39: 45023 | Q39: 23 | R39: 29 | S39: 45904 | T39: 0 | U39: A | V39: T3.26 | X39: Có nguyện vọng | Y39: Nợ môn_Không TN | AF39: Không đủ điều kiện | AH39: ELC
A40: =IF(L40="","",COUNTA($L40:L$5)) -> 36 | B40: Hungnc | C40: Khanhntk | D40: SG | E40: 19 | F40: E | G40: 23C5102D1178 | H40: ESG219 | I40: anhntt023 | J40: Nguyễn Thị Tú | K40: Anh | L40: 28689 | M40: Nữ | N40: Hợp lệ | O40: HT | P40: 45016 | Q40: 20 | R40: 30 | S40: 45904 | T40: 0 | U40: A | V40: T3.26 | X40: Có nguyện vọng | Y40: Đã HTCT | AF40: Dự kiến đủ điều kiện | AH40: ELC
A41: =IF(L41="","",COUNTA($L41:L$5)) -> 37 | B41: Hungnc | C41: Khanhntk | D41: SG | E41: 19 | F41: F | G41: 23C7102D0898 | H41: FSG219 | I41: sangnv009 | J41: Nguyễn Viết | K41: Sang | L41: 31925 | M41: Nam | N41: Chưa TĐB | O41: HT | P41: 44999 | Q41: 16 | R41: 31 | S41: 45934 | T41: 0 | U41: A | V41: T3.26 | X41: Có nguyện vọng | Y41: Nợ môn_Không TN | AF41: Không đủ điều kiện | AH41: ELC
A42: =IF(L42="","",COUNTA($L42:L$5)) -> 38 | B42: Hungnc | C42: Khanhntk | D42: SG | E42: 19 | F42: F | G42: 23C7102D0900 | H42: FSG219 | I42: vanha | J42: Hoàng Anh | K42: Văn | L42: 35636 | M42: Nam | N42: Chưa TĐB | O42: HT | P42: 44999 | Q42: 17 | R42: 31 | S42: 45934 | T42: 0 | U42: A | V42: T3.26 | X42: Có nguyện vọng | Y42: Nợ môn_Không TN | AF42: Không đủ điều kiện | AH42: ELC
A43: =IF(L43="","",COUNTA($L43:L$5)) -> 39 | B43: Hungnc | C43: Khanhntk | D43: SG | E43: 19 | F43: H | G43: 23C5002D0902 | H43: HSG219 | I43: kiennt035 | J43: Nguyễn Thế | K43: Kiên | L43: 32492 | M43: Nam | N43: Hợp lệ | O43: HT | P43: 44999 | Q43: 23 | R43: 29 | S43: 45873 | T43: 0 | U43: A | V43: T3.26 | X43: Có nguyện vọng | Y43: Đã HTCT | AF43: Dự kiến đủ điều kiện | AH43: ELC
A44: =IF(L44="","",COUNTA($L44:L$5)) -> 40 | B44: Quynhtnn | C44: Khanhntk | D44: DNBD | E44: 17 | F44: B | G44: 19C-42-49.6-02813 | H44: BDNBD617 | I44: quocnpa | J44: Nguyễn Phan Anh | K44: Quốc | L44: 33692 | M44: Nam | N44: Hợp lệ | O44: HT | P44: 43712 | Q44: 0 | R44: 36 | S44: 44808 | T44: 0 | U44: A | V44: T3.26 | X44: Có nguyện vọng | Y44: Đã HTCT | AF44: Dự kiến đủ điều kiện | AH44: ĐN
A45: =IF(L45="","",COUNTA($L45:L$5)) -> 41 | B45: Quynhtnn | C45: Khanhntk | D45: DNBD | E45: 17 | F45: C | G45: 22C1037D0497 | H45: CDNBD617 | I45: khoapla | J45: Phạm Lê Anh | K45: Khoa | L45: 33126 | M45: Nam | N45: Hợp lệ | O45: HT | P45: 44641 | Q45: 0 | R45: 36 | S45: 45737 | T45: 0 | U45: A | V45: T3.26 | X45: Có nguyện vọng | Y45: Đã HTCT | AF45: Dự kiến đủ điều kiện | AH45: ĐN
A46: =IF(L46="","",COUNTA($L46:L$5)) -> 42 | B46: Quynhtnn | C46: Khanhntk | D46: DNP | E46: 13 | F46: B | G46: 20C-42-55.0-00394 | H46: BDNP513 | I46: hieupv005 | J46: Phùng Văn | K46: Hiếu | L46: 34297 | M46: Nam | N46: Hợp lệ | O46: HT | P46: 43865 | Q46: 0 | R46: 36 | S46: 44961 | T46: 0 | U46: A | V46: KH CŨ | X46: Có nguyện vọng | Y46: Đã HTCT | AF46: Dự kiến đủ điều kiện | AH46: ĐN
A47: =IF(L47="","",COUNTA($L47:L$5)) -> 43 | B47: Quynhtnn | C47: Khanhntk | D47: DNP | E47: 13 | F47: B | G47: 20C-42-55.0-02456 | H47: BDNP213 | I47: taytv | J47: Trương Văn | K47: Tây | L47: 33173 | M47: Nam | N47: Chờ hoàn thiện | O47: HT | P47: 43991 | Q47: 0 | R47: 36 | S47: 45086 | T47: 0 | U47: A | V47: KH CŨ | X47: Có nguyện vọng | Y47: Đã HTCT | AF47: Dự kiến đủ điều kiện | AH47: ĐN
A48: =IF(L48="","",COUNTA($L48:L$5)) -> 44 | B48: Quynhtnn | C48: Khanhntk | D48: DNP | E48: 13 | F48: B | G48: 20C-42-55.0-01992 | H48: BDNP513 | I48: tuanla011 | J48: Lê Anh | K48: Tuấn | L48: 36659 | M48: Nam | N48: Hợp lệ | O48: HT | P48: 43962 | Q48: 0 | R48: 36 | S48: 45057 | T48: 0 | U48: A | V48: KH CŨ | X48: Có nguyện vọng | Y48: Đã HTCT | AF48: Dự kiến đủ điều kiện | AH48: ĐN
... A70: =IF(L70="","",COUNTA($L70:L$5)) -> 66 | B70: Quynhtnn | C70: Khanhntk | D70: DNP | E70: 17 | F70: H | G70: 22C5004D2223 | H70: HDNP617 | I70: ydh | J70: Đặng Hữu | K70: Ý | L70: 36357 | M70: Nam | N70: Chờ hoàn thiện | O70: HT | P70: 44712 | Q70: 0 | R70: 36 | S70: 45808 | T70: 0 | U70: A | V70: T3.26 | X70: Có nguyện vọng | Y70: Nợ môn_Không TN | AF70: Không đủ điều kiện | AH70: ĐN
A71: =IF(L71="","",COUNTA($L71:L$5)) -> 67 | B71: Sangpn | C71: Khanhntk | D71: DNVT | E71: 17 | F71: A | G71: 22C4102H2737 | H71: ADNVT617 | I71: cuongdh004 | J71: Đặng Hữu | K71: Cường | L71: 33955 | M71: Nam | N71: Hợp lệ | O71: HT | P71: 44742 | R71: 36 | S71: 45838 | T71: 46082 | U71: A | V71: T3.26 | X71: Có nguyện vọng | Y71: Đã HTCT | Z71: Đã HTCT | AF71: Dự kiến đủ điều kiện | AH71: ĐN
A72: =IF(L72="","",COUNTA($L72:L$5)) -> 68 | B72: Sangpn | C72: Khanhntk | D72: DNVT | E72: 17 | F72: A | G72: 22C4102H2727 | H72: ADNVT617 | I72: duonglt007 | J72: Lương Thị | K72: Đương | L72: 36757 | M72: Nữ | N72: Hợp lệ | O72: HT | P72: 44742 | R72: 36 | S72: 45838 | T72: 46082 | U72: A | V72: T3.26 | X72: Có nguyện vọng | Y72: Đã HTCT | Z72: Đã HTCT | AF72: Dự kiến đủ điều kiện | AH72: ĐN
A73: =IF(L73="","",COUNTA($L73:L$5)) -> 69 | B73: Sangpn | C73: Khanhntk | D73: DNVT | E73: 17 | F73: A | G73: 22C4102H1107 | H73: ADNVT617 | I73: hangptm002 | J73: Phan Thị Mỹ | K73: Hằng | L73: 35691 | M73: Nữ | N73: Hợp lệ | O73: HT | P73: 44658 | R73: 36 | S73: 45754 | T73: 46082 | U73: A | V73: T3.26 | X73: Có nguyện vọng | Y73: Đã HTCT | Z73: Đã HTCT | AF73: Dự kiến đủ điều kiện | AH73: ĐN
A74: =IF(L74="","",COUNTA($L74:L$5)) -> 70 | B74: Sangpn | C74: Khanhntk | D74: DNVT | E74: 17 | F74: A | G74: 22C4102H2736 | H74: ADNVT617 | I74: khuyenntn | J74: Nguyễn Thị Nhã | K74: Khuyên | L74: 34392 | M74: Nữ | N74: Hợp lệ | O74: HT | P74: 44742 | R74: 36 | S74: 45838 | T74: 46082 | U74: A | V74: T3.26 | X74: Có nguyện vọng | Y74: Đã HTCT | Z74: Đã HTCT | AF74: Dự kiến đủ điều kiện | AH74: ĐN
A75: =IF(L75="","",COUNTA($L75:L$5)) -> 71 | B75: Sangpn | C75: Khanhntk | D75: DNVT | E75: 17 | F75: A | G75: 22C4102H1748 | H75: ADNVT317 | I75: tambt006 | J75: Bùi Thị | K75: Tâm | L75: 34802 | M75: Nữ | N75: Hợp lệ | O75: HT | P75: 44698 | Q75: 28 | R75: 28 | S75: 45552 | T75: 0 | U75: A | V75: KH CŨ | X75: Có nguyện vọng | Y75: Nợ môn_Không TN | Z75: Nợ môn | AF75: Không đủ điều kiện | AH75: ĐN
A76: =IF(L76="","",COUNTA($L76:L$5)) -> 72 | B76: Sangpn | C76: Khanhntk | D76: DNVT | E76: 17 | F76: A | G76: 22C4102H2739 | H76: ADNVT617 | I76: tuyetpt005 | J76: Phạm Thị | K76: Tuyết | L76: 31640 | M76: Nữ | N76: Hợp lệ | O76: HT | P76: 44742 | R76: 36 | S76: 45838 | T76: 46082 | U76: A | V76: T3.26 | X76: Có nguyện vọng | Y76: Đã HTCT | Z76: Đã HTCT | AF76: Dự kiến đủ điều kiện | AH76: ĐN
A77: =IF(L77="","",COUNTA($L77:L$5)) -> 73 | B77: Sangpn | C77: Khanhntk | D77: DNVT | E77: 17 | F77: B | G77: 22C4202H2756 | H77: BDNVT617 | I77: donglv002 | J77: Lý Văn | K77: Đông | L77: 35251 | M77: Nam | N77: Hợp lệ | O77: HT | P77: 44742 | R77: 36 | S77: 45838 | T77: 46082 | U77: A | V77: T3.26 | X77: Có nguyện vọng | Y77: Đã HTCT | AF77: Dự kiến đủ điều kiện | AH77: ĐN
A78: =IF(L78="","",COUNTA($L78:L$5)) -> 74 | B78: Sangpn | C78: Khanhntk | D78: DNVT | E78: 17 | F78: B | G78: 22C1002H1725 | H78: BDNVT617 | I78: hieudc | J78: Đoàn Công | K78: Hiếu | L78: 32246 | M78: Nam | N78: Hợp lệ | O78: HT | P78: 44698 | R78: 36 | S78: 45794 | T78: 46082 | U78: A | V78: T3.26 | X78: Có nguyện vọng | Y78: Nợ môn_Không TN | Z78: Nợ BA03, EG35, EG38, EG41 | AF78: Không đủ điều kiện | AH78: ĐN
A79: =IF(L79="","",COUNTA($L79:L$5)) -> 75 | B79: Sangpn | C79: Khanhntk | D79: DNVT | E79: 17 | F79: B | G79: 22C4202H2750 | H79: BDNVT617 | I79: hieunv020 | J79: Nguyễn Văn | K79: Hiếu | L79: 32775 | M79: Nam | N79: Hợp lệ | O79: HT | P79: 44742 | R79: 36 | S79: 45838 | T79: 46082 | U79: A | V79: T3.26 | X79: Có nguyện vọng | Y79: Nợ môn_Không TN | Z79: Nợ EG09.1, EG09.3 | AF79: Không đủ điều kiện | AH79: ĐN
A80: =IF(L80="","",COUNTA($L80:L$5)) -> 76 | B80: Sangpn | C80: Khanhntk | D80: DNVT | E80: 17 | F80: B | G80: 22C4202H1150 | H80: BDNVT617 | I80: hungdm017 | J80: Đỗ Mạnh | K80: Hùng | L80: 32522 | M80: Nam | N80: Hợp lệ | O80: HT | P80: 44658 | R80: 36 | S80: 45754 | T80: 46082 | U80: A | V80: T3.26 | X80: Có nguyện vọng | Y80: Đã HTCT | AF80: Dự kiến đủ điều kiện | AH80: ĐN
A81: =IF(L81="","",COUNTA($L81:L$5)) -> 77 | B81: Sangpn | C81: Khanhntk | D81: DNVT | E81: 17 | F81: B | G81: 22C4202H1765 | H81: BDNVT617 | I81: huongbtt002 | J81: Bùi Trần Thanh | K81: Hương | L81: 31783 | M81: Nữ | N81: Hợp lệ | O81: HT | P81: 44698 | R81: 36 | S81: 45794 | T81: 46082 | U81: A | V81: T3.26 | X81: Có nguyện vọng | Y81: Đã HTCT | AF81: Dự kiến đủ điều kiện | AH81: ĐN
A82: =IF(L82="","",COUNTA($L82:L$5)) -> 78 | B82: Sangpn | C82: Khanhntk | D82: DNVT | E82: 17 | F82: B | G82: 22C4202H1766 | H82: BDNVT617 | I82: linhvtp | J82: Vũ Thị Phương | K82: Linh | L82: 36228 | M82: Nữ | N82: Hợp lệ | O82: HT | P82: 44698 | R82: 36 | S82: 45794 | T82: 46082 | U82: A | V82: T3.26 | X82: Có nguyện vọng | Y82: Đã HTCT | AF82: Dự kiến đủ điều kiện | AH82: ĐN
A83: =IF(L83="","",COUNTA($L83:L$5)) -> 79 | B83: Sangpn | C83: Khanhntk | D83: DNVT | E83: 17 | F83: B | G83: 22C4202H2742 | H83: BDNVT617 | I83: longnvh | J83: Nguyễn Võ Hoàng | K83: Long | L83: 34378 | M83: Nam | N83: Hợp lệ | O83: HT | P83: 44742 | R83: 36 | S83: 45838 | T83: 46082 | U83: A | V83: T3.26 | X83: Có nguyện vọng | Y83: Đã HTCT | AF83: Dự kiến đủ điều kiện | AH83: ĐN
A84: =IF(L84="","",COUNTA($L84:L$5)) -> 80 | B84: Sangpn | C84: Khanhntk | D84: DNVT | E84: 17 | F84: B | G84: 22C4202H1763 | H84: BDNVT617 | I84: phongnt013 | J84: Nguyễn Tuấn | K84: Phong | L84: 33606 | M84: Nam | N84: Hợp lệ | O84: HT | P84: 44698 | R84: 36 | S84: 45794 | T84: 46082 | U84: A | V84: T3.26 | X84: Có nguyện vọng | Y84: Đã HTCT | AF84: Dự kiến đủ điều kiện | AH84: ĐN
A85: =IF(L85="","",COUNTA($L85:L$5)) -> 81 | B85: Sangpn | C85: Khanhntk | D85: DNVT | E85: 17 | F85: B | G85: 22C4202H1761 | H85: BDNVT617 | I85: phudk | J85: Dương Kim | K85: Phú | L85: 28201 | M85: Nam | N85: Hợp lệ | O85: HT | P85: 44698 | R85: 36 | S85: 45794 | T85: 46082 | U85: A | V85: T3.26 | X85: Có nguyện vọng | Y85: Đã HTCT | AF85: Dự kiến đủ điều kiện | AH85: ĐN
A86: =IF(L86="","",COUNTA($L86:L$5)) -> 82 | B86: Sangpn | C86: Khanhntk | D86: DNVT | E86: 17 | F86: B | G86: 22C4202H1752 | H86: BDNVT617 | I86: quyencc | J86: Cổ Chí | K86: Quyền | L86: 33959 | M86: Nam | N86: Hợp lệ | O86: HT | P86: 44698 | R86: 36 | S86: 45794 | T86: 46082 | U86: A | V86: T3.26 | X86: Có nguyện vọng | Y86: Đã HTCT | AF86: Dự kiến đủ điều kiện | AH86: ĐN
A87: =IF(L87="","",COUNTA($L87:L$5)) -> 83 | B87: Sangpn | C87: Khanhntk | D87: DNVT | E87: 17 | F87: B | G87: 22C4202H1146 | H87: BDNVT617 | I87: taitd002 | J87: Trần Đức | K87: Tài | L87: 37316 | M87: Nam | N87: Hợp lệ | O87: HT | P87: 44658 | R87: 36 | S87: 45754 | T87: 46082 | U87: A | V87: T3.26 | X87: Có nguyện vọng | Y87: Đã HTCT | AF87: Dự kiến đủ điều kiện | AH87: ĐN
A88: =IF(L88="","",COUNTA($L88:L$5)) -> 84 | B88: Sangpn | C88: Khanhntk | D88: DNVT | E88: 17 | F88: B | G88: 22C4202H2767 | H88: BDNVT617 | I88: thachnt003 | J88: Nguyễn Thái | K88: Thạch | L88: 30828 | M88: Nam | N88: Chưa TĐB | O88: HT | P88: 44742 | R88: 36 | S88: 45838 | T88: 46082 | U88: A | V88: T3.26 | X88: Có nguyện vọng | Y88: Đã HTCT | AF88: Dự kiến đủ điều kiện | AH88: ĐN
A89: =IF(L89="","",COUNTA($L89:L$5)) -> 85 | B89: Sangpn | C89: Khanhntk | D89: DNVT | E89: 17 | F89: B | G89: 22C4202H2763 | H89: BDNVT617 | I89: thaoptt007 | J89: Phạm Thị Thanh | K89: Thảo | L89: 36610 | M89: Nữ | N89: Hợp lệ | O89: HT | P89: 44742 | R89: 36 | S89: 45838 | T89: 46082 | U89: A | V89: T3.26 | X89: Có nguyện vọng | Y89: Đã HTCT | AF89: Dự kiến đủ điều kiện | AH89: ĐN
A90: =IF(L90="","",COUNTA($L90:L$5)) -> 86 | B90: Sangpn | C90: Khanhntk | D90: DNVT | E90: 17 | F90: B | G90: 22C4202H2754 | H90: BDNVT617 | I90: thanghs | J90: Hồ Sơn | K90: Thắng | L90: 32628 | M90: Nam | N90: Hợp lệ | O90: HT | P90: 44742 | R90: 36 | S90: 45838 | T90: 46082 | U90: A | V90: T3.26 | X90: Có nguyện vọng | Y90: Nợ môn_Không TN | Z90: Nợ môn | AF90: Không đủ điều kiện | AH90: ĐN
A91: =IF(L91="","",COUNTA($L91:L$5)) -> 87 | B91: Sangpn | C91: Khanhntk | D91: DNVT | E91: 17 | F91: B | G91: 22C4202H1775 | H91: BDNVT617 | I91: thinhnpp | J91: Nguyễn Phan Phúc | K91: Thịnh | L91: 36546 | M91: Nam | N91: Hợp lệ | O91: HT | P91: 44698 | R91: 36 | S91: 45794 | T91: 46082 | U91: A | V91: T3.26 | X91: Có nguyện vọng | Y91: Nợ môn_Không TN | Z91: Nợ BA19 | AF91: Không đủ điều kiện | AH91: ĐN
A92: =IF(L92="","",COUNTA($L92:L$5)) -> 88 | B92: Sangpn | C92: Khanhntk | D92: DNVT | E92: 17 | F92: B | G92: 22C4202H2744 | H92: BDNVT617 | I92: tramtnt002 | J92: Trần Ngọc Thùy | K92: Trâm | L92: 34225 | M92: Nữ | N92: Hợp lệ | O92: HT | P92: 44742 | R92: 36 | S92: 45838 | T92: 46082 | U92: A | V92: T3.26 | X92: Có nguyện vọng | Y92: Đã HTCT | AF92: Dự kiến đủ điều kiện | AH92: ĐN
A93: =IF(L93="","",COUNTA($L93:L$5)) -> 89 | B93: Sangpn | C93: Khanhntk | D93: DNVT | E93: 17 | F93: B | G93: 22C4202H2765 | H93: BDNVT617 | I93: trinhtc | J93: Trần Cẩm | K93: Trinh | L93: 36716 | M93: Nữ | N93: Hợp lệ | O93: HT | P93: 44742 | R93: 36 | S93: 45838 | T93: 46082 | U93: A | V93: T3.26 | X93: Có nguyện vọng | Y93: Đã HTCT | AF93: Dự kiến đủ điều kiện | AH93: ĐN
A94: =IF(L94="","",COUNTA($L94:L$5)) -> 90 | B94: Sangpn | C94: Khanhntk | D94: DNVT | E94: 17 | F94: B | G94: 22C4202H1158 | H94: BDNVT417 | I94: truongpt002 | J94: Phạm Thị | K94: Trường | L94: 31280 | M94: Nữ | N94: Hợp lệ | O94: HT | P94: 44658 | Q94: 19 | R94: 30 | S94: 45603 | T94: 0 | U94: A | V94: KH CŨ | X94: Có nguyện vọng | Y94: Nợ môn_Không TN | Z94: Nợ BA09, BA28, EG21 | AF94: Không đủ điều kiện | AH94: ĐN
A95: =IF(L95="","",COUNTA($L95:L$5)) -> 91 | B95: Sangpn | C95: Khanhntk | D95: DNVT | E95: 17 | F95: B | G95: 22C4202H2747 | H95: BDNVT617 | I95: tuanlh005 | J95: Lê Hoàng | K95: Tuấn | L95: 34643 | M95: Nam | N95: Hợp lệ | O95: HT | P95: 44742 | R95: 36 | S95: 45838 | T95: 46082 | U95: A | V95: T3.26 | X95: Có nguyện vọng | Y95: Đã HTCT | AF95: Dự kiến đủ điều kiện | AH95: ĐN
A96: =IF(L96="","",COUNTA($L96:L$5)) -> 92 | B96: Sangpn | C96: Khanhntk | D96: DNVT | E96: 17 | F96: B | G96: 22C4202H1149 | H96: BDNVT617 | I96: tuanna037 | J96: Nguyễn Anh | K96: Tuấn | L96: 30561 | M96: Nam | N96: Hợp lệ | O96: HT | P96: 44658 | R96: 36 | S96: 45754 | T96: 46082 | U96: A | V96: T3.26 | X96: Có nguyện vọng | Y96: Đã HTCT | AF96: Dự kiến đủ điều kiện | AH96: ĐN
A97: =IF(L97="","",COUNTA($L97:L$5)) -> 93 | B97: Sangpn | C97: Khanhntk | D97: DNVT | E97: 17 | F97: B | G97: 22C4202H1754 | H97: BDNVT617 | I97: tungdx | J97: Đỗ Xuân | K97: Tùng | L97: 29911 | M97: Nam | N97: Hợp lệ | O97: HT | P97: 44698 | R97: 36 | S97: 45794 | T97: 46082 | U97: A | V97: T3.26 | X97: Có nguyện vọng | Y97: Đã HTCT | AF97: Dự kiến đủ điều kiện | AH97: ĐN
A98: =IF(L98="","",COUNTA($L98:L$5)) -> 94 | B98: Sangpn | C98: Khanhntk | D98: DNVT | E98: 17 | F98: B | G98: 22C4202H1773 | H98: BDNVT617 | I98: vynn | J98: Ngô Nhựt | K98: Vy | L98: 36684 | M98: Nữ | N98: Hợp lệ | O98: HT | P98: 44698 | R98: 36 | S98: 45794 | T98: 46082 | U98: A | V98: T3.26 | X98: Có nguyện vọng | Y98: Nợ môn_Không TN | Z98: Nợ BA19 | AF98: Không đủ điều kiện | AH98: ĐN
A99: =IF(L99="","",COUNTA($L99:L$5)) -> 95 | B99: Sangpn | C99: Khanhntk | D99: DNVT | E99: 17 | F99: C | G99: 22C1002H1099 | H99: CDNVT617 | I99: anhnt097 | J99: Nguyễn Tuấn | K99: Anh | L99: 36268 | M99: Nam | N99: Hợp lệ | O99: HT | P99: 44658 | R99: 36 | S99: 45754 | T99: 46082 | U99: A | V99: T3.26 | X99: Có nguyện vọng | Y99: Nợ môn_Không TN | Z99: Nợ IT43 | AF99: Không đủ điều kiện | AH99: ĐN
A100: =IF(L100="","",COUNTA($L100:L$5)) -> 96 | B100: Sangpn | C100: Khanhntk | D100: DNVT | E100: 17 | F100: C | G100: 22C1002H2722 | H100: CDNVT617 | I100: duynca | J100: Nguyễn Công Anh | K100: Duy | L100: 34377 | M100: Nam | N100: Hợp lệ | O100: HT | P100: 44742 | R100: 36 | S100: 45838 | T100: 46082 | U100: A | V100: T3.26 | X100: Có nguyện vọng | Y100: Đã HTCT | AF100: Dự kiến đủ điều kiện | AH100: ĐN
A101: =IF(L101="","",COUNTA($L101:L$5)) -> 97 | B101: Sangpn | C101: Khanhntk | D101: DNVT | E101: 17 | F101: C | G101: 22C1002H2717 | H101: CDNVT617 | I101: trontv | J101: Trương Văn | K101: Trơn | L101: 33536 | M101: Nam | N101: Hợp lệ | O101: HT | P101: 44742 | R101: 36 | S101: 45838 | T101: 46082 | U101: A | V101: T3.26 | X101: Có nguyện vọng | Y101: Nợ môn_Không TN | Z101: Nợ IT43, IT60, EG11, EG45 | AF101: Không đủ điều kiện | AH101: ĐN
A102: =IF(L102="","",COUNTA($L102:L$5)) -> 98 | B102: Sangpn | C102: Khanhntk | D102: DNVT | E102: 17 | F102: C | G102: 22C1002H1098 | H102: CDNVT617 | I102: vietnt011 | J102: Nguyễn Trung | K102: Việt | L102: 34595 | M102: Nam | N102: Chưa TĐB | O102: HT | P102: 44658 | R102: 36 | S102: 45754 | T102: 46082 | U102: A | V102: T3.26 | X102: Có nguyện vọng | Y102: Nợ môn_Không TN | Z102: Nợ IT43, IT60 | AF102: Không đủ điều kiện | AH102: ĐN
A103: =IF(L103="","",COUNTA($L103:L$5)) -> 99 | B103: Sangpn | C103: Khanhntk | D103: DNVT | E103: 17 | F103: D | G103: 22C4502H2862 | H103: DDNVT617 | I103: anhttn012 | J103: Trương Thị Ngọc | K103: Anh | L103: 34941 | M103: Nữ | N103: Hợp lệ | O103: HT | P103: 44742 | R103: 36 | S103: 45838 | T103: 46082 | U103: A | V103: T3.26 | X103: Có nguyện vọng | Y103: Đã HTCT | AF103: Dự kiến đủ điều kiện | AH103: ĐN
A104: =IF(L104="","",COUNTA($L104:L$5)) -> 100 | B104: Sangpn | C104: Khanhntk | D104: DNVT | E104: 17 | F104: D | G104: 22C4502H1841 | H104: DDNVT617 | I104: duynn007 | J104: Nguyễn Nhựt | K104: Duy | L104: 35594 | M104: Nam | N104: Hợp lệ | O104: HT | P104: 44698 | R104: 36 | S104: 45794 | T104: 46082 | U104: A | V104: T3.26 | X104: Có nguyện vọng | Y104: Nợ môn_Không TN | Z104: Nợ EG39 | AF104: Không đủ điều kiện | AH104: ĐN
A105: =IF(L105="","",COUNTA($L105:L$5)) -> 101 | B105: Sangpn | C105: Khanhntk | D105: DNVT | E105: 17 | F105: E | G105: 22C5102H1126 | H105: EDNVT617 | I105: dungnv037 | J105: Nguyễn Văn | K105: Dũng | L105: 29502 | M105: Nam | N105: Hợp lệ | O105: HT | P105: 44658 | R105: 36 | S105: 45754 | T105: 46082 | U105: A | V105: T3.26 | X105: Có nguyện vọng | Y105: Nợ môn_Không TN | Z105: Nợ EL72 | AF105: Không đủ điều kiện | AH105: ĐN
A106: =IF(L106="","",COUNTA($L106:L$5)) -> 102 | B106: Sangpn | C106: Khanhntk | D106: DNVT | E106: 17 | F106: E | G106: 22C5102H1832 | H106: EDNVT617 | I106: hangntn005 | J106: Nguyễn Thị Ngọc | K106: Hằng | L106: 31701 | M106: Nữ | N106: Hợp lệ | O106: HT | P106: 44698 | R106: 36 | S106: 45794 | T106: 46082 | U106: A | V106: T3.26 | X106: Có nguyện vọng | Y106: Đã HTCT | AF106: Dự kiến đủ điều kiện | AH106: ĐN
A107: =IF(L107="","",COUNTA($L107:L$5)) -> 103 | B107: Sangpn | C107: Khanhntk | D107: DNVT | E107: 17 | F107: E | G107: 22C5102H1833 | H107: EDNVT417 | I107: huytq011 | J107: Trần Quang | K107: Huy | L107: 31519 | M107: Nam | N107: Hợp lệ | O107: HT | P107: 44698 | Q107: 17 | R107: 31 | S107: 45643 | T107: 0 | U107: A | V107: KH CŨ | X107: Có nguyện vọng | Y107: Nợ môn_Không TN | Z107: Nợ EL14, EL18, EL24, EL27 | AF107: Không đủ điều kiện | AH107: ĐN
A108: =IF(L108="","",COUNTA($L108:L$5)) -> 104 | B108: Sangpn | C108: Khanhntk | D108: DNVT | E108: 17 | F108: E | G108: 22C5102H1831 | H108: EDNVT617 | I108: thanhth006 | J108: Trần Hoài | K108: Thanh | L108: 31161 | M108: Nữ | N108: Hợp lệ | O108: HT | P108: 44698 | R108: 36 | S108: 45794 | T108: 46082 | U108: A | V108: T3.26 | X108: Có nguyện vọng | Y108: Đã HTCT | AF108: Dự kiến đủ điều kiện | AH108: ĐN
A109: =IF(L109="","",COUNTA($L109:L$5)) -> 105 | B109: Sangpn | C109: Khanhntk | D109: DNVT | E109: 17 | F109: E | G109: 22C5102H1837 | H109: EDNVT617 | I109: thihtp | J109: Hồ Thị Phương | K109: Thi | L109: 35321 | M109: Nữ | N109: Hợp lệ | O109: HT | P109: 44698 | R109: 36 | S109: 45794 | T109: 46082 | U109: A | V109: T3.26 | X109: Có nguyện vọng | Y109: Nợ môn_Không TN | Z109: Nợ EG09.3, EL27, EL52 | AF109: Không đủ điều kiện | AH109: ĐN
A110: =IF(L110="","",COUNTA($L110:L$5)) -> 106 | B110: Sangpn | C110: Khanhntk | D110: DNVT | E110: 17 | F110: E | G110: 22C5102H2845 | H110: EDNVT617 | I110: thulta | J110: Lê Thị Ánh | K110: Thu | L110: 34507 | M110: Nữ | N110: Hợp lệ | O110: HT | P110: 44742 | R110: 36 | S110: 45838 | T110: 46082 | U110: A | V110: T3.26 | X110: Có nguyện vọng | Y110: Nợ môn_Không TN | Z110: Nợ EL70 | AF110: Không đủ điều kiện | AH110: ĐN
A111: =IF(L111="","",COUNTA($L111:L$5)) -> 107 | B111: Sangpn | C111: Khanhntk | D111: DNVT | E111: 17 | F111: E | G111: 22C5102H1830 | H111: EDNVT617 | I111: tungdt022 | J111: Đinh Tấn | K111: Tùng | L111: 30089 | M111: Nam | N111: Hợp lệ | O111: HT | P111: 44698 | R111: 36 | S111: 45794 | T111: 46082 | U111: A | V111: T3.26 | X111: Có nguyện vọng | Y111: Đã HTCT | AF111: Dự kiến đủ điều kiện | AH111: ĐN
A112: =IF(L112="","",COUNTA($L112:L$5)) -> 108 | B112: Sangpn | C112: Khanhntk | D112: DNVT | E112: 17 | F112: F | G112: 22C7102H2780 | H112: FDNVT417 | I112: anhkh002 | J112: Kiều Hà | K112: Anh | L112: 34914 | M112: Nữ | N112: Hợp lệ | O112: HT | P112: 44742 | Q112: 18 | R112: 31 | S112: 45687 | T112: 0 | U112: A | V112: KH CŨ | X112: Có nguyện vọng | Y112: Nợ môn_Không TN | Z112: Nợ EN31, EN35, EN39 | AF112: Không đủ điều kiện | AH112: ĐN
A113: =IF(L113="","",COUNTA($L113:L$5)) -> 109 | B113: Sangpn | C113: Khanhntk | D113: DNVT | E113: 17 | F113: F | G113: 22C7102H1786 | H113: FDNVT617 | I113: anhntn041 | J113: Nguyễn Thị Ngọc | K113: Anh | L113: 33764 | M113: Nữ | N113: Hợp lệ | O113: HT | P113: 44698 | R113: 36 | S113: 45794 | T113: 46082 | U113: A | V113: T3.26 | X113: Có nguyện vọng | Y113: Nợ môn_Không TN | Z113: Nợ môn | AF113: Không đủ điều kiện | AH113: ĐN
A114: =IF(L114="","",COUNTA($L114:L$5)) -> 110 | B114: Sangpn | C114: Khanhntk | D114: DNVT | E114: 17 | F114: F | G114: 22C7102H1806 | H114: FDNVT617 | I114: anhttv014 | J114: Trịnh Thị Vân | K114: Anh | L114: 35565 | M114: Nữ | N114: Hợp lệ | O114: HT | P114: 44698 | R114: 36 | S114: 45794 | T114: 46082 | U114: A | V114: T3.26 | X114: Có nguyện vọng | Y114: Đã HTCT | Z114: Đã HTCT | AF114: Dự kiến đủ điều kiện | AH114: ĐN
A115: =IF(L115="","",COUNTA($L115:L$5)) -> 111 | B115: Sangpn | C115: Khanhntk | D115: DNVT | E115: 17 | F115: F | G115: 22C7102H1804 | H115: FDNVT617 | I115: daodth002 | J115: Đàm Thị Hồng | K115: Đào | L115: 33153 | M115: Nữ | N115: Hợp lệ | O115: HT | P115: 44698 | R115: 36 | S115: 45794 | T115: 46082 | U115: A | V115: T3.26 | X115: Có nguyện vọng | Y115: Đã HTCT | Z115: Đã HTCT | AF115: Dự kiến đủ điều kiện | AH115: ĐN
A116: =IF(L116="","",COUNTA($L116:L$5)) -> 112 | B116: Sangpn | C116: Khanhntk | D116: DNVT | E116: 17 | F116: F | G116: 22C7102H2806 | H116: FDNVT417 | I116: hienntt043 | J116: Nguyễn Thị Thu | K116: Hiền | L116: 32840 | M116: Nữ | N116: Hợp lệ | O116: HT | P116: 44742 | Q116: 13 | R116: 32 | S116: 45746 | T116: 0 | U116: A | V116: KH CŨ | X116: Có nguyện vọng | Y116: Nợ môn_Không TN | Z116: Nợ EN29 | AF116: Không đủ điều kiện | AH116: ĐN
A117: =IF(L117="","",COUNTA($L117:L$5)) -> 113 | B117: Sangpn | C117: Khanhntk | D117: DNVT | E117: 17 | F117: F | G117: 22C7101H1455 | H117: FDNVT417 | I117: hieuptx | J117: Phan Thị Xuân | K117: Hiếu | L117: 34139 | M117: Nữ | N117: Hợp lệ | O117: HT | P117: 44685 | Q117: 11 | R117: 33 | S117: 45692 | T117: 46082 | U117: A | V117: KH CŨ | X117: Có nguyện vọng | Y117: Đã HTCT | Z117: Đã HTCT | AF117: Dự kiến đủ điều kiện | AH117: ĐN
A118: =IF(L118="","",COUNTA($L118:L$5)) -> 114 | B118: Sangpn | C118: Khanhntk | D118: DNVT | E118: 17 | F118: F | G118: 22C7102H1789 | H118: FDNVT417 | I118: hopt | J118: Phạm Trọng | K118: Họ | L118: 34337 | M118: Nam | N118: Hợp lệ | O118: HT | P118: 44698 | Q118: 16 | R118: 31 | S118: 45674 | T118: 0 | U118: A | V118: KH CŨ | X118: Có nguyện vọng | Y118: Nợ môn_Không TN | Z118: Nợ môn | AF118: Không đủ điều kiện | AH118: ĐN
A119: =IF(L119="","",COUNTA($L119:L$5)) -> 115 | B119: Sangpn | C119: Khanhntk | D119: DNVT | E119: 17 | F119: F | G119: 22C7102H1816 | H119: FDNVT617 | I119: hont003 | J119: Nguyễn Thái | K119: Hồ | L119: 35293 | M119: Nam | N119: Chưa TĐB | O119: HT | P119: 44698 | R119: 36 | S119: 45794 | T119: 46082 | U119: A | V119: T3.26 | X119: Có nguyện vọng | Y119: Nợ môn_Không TN | Z119: Nợ EN23, EG46 | AF119: Không đủ điều kiện | AH119: ĐN
A120: =IF(L120="","",COUNTA($L120:L$5)) -> 116 | B120: Sangpn | C120: Khanhntk | D120: DNVT | E120: 17 | F120: F | G120: 22C7102H0494 | H120: FDNVT617 | I120: hungtd015 | J120: Trương Đức | K120: Hưng | L120: 34035 | M120: Nam | N120: Hợp lệ | O120: HT | P120: 44641 | R120: 36 | S120: 45737 | T120: 46082 | U120: A | V120: T3.26 | X120: Có nguyện vọng | Y120: Đã HTCT | Z120: Đã HTCT | AF120: Dự kiến đủ điều kiện | AH120: ĐN
A121: =IF(L121="","",COUNTA($L121:L$5)) -> 117 | B121: Sangpn | C121: Khanhntk | D121: DNVT | E121: 17 | F121: F | G121: 22C7102H2771 | H121: FDNVT617 | I121: maidtt008 | J121: Đặng Thị Tuyết | K121: Mai | L121: 37166 | M121: Nữ | N121: Hợp lệ | O121: HT | P121: 44742 | R121: 36 | S121: 45838 | T121: 46082 | U121: A | V121: T3.26 | X121: Có nguyện vọng | Y121: Đã HTCT | Z121: Đã HTCT | AF121: Dự kiến đủ điều kiện | AH121: ĐN
A122: =IF(L122="","",COUNTA($L122:L$5)) -> 118 | B122: Sangpn | C122: Khanhntk | D122: DNVT | E122: 17 | F122: F | G122: 22C7102H2782 | H122: FDNVT617 | I122: mainh | J122: Nguyễn Huỳnh | K122: Mai | L122: 33328 | M122: Nữ | N122: Hợp lệ | O122: HT | P122: 44742 | R122: 36 | S122: 45838 | T122: 46082 | U122: A | V122: T3.26 | X122: Có nguyện vọng | Y122: Đã HTCT | Z122: Đã HTCT | AF122: Dự kiến đủ điều kiện | AH122: ĐN
...

Sheet CHECK ĐƠN T12.2025
A1: STT | B1: Quản lý sinh viên | C1: Giáo vụ | D1: Tài khoản | E1: Mã sinh viên | F1: Họ và tên đệm | G1: Tên | H1: Ngày sinh | I1: Giới tính | J1: Khóa | K1: Tên lớp | L1: Tên ngành | M1: Đơn vị phối hợp (Mã đơn vị) | N1: Tên đơn vị phối hợp | O1: Trạng thái QLSV dự kiến T12/2025 | P1: Đã có đơn scan | Q1: Bản cứng | R1: Trường hợp trước 10h sáng mai chưa có bản cứng. Tự cá nhân QLSV báo cáo Ban Lãnh đạo Viện.
A2: 1 | B2: Anhlt | C2: Quynhtnn | D2: lamvn | E2: 20C-50-55.0-03293 | F2: Võ Ngọc | G2: Lâm | H2: 31924 | I2: Nam | J2: 13 | K2: HDNP513 | L2: Luật | M2: DNP | N2: Trung tâm Đại học Mở Hà Nội tại Đà Nẵng | O2: TH | P2: x
A3: 2 | B3: Anhlt | C3: Sangpn | D3: hienhh002 | E3: 21C7102H0573 | F3: Hồ Hữu | G3: Hiền | H3: 33867 | I3: Nam | J3: 16 | K3: FDNVT516 | L3: Ngôn ngữ Anh | M3: DNVT | N3: Trường Trung cấp Vạn Tường | O3: TH | P3: x
A4: 3 | B4: Anhlt | C4: Sangpn | D4: locddx | E4: 21C-50-55.4-04204 | F4: Đặng Đoàn Xuân | G4: Lộc | H4: 29855 | I4: Nữ | J4: 16 | K4: HDNVT516 | L4: Luật | M4: DNVT | N4: Trường Trung cấp Vạn Tường | O4: TH | P4: x
A5: 4 | B5: Hungdv | C5: Trinhptt | D5: 24C7201P1189 | E5: 24C7201P1189 | F5: Bùi Thị | G5: Phượng | H5: 36979 | I5: Nữ | K5: TQ24(CĐCT) | L5: Ngôn ngữ Trung Quốc | M5: TX - KTM | N5: Trường Trung cấp Kinh tế, Kỹ thuật, Thương mại | O5: TH | P5: x | Q5: x
A6: 5 | B6: Huongdt | C6: Dungnt | D6: hanght013 | E6: 23C4119D5004 | F6: Hoàng Thị | G6: Hằng | H6: 34294 | I6: Nữ | J6: 20 | K6: ABN520 | L6: Kế toán | M6: BN | N6: Trung tâm GDTX Bắc Ninh | O6: TH | P6: x | Q6: x
A7: 6 | B7: Huongdt | C7: Nhungntt | D7: trangntt097 | E7: 24C4101U5492 | F7: Nguyễn Thị Thu | G7: Trang | H7: 36433 | I7: Nữ | J7: 22 | K7: AKTM422 | L7: Kế toán | M7: KTM | N7: Trường Trung cấp Kinh tế, Kỹ thuật, Thương mại | O7: TH | P7: x
A8: 7 | B8: Huongdt | C8: Nhungntt | D8: minhln014 | E8: 24C1001U8108 | F8: Lê Nho | G8: Minh | H8: 34717 | I8: Nam | J8: 22 | K8: CKTM422 | L8: Công nghệ thông tin | M8: KTM | N8: Trường Trung cấp Kinh tế, Kỹ thuật, Thương mại | O8: TH | P8: x | Q8: x
A9: 8 | B9: Huongdt | C9: Nhungntt | D9: toanbs | E9: 24C1001U7788 | F9: Bùi Song | G9: Toàn | H9: 33317 | I9: Nam | J9: 22 | K9: CKTM622 | L9: Công nghệ thông tin | M9: KTM | N9: Trường Trung cấp Kinh tế, Kỹ thuật, Thương mại | O9: TH | P9: x | Q9: x
A10: 9 | B10: Huongdt | C10: Nhungntt | D10: mailt018 | E10: 24C7201U4857 | F10: Lê Thị | G10: Mai | H10: 38076 | I10: Nữ | J10: 22 | K10: OKTM422 | L10: Ngôn ngữ Trung Quốc | M10: KTM | N10: Trường Trung cấp Kinh tế, Kỹ thuật, Thương mại | O10: TH | P10: x
A11: 10 | B11: Huongdt | C11: Nhungntt | D11: maint060 | E11: 24C7201U4856 | F11: Nguyễn Thị | G11: Mai | H11: 38001 | I11: Nữ | J11: 22 | K11: OKTM422 | L11: Ngôn ngữ Trung Quốc | M11: KTM | N11: Trường Trung cấp Kinh tế, Kỹ thuật, Thương mại | O11: TH | P11: x
A12: 11 | B12: Huongdt | C12: Nhungntt | D12: mytlt | E12: 24C7201U5481 | F12: Trương Lê Trà | G12: My | H12: 38960 | I12: Nữ | J12: 22 | K12: OKTM522 | L12: Ngôn ngữ Trung Quốc | M12: KTM | N12: Trường Trung cấp Kinh tế, Kỹ thuật, Thương mại | O12: TH | P12: x | Q12: x
A13: 12 | B13: Huongdt | C13: Ngocnt | D13: tuyetdt012 | E13: 21C5001H1438 | F13: Đoàn Thị | G13: Tuyết | H13: 26758 | I13: Nữ | J13: 16 | K13: HHTM516 | L13: Luật | M13: NT | N13: Trường Trung cấp Ngoại thương | O13: TH | P13: x | Q13: x
A14: 13 | B14: Huongdt | C14: Ngocnt | D14: andt011 | E14: 24C4101S8261 | F14: Đỗ Thị | G14: Ân | H14: 29230 | I14: Nữ | J14: 22 | K14: ANT522 | L14: Kế toán | M14: NT | N14: Trường Trung cấp Ngoại thương | O14: TH | P14: x | Q14: x
A15: 14 | B15: Huongdt | C15: Ngocnt | D15: quyetlv004 | E15: 24C1001S8232 | F15: Lê Văn | G15: Quyết | H15: 37146 | I15: Nam | J15: 22 | K15: CNT522 | L15: Công nghệ thông tin | M15: NT | N15: Trường Trung cấp Ngoại thương | O15: TH | P15: x | Q15: x
A16: 15 | B16: Huongdt | C16: Ngocnt | D16: loanntb002 | E16: 24C7101S7338 | F16: Nguyễn Thị Bích | G16: Loan | H16: 29953 | I16: Nữ | J16: 22 | K16: FNT322 | L16: Ngôn ngữ Anh | M16: NT | N16: Trường Trung cấp Ngoại thương | O16: TH | P16: x
A17: 16 | B17: Huongdt | C17: Ngocnt | D17: hangttt026 | E17: 24C7101S7346 | F17: Tạ Thị Thanh | G17: Hằng | H17: 37762 | I17: Nữ | J17: 22 | K17: FNT322 | L17: Ngôn ngữ Anh | M17: NT | N17: Trường Trung cấp Ngoại thương | O17: TH | P17: x | Q17: x
A18: 17 | B18: Huongdt | C18: Ngocnt | D18: phuongbm005 | E18: 24C7101S7300 | F18: Bùi Minh | G18: Phương | H18: 37558 | I18: Nữ | J18: 22 | K18: FNT422 | L18: Ngôn ngữ Anh | M18: NT | N18: Trường Trung cấp Ngoại thương | O18: TH | P18: x | Q18: x
A19: 18 | B19: Huongdt | C19: Ngocnt | D19: anhbh008 | E19: 24C7101S7325 | F19: Bùi Hiếu | G19: Anh | H19: 36591 | I19: Nữ | J19: 22 | K19: FNT522 | L19: Ngôn ngữ Anh | M19: NT | N19: Trường Trung cấp Ngoại thương | O19: TH | P19: x | Q19: x
A20: 19 | B20: Huongdt | C20: Ngocnt | D20: maipt016 | E20: 24C7101S7310 | F20: Phàn Thị | G20: Mai | H20: 37319 | I20: Nữ | J20: 22 | K20: FNT622 | L20: Ngôn ngữ Anh | M20: NT | N20: Trường Trung cấp Ngoại thương | O20: TH | P20: x | Q20: x
A21: 20 | B21: Huongdt | C21: Ngocnt | D21: quangbt002 | E21: 24C5001S7237 | F21: Bùi Tuấn | G21: Quang | H21: 36158 | I21: Nam | J21: 22 | K21: HNT322 | L21: Luật | M21: NT | N21: Trường Trung cấp Ngoại thương | O21: TH | P21: x | Q21: x
A22: 21 | B22: Huongdt | C22: Ngocnt | D22: minhtt015 | E22: 24C5001S7266 | F22: Trương Thu | G22: Minh | H22: 28508 | I22: Nữ | J22: 22 | K22: HNT422 | L22: Luật | M22: NT | N22: Trường Trung cấp Ngoại thương | O22: TH | P22: x
A23: 22 | B23: Huongdt | C23: Ngocnt | D23: giangpv002 | E23: 24C5001S8382 | F23: Phan Văn | G23: Giang | H23: 33564 | I23: Nam | J23: 22 | K23: HNT422 | L23: Luật | M23: NT | N23: Trường Trung cấp Ngoại thương | O23: TH | P23: x | Q23: x
A24: 23 | B24: Huongdt | C24: Ngocnt | D24: chudh | E24: 24C5001S7239 | F24: Đặng Hữu | G24: Chu | H24: 26581 | I24: Nam | J24: 22 | K24: HNT622 | L24: Luật | M24: NT | N24: Trường Trung cấp Ngoại thương | O24: TH | P24: x | Q24: x
A25: 24 | B25: Huongdt | C25: Ngocnt | D25: datnc006 | E25: 24C5001S8363 | F25: Nguyễn Công | G25: Đạt | H25: 29328 | I25: Nam | J25: 22 | K25: HNT622 | L25: Luật | M25: NT | N25: Trường Trung cấp Ngoại thương | O25: TH | P25: x | Q25: x
A26: 25 | B26: Huongdt | C26: Ngocnt | D26: longnv029 | E26: 24C5001S8373 | F26: Nguyễn Vũ | G26: Long | H26: 32932 | I26: Nam | J26: 22 | K26: HNT622 | L26: Luật | M26: NT | N26: Trường Trung cấp Ngoại thương | O26: TH | P26: x | Q26: x
A27: 26 | B27: Huongdt | C27: Ngocnt | D27: hoict | E27: 24C5001S8409 | F27: Cao Thị | G27: Hồi | H27: 32596 | I27: Nữ | J27: 22 | K27: HNT622 | L27: Luật | M27: NT | N27: Trường Trung cấp Ngoại thương | O27: TH | P27: x | Q27: x
A28: 27 | B28: Huongdt | C28: Ngocnt | D28: phuongtdm | E28: 24C4701S7480 | F28: Trương Đức Minh | G28: Phương | H28: 36355 | I28: Nam | J28: 22 | K28: NNT622 | L28: Thương mại điện tử | M28: NT | N28: Trường Trung cấp Ngoại thương | O28: TH | P28: x | Q28: x
A29: 28 | B29: Huongdt | C29: Ngocnt | D29: hieunv029 | E29: 24C4701S8332 | F29: Nguyễn Văn | G29: Hiếu | H29: 38057 | I29: Nam | J29: 22 | K29: NNT622 | L29: Thương mại điện tử | M29: NT | N29: Trường Trung cấp Ngoại thương | O29: TH | P29: x | Q29: x
A30: 29 | B30: Huongdt | C30: Ngocnt | D30: linhntt046 | E30: 24C4701S8330 | F30: Nguyễn Thị Thùy | G30: Linh | H30: 38815 | I30: Nữ | J30: 22 | K30: NNT622 | L30: Thương mại điện tử | M30: NT | N30: Trường Trung cấp Ngoại thương | O30: TH | P30: x | Q30: x
A31: 30 | B31: Huongdt | C31: Ngocnt | D31: quynhdt016 | E31: 24C7201S8548 | F31: Đặng Thu | G31: Quỳnh | H31: 27901 | I31: Nữ | J31: 22 | K31: ONT322 | L31: Ngôn ngữ Trung Quốc | M31: NT | N31: Trường Trung cấp Ngoại thương | O31: TH | P31: x | Q31: x
A32: 31 | B32: Huongdt | C32: Ngocnt | D32: dunglt036 | E32: 24C7201S8552 | F32: Lê Thị | G32: Dung | H32: 32208 | I32: Nữ | J32: 22 | K32: ONT422 | L32: Ngôn ngữ Trung Quốc | M32: NT | N32: Trường Trung cấp Ngoại thương | O32: TH | P32: x | Q32: x | R32: Chuyển ĐT rồi
A33: 32 | B33: Huongdt | C33: Ngocnt | D33: tranglk002 | E33: 24C7201S7357 | F33: Lê Kiều | G33: Trang | H33: 38982 | I33: Nữ | J33: 22 | K33: ONT622 | L33: Ngôn ngữ Trung Quốc | M33: NT | N33: Trường Trung cấp Ngoại thương | O33: TH | P33: x
A34: 33 | B34: Huongdt | C34: Ngocnt | D34: huonghtd | E34: 24C7201S7356 | F34: Hồ Trần Diệu | G34: Hương | H34: 37859 | I34: Nữ | J34: 22 | K34: ONT622 | L34: Ngôn ngữ Trung Quốc | M34: NT | N34: Trường Trung cấp Ngoại thương | O34: TH | P34: x
A35: 34 | B35: Huongdt | C35: Ngocnt | D35: quyenttk | E35: 24C7201S7396 | F35: Trần Thị Kim | G35: Quyên | H35: 35015 | I35: Nữ | J35: 22 | K35: ONT622 | L35: Ngôn ngữ Trung Quốc | M35: NT | N35: Trường Trung cấp Ngoại thương | O35: TH | P35: x | Q35: x
A36: 35 | B36: Huongdt | C36: Ngocnt | D36: linhltt013 | E36: 24C7201S8554 | F36: Lê Thị Thùy | G36: Linh | H36: 32436 | I36: Nữ | J36: 22 | K36: ONT622 | L36: Ngôn ngữ Trung Quốc | M36: NT | N36: Trường Trung cấp Ngoại thương | O36: TH | P36: x | Q36: x
A37: 36 | B37: Huongdt | C37: Ngocnt | D37: huongmt004 | E37: 24C7201S8530 | F37: Ma Thị | G37: Hường | H37: 36807 | I37: Nữ | J37: 22 | K37: ONT622 | L37: Ngôn ngữ Trung Quốc | M37: NT | N37: Trường Trung cấp Ngoại thương | O37: TH | P37: x | Q37: x
A38: 37 | B38: Huongdt | C38: Ngocnt | D38: tuyenlt005 | E38: 24C7201S8573 | F38: Lý Thị | G38: Tuyên | H38: 36754 | I38: Nữ | J38: 22 | K38: ONT622 | L38: Ngôn ngữ Trung Quốc | M38: NT | N38: Trường Trung cấp Ngoại thương | O38: TH | P38: x | Q38: x
A39: 38 | B39: Huongdt | C39: Ngocnt | D39: menht003 | E39: 24C7201S8586 | F39: Hoàng Thị | G39: Mến | H39: 32015 | I39: Nữ | J39: 22 | K39: ONT622 | L39: Ngôn ngữ Trung Quốc | M39: NT | N39: Trường Trung cấp Ngoại thương | O39: TH | P39: x | Q39: x
A40: 39 | B40: Huongdt | C40: Ngocnt | D40: phuongttm012 | E40: 24C7201S8543 | F40: Trịnh Thị Mai | G40: Phương | H40: 38683 | I40: Nữ | J40: 22 | K40: ONT622 | L40: Ngôn ngữ Trung Quốc | M40: NT | N40: Trường Trung cấp Ngoại thương | O40: TH | P40: x
A41: 40 | B41: Huongdt | C41: Ngocnt | D41: khanhdx002 | E41: 24C7201S8550 | F41: Đỗ Xuân | G41: Khánh | H41: 28408 | I41: Nam | J41: 22 | K41: ONT622 | L41: Ngôn ngữ Trung Quốc | M41: NT | N41: Trường Trung cấp Ngoại thương | O41: TH | P41: x
A42: 41 | B42: Huongdt | C42: Ngocnt | D42: phuongntl010 | E42: 24C7201S8590 | F42: Nguyễn Thị Lê | G42: Phương | H42: 32145 | I42: Nữ | J42: 22 | K42: ONT622 | L42: Ngôn ngữ Trung Quốc | M42: NT | N42: Trường Trung cấp Ngoại thương | O42: TH | P42: x | Q42: x
A43: 42 | B43: Huongdt | C43: Nhungnt | D43: tranglt033 | E43: 25C7101T2191 | F43: Lê Thu | G43: Trang | H43: 36455 | I43: Nữ | J43: 23 | K43: FSPH123 | L43: Ngôn ngữ Anh | M43: SPH | N43: Trường Cao đẳng Sư phạm Trung Ương (Hà Nội) | O43: TH | P43: x | Q43: x
A44: 43 | B44: Huongdt | C44: Ngocnt | D44: thuydtt033 | E44: 24C7101S8452 | F44: Đặng Thị Thanh | G44: Thùy | H44: 31225 | I44: Nữ | J44: 22 | K44: FNT422 | L44: Công nghệ thông tin | M44: DNVT | N44: Trường Trung cấp Vạn Tường | O44: TH | P44: x | Q44: x
A45: 44 | B45: Lytth | C45: Trinhptt | D45: nguyendht | E45: 22C1001P4704 | F45: Đàm Hà Thảo | G45: Nguyên | H45: 36252 | I45: Nữ | J45: 18 | K45: CHDN518 | L45: Công nghệ thông tin | M45: KTM | N45: Trường Trung cấp Kinh tế, Kỹ thuật, Thương mại | O45: TH | P45: x | Q45: x
A46: 45 | B46: Lytth | C46: Dungnt | D46: trongvv | E46: 24C5108D2354 | F46: Vi Văn | G46: Trọng | H46: 34813 | I46: Nam | J46: 21 | K46: ELCA521 | L46: Luật kinh tế | M46: LCA | N46: Trung tâm KTTH - HNDN và GDTX Lào Cai | O46: TH | P46: x | Q46: x
A47: 46 | B47: Lytth | C47: Travtl | D47: lamlh004 | E47: 24C5001S1443 | F47: Lò Hoàng | G47: Lâm | H47: 37867 | I47: Nam | J47: 21 | K47: HNT421 | L47: Luật | M47: NT | N47: Trường Trung cấp Ngoại thương | O47: TH | P47: x | Q47: x
A48: 47 | B48: Ngabt | C48: Ngocnt | D48: toannc003 | E48: 24C4138D0233 | F48: Nguyễn Công | G48: Toàn | H48: 30513 | I48: Nam | J48: 20 | K48: AGL620 | L48: Kế toán | M48: GL | N48: Trung tâm Giáo dục thường xuyên tỉnh Gia Lai | O48: TH | P48: x | Q48: x
A49: 48 | B49: Ngabt | C49: Ngocnt | D49: giangmtb | E49: 24C7138D8732 | F49: Mai Thị Bình | G49: Giang | H49: 30058 | I49: Nữ | J49: 22 | K49: FGL422 | L49: Ngôn ngữ Anh | M49: GL | N49: Trung tâm Giáo dục thường xuyên tỉnh Gia Lai | O49: TH | P49: x | Q49: x
A50: 49 | B50: Ngabt | C50: Ngocnt | D50: saosh | E50: 25C7138D5711 | F50: Siu H' | G50: Sao | H50: 36019 | I50: Nữ | J50: 24 | K50: FGL324 | L50: Ngôn ngữ Anh | M50: GL | N50: Trung tâm Giáo dục thường xuyên tỉnh Gia Lai | O50: TH | P50: x | Q50: 0 | R50: Rút HP
A51: 50 | B51: Ngabt | C51: Ngocnt | D51: hongdb | E51: 25C7238D5713 | F51: Diệp Bảo | G51: Hồng | H51: 36569 | I51: Nữ | J51: 24 | K51: OGL524 | L51: Ngôn ngữ Trung Quốc | M51: GL | N51: Trung tâm Giáo dục thường xuyên tỉnh Gia Lai | O51: TH | P51: x | Q51: 0 | R51: Rút HP
A52: 51 | B52: Ngabt | C52: Lyntn | D52: nghianv008 | E52: 24C5001R5921 | F52: Ngô Văn | G52: Nghĩa | H52: 31753 | I52: Nam | J52: 23 | K52: HNT123 | L52: Luật | M52: NT | N52: Trường Trung cấp Ngoại thương | O52: TH | P52: x | Q52: x
A53: 52 | B53: Ngabt | C53: Lyntn | D53: miennt003 | E53: 25C4101S1670 | F53: Nguyễn Thị | G53: Miền | H53: 34038 | I53: Nữ | J53: 23 | K53: ANT323 | L53: Kế toán | M53: NT | N53: Trường Trung cấp Ngoại thương | O53: TH | P53: x | Q53: x
A54: 53 | B54: Ngabt | C54: Lyntn | D54: thaovp008 | E54: 25C4101S0568 | F54: Vi Phương | G54: Thảo | H54: 33988 | I54: Nữ | J54: 23 | K54: ANT523 | L54: Kế toán | M54: NT | N54: Trường Trung cấp Ngoại thương | O54: TH | P54: x | Q54: x
A55: 54 | B55: Ngabt | C55: Lyntn | D55: kiendt016 | E55: 25C4201S0587 | F55: Đặng Trung | G55: Kiên | H55: 34261 | I55: Nam | J55: 23 | K55: BNT523 | L55: Quản trị kinh doanh | M55: NT | N55: Trường Trung cấp Ngoại thương | O55: TH | P55: x | Q55: x
A56: 55 | B56: Ngabt | C56: Lyntn | D56: haht017 | E56: 25C4201S0589 | F56: Hoàng Thị | G56: Hà | H56: 35961 | I56: Nữ | J56: 23 | K56: BNT523 | L56: Quản trị kinh doanh | M56: NT | N56: Trường Trung cấp Ngoại thương | O56: TH | P56: x | Q56: x
A57: 56 | B57: Ngabt | C57: Lyntn | D57: maibt009 | E57: 25C1001S1427 | F57: Bùi Thị | G57: Mai | H57: 32121 | I57: Nữ | J57: 23 | K57: CNT323 | L57: Công nghệ thông tin | M57: NT | N57: Trường Trung cấp Ngoại thương | O57: TH | P57: x | Q57: x
A58: 57 | B58: Ngabt | C58: Lyntn | D58: anhlt046 | E58: 25C1001S0512 | F58: Lê Tuấn | G58: Anh | H58: 35956 | I58: Nam | J58: 23 | K58: CNT523 | L58: Công nghệ thông tin | M58: NT | N58: Trường Trung cấp Ngoại thương | O58: TH | P58: x | Q58: x
A59: 58 | B59: Ngabt | C59: Lyntn | D59: chiuntm | E59: 25C1001S0538 | F59: Nguyễn Thị Minh | G59: Chìu | H59: 38082 | I59: Nữ | J59: 23 | K59: CNT523 | L59: Công nghệ thông tin | M59: NT | N59: Trường Trung cấp Ngoại thương | O59: TH | P59: x | Q59: x
A60: 59 | B60: Ngabt | C60: Lyntn | D60: cuongpm008 | E60: 25C1001S0521 | F60: Phùng Minh | G60: Cường | H60: 30679 | I60: Nam | J60: 23 | K60: CNT523 | L60: Công nghệ thông tin | M60: NT | N60: Trường Trung cấp Ngoại thương | O60: TH | P60: x | Q60: x
A61: 60 | B61: Ngabt | C61: Lyntn | D61: chienpx003 | E61: 25C1001S0504 | F61: Phạm Xuân | G61: Chiến | H61: 36069 | I61: Nam | J61: 23 | K61: CNT523 | L61: Công nghệ thông tin | M61: NT | N61: Trường Trung cấp Ngoại thương | O61: TH | P61: x | Q61: x
A62: 61 | B62: Ngabt | C62: Lyntn | D62: locct003 | E62: 25C1001S1428 | F62: Chang Tuấn | G62: Lộc | H62: 37940 | I62: Nam | J62: 23 | K62: CNT523 | L62: Công nghệ thông tin | M62: NT | N62: Trường Trung cấp Ngoại thương | O62: TH | P62: x | Q62: x
A63: 62 | B63: Ngabt | C63: Lyntn | D63: tamnv011 | E63: 25C5101S1660 | F63: Nguyễn Văn | G63: Tam | H63: 30474 | I63: Nam | J63: 23 | K63: ENT323 | L63: Luật kinh tế | M63: NT | N63: Trường Trung cấp Ngoại thương | O63: TH | P63: x | Q63: x
... A85: 84 | B85: Ngabt | C85: Lyntn | D85: duydm | E85: 25C1001S2554 | F85: Đức Minh | G85: Duy | H85: 36945 | I85: Nam | J85: 23 | K85: CNT423 | L85: Công nghệ thông tin | M85: NT | N85: Trường Trung cấp Ngoại thương | O85: TH | P85: x | Q85: x
A86: 85 | B86: Ngabt | C86: Lyntn | D86: thuyhtb003 | E86: 25C5001S2731 | F86: Hoàng Thị Bích | G86: Thủy | H86: 30351 | I86: Nữ | J86: 23 | K86: HNT523 | L86: Luật | M86: NT | N86: Trường Trung cấp Ngoại thương | O86: TH | P86: 0 | Q86: 0 | R86: Rút HP
A87: 86 | B87: Ngabt | C87: Lyntn | D87: cuongnh018 | E87: 25C4501S2693 | F87: Nguyễn Hùng | G87: Cường | H87: 37833 | I87: Nam | J87: 23 | K87: DNT523 | L87: Tài chính - Ngân hàng | M87: NT | N87: Trường Trung cấp Ngoại thương | O87: TH | P87: x | Q87: x
A88: 87 | B88: Ngabt | C88: Lyntn | D88: phuonglt047 | E88: 25C1001S3511 | F88: Lê Thị | G88: Phượng | H88: 35492 | I88: Nữ | J88: 23 | K88: CNT323 | L88: Công nghệ thông tin | M88: NT | N88: Trường Trung cấp Ngoại thương | O88: TH | P88: x | Q88: x
A89: 88 | B89: Ngabt | C89: Lyntn | D89: datdt015 | E89: 25C4201S3540 | F89: Dương Tuấn | G89: Đạt | H89: 37785 | I89: Nam | J89: 23 | K89: BNT323 | L89: Quản trị kinh doanh | M89: NT | N89: Trường Trung cấp Ngoại thương | O89: TH | P89: x | Q89: x
A90: 89 | B90: Ngabt | C90: Lyntn | D90: tunt035 | E90: 25C4601S3701 | F90: Nguyễn Thị | G90: Tư | H90: 35854 | I90: Nữ | J90: 23 | K90: GNT323 | L90: Quản trị dịch vụ du lịch và Lữ hành | M90: NT | N90: Trường Trung cấp Ngoại thương | O90: TH | P90: x | Q90: x
A91: 90 | B91: Ngabt | C91: Lyntn | D91: huongttt040 | E91: 25C5101S3599 | F91: Trần Thị Thu | G91: Hương | H91: 34305 | I91: Nữ | J91: 23 | K91: ENT323 | L91: Luật Kinh tế | M91: NT | N91: Trường Trung cấp Ngoại thương | O91: TH | P91: x | Q91: x
A92: 91 | B92: Ngabt | C92: Lyntn | D92: hungdn011 | E92: 25C1001S3927 | F92: Dương Ngọc | G92: Hưng | H92: 33212 | I92: Nam | J92: 23 | K92: CNT423 | L92: Công nghệ thông tin | M92: NT | N92: Trường Trung cấp Ngoại thương | O92: TH | P92: x | Q92: x
A93: 92 | B93: Ngabt | C93: Lyntn | D93: tiennc005 | E93: 25C1001S3930 | F93: Nguyễn Công | G93: Tiến | H93: 37796 | I93: Nam | J93: 23 | K93: CNT423 | L93: Công nghệ thông tin | M93: NT | N93: Trường Trung cấp Ngoại thương | O93: TH | P93: x | Q93: x
A94: 93 | B94: Ngabt | C94: Lyntn | D94: xuyenht003 | E94: 25C4201S3971 | F94: Hà Thị | G94: Xuyên | H94: 32826 | I94: Nữ | J94: 23 | K94: BNT423 | L94: Quản trị kinh doanh | M94: NT | N94: Trường Trung cấp Ngoại thương | O94: TH | P94: x | Q94: x
A95: 94 | B95: Ngabt | C95: Lyntn | D95: anhlv014 | E95: 25C5001S4005 | F95: Lê Việt | G95: Anh | H95: 35754 | I95: Nam | J95: 23 | K95: HNT223 | L95: Luật | M95: NT | N95: Trường Trung cấp Ngoại thương | O95: TH | P95: x | Q95: x
A96: 95 | B96: Ngabt | C96: Lyntn | D96: hanttt002 | E96: 25C5001S4010 | F96: Trần Thị Thu | G96: Hàn | H96: 29282 | I96: Nữ | J96: 23 | K96: HNT123 | L96: Luật | M96: NT | N96: Trường Trung cấp Ngoại thương | O96: TH | P96: x | Q96: x
A97: 96 | B97: Ngabt | C97: Lyntn | D97: thulx | E97: 25C5001S4011 | F97: Lò Xuân | G97: Thu | H97: 32432 | I97: Nữ | J97: 23 | K97: HNT423 | L97: Luật | M97: NT | N97: Trường Trung cấp Ngoại thương | O97: TH | P97: x | Q97: x
A98: 97 | B98: Ngabt | C98: Lyntn | D98: anhtn022 | E98: 25C1001S4300 | F98: Trần Ngọc | G98: Anh | H98: 29847 | I98: Nam | J98: 23 | K98: CNT423 | L98: Công nghệ thông tin | M98: NT | N98: Trường Trung cấp Ngoại thương | O98: TH | P98: x | Q98: x
... A100: 99 | B100: Ngabt | C100: Lyntn | D100: datlt016 | E100: 25C4201S4311 | F100: Lý Tiến | G100: Đạt | H100: 37000 | I100: Nam | J100: 23 | K100: BNT423 | L100: Quản trị kinh doanh | M100: NT | N100: Trường Trung cấp Ngoại thương | O100: TH | P100: x | Q100: x
A101: 100 | B101: Ngabt | C101: Lyntn | D101: maict003 | E101: 25C5001S4331 | F101: Chu Thị | G101: Mai | H101: 32179 | I101: Nữ | J101: 23 | K101: HNT423 | L101: Luật | M101: NT | N101: Trường Trung cấp Ngoại thương | O101: TH | P101: 0 | Q101: 0 | R101: Rút HP
A102: 101 | B102: Nhungnt | C102: Dungnt | D102: duongqt | E102: 24C1001R6504 | F102: Quách Thùy | G102: Dương | H102: 31001 | I102: Nữ | J102: 22 | K102: CLHT522 | L102: Công nghệ thông tin | M102: LHT | N102: Trường Trung cấp Y Dược Lê Hữu Trác | O102: TH | P102: x | Q102: x | R102: Chuyển ĐT rồi
A103: 102 | B103: Nhungnt | C103: Namnh | D103: 24C4119E7735 | E103: 24C4119E7735 | F103: Đinh Thị | G103: Sim | H103: 33886 | I103: Nữ | K103: K26KT QV | L103: Kế toán | M103: TX - QVBN | N103: Trung tâm GDNN - GDTX Bắc Ninh | O103: TH | P103: x | Q103: x
A104: 103 | B104: Phuongbm | C104: Dungnt | D104: thuongbn | E104: 23C5018D6082 | F104: Bùi Ngọc | G104: Thường | H104: 28734 | I104: Nam | J104: 20 | K104: HBG420 | L104: Luật | M104: BG | N104: Trung tâm GDTX - Ngoại ngữ, Tin học tỉnh Bắc Ninh | O104: TH | P104: x | Q104: x
A105: 104 | B105: Thanhdt | C105: Dungnt | D105: tuyentth002 | E105: 25C4501G4222 | F105: Trần Thị Hồng | G105: Tuyên | H105: 33876 | I105: Nữ | J105: 23 | K105: DHCT423 | L105: Tài chính - Ngân hàng | M105: HCT | N105: Trường Trung cấp Công nghệ và Kinh tế Đối ngoại | O105: TH | P105: x
A106: 105 | B106: Thanhdt | C106: Travtl | D106: thuydtm002 | E106: 25C7103D2513 | F106: Đoàn Thị Minh | G106: Thùy | H106: 37890 | I106: Nữ | J106: 23 | K106: FHPH323 | L106: Ngôn ngữ Anh | M106: HPH | N106: Trung tâm Giáo dục thường xuyên Hải Phòng | O106: TH | P106: x
A107: 106 | B107: Thanhdt | C107: Dungbn | D107: namnv036 | E107: 25C7101K3799 | F107: Nguyễn Văn | G107: Nam | H107: 35934 | I107: Nam | J107: 23 | K107: FVC123 | L107: Ngôn ngữ Anh | M107: VC | N107: Trường Cao đẳng Công thương Việt Nam | O107: TH | P107: x
A108: 107 | B108: Thanhdt | C108: Nhungnt | D108: tuyendtt005 | E108: 24C4116D7688 | F108: Đặng Thị Thanh | G108: Tuyền | H108: 32806 | I108: Nữ | J108: 22 | K108: AVP522 | L108: Kế toán | M108: VP | N108: Trung tâm GDTX Vĩnh Phúc | O108: TH | P108: x
A109: 108 | B109: Thuongptm | C109: Hungnc | D109: viettt003 | E109: 23C5048E3794 | F109: Trần Tiến | G109: Việt | H109: 33903 | I109: Nam | J109: 20 | K109: HDNTB620 | L109: Luật | M109: DNTB | N109: Trung tâm GDNN - GDTX khu vực 8 | O109: TH | P109: x
A110: 109 | B110: Trangttq | C110: Travtl | D110: hieupqv | E110: 24C7101S1533 | F110: Phùng Quang Vũ | G110: Hiếu | H110: 35392 | I110: Nam | J110: 21 | K110: FNT321 | L110: Ngôn ngữ Anh | M110: NT | N110: Trường Trung cấp Ngoại thương | O110: TH | P110: x | Q110: x | R110: Chuyển ĐT rồi
A111: 110 | B111: Trangttq | C111: Travtl | D111: chill003 | E111: 24C7101S1482 | F111: Lê Linh | G111: Chi | H111: 36579 | I111: Nữ | J111: 21 | K111: FNT421 | L111: Ngôn ngữ Anh | M111: NT | N111: Trường Trung cấp Ngoại thương | O111: TH | P111: x | Q111: x | R111: Chuyển ĐT rồi
A112: 111 | B112: Trangttq | C112: Nhungnt | D112: huyendtn005 | E112: 22C7117D5763 | F112: Dương Thị Ngọc | G112: Huyền | H112: 36571 | I112: Nữ | J112: 18 | K112: FQN618 | L112: Ngôn ngữ Anh | M112: QN | N112: Trường Đào tạo Cán bộ Nguyễn Văn Cừ Quảng Ninh | O112: TH | P112: x | Q112: x
A113: 112 | B113: Trangttq | C113: Nhungnt | D113: lent026 | E113: 25C7217D3203 | F113: Nguyễn Thị | G113: Lệ | H113: 35899 | I113: Nữ | J113: 23 | K113: OQN523 | L113: Ngôn ngữ Trung Quốc | M113: QN | N113: Trường Đào tạo Cán bộ Nguyễn Văn Cừ Quảng Ninh | O113: TH | P113: x | Q113: x | R113: Chuyển ĐT rồi
A114: 113 | B114: Yenth | C114: Myntd | D114: dungkm | E114: 22C1001J1647 | F114: Khưu Mạnh | G114: Dũng | H114: 37375 | I114: Nam | J114: 17 | K114: CDT517 | L114: Công nghệ thông tin | M114: DT | N114: Viện Đào tạo và Phát triển Giáo dục Việt Nam | O114: TH | P114: x | Q114: x
A115: 114 | B115: Yenth | C115: Myntd | D115: hainn006 | E115: 21C-50-50.2-05765 | F115: Nguyễn Ngọc | G115: Hải | H115: 35407 | I115: Nam | J115: 17 | K115: HDT517 | L115: Luật | M115: DT | N115: Viện Đào tạo và Phát triển Giáo dục Việt Nam | O115: TH | P115: x | Q115: x
A116: 115 | B116: Yenth | C116: Dungbn | D116: laica | E116: 19C-51-49.4-03179 | F116: Chảo A | G116: Lai | H116: 27897 | I116: Nam | J116: 12 | K116: ELC512 | L116: Luật kinh tế | M116: LC | N116: Trung tâm Giáo dục thường xuyên Hướng nghiệp tỉnh Lai Châu | O116: TH | P116: x | Q116: x
A117: 116 | B117: Huongdt | C117: Dungnt | D117: hoangnm004 | E117: 17C-10-42.0-02318 | F117: Nguyễn Mạnh | G117: Hoàng | H117: 32001 | I117: Nam | J117: 7 | K117: C17 | L117: Công nghệ thông tin | M117: EL | N117: Trung tâm ĐT Trực tuyến | O117: XV | P117: x | Q117: x
A118: 117 | B118: Huongdt | C118: Dungnt | D118: binhtt005 | E118: 17C-45-42.0-03941 | F118: Trương Thanh | G118: Bình | H118: 35402 | I118: Nam | J118: 8 | K118: DTC18 | L118: Tài chính - Ngân hàng | M118: EL | N118: Trung tâm ĐT Trực tuyến | O118: XV | P118: x | Q118: x
A119: 118 | B119: Huongdt | C119: Ngocnt | D119: thomnt017 | E119: 24C7101I1167 | F119: Nguyễn Thị | G119: Thơm | H119: 33236 | I119: Nữ | J119: 21 | K119: FTL321 | L119: Ngôn ngữ Anh | M119: TL | N119: Trường Trung cấp Kinh tế - Kỹ thuật Bắc Thăng Long | O119: XV | P119: x | Q119: x
A120: 119 | B120: Khanhntk | C120: Quynhtnn | D120: thucnp | E120: 20C-10-55.0-04101 | F120: Nguyễn Phi | G120: Thức | H120: 32583 | I120: Nam | J120: 17 | K120: CDNP217 | L120: Công nghệ thông tin | M120: DNP | N120: Trung tâm Đại học Mở Hà Nội tại Đà Nẵng | O120: XV | P120: x | Q120: x
A121: 120 | B121: Khanhntk | C121: Hoangnm | D121: dungdtt | E121: 17C-71-43.9-03453 | F121: Đinh Thị Thùy | G121: Dung | H121: 32410 | I121: Nữ | J121: 7 | K121: FQB57 | L121: Ngôn ngữ Anh | M121: QB | N121: Trường Đại học Quảng Bình | O121: XV | P121: x | Q121: x
A122: 121 | B122: Lytth | C122: Travtl | D122: khanhnv014 | E122: 24C1001S1336 | F122: Nguyễn Văn | G122: Khánh | H122: 35781 | I122: Nam | J122: 21 | K122: CNT421 | L122: Công nghệ thông tin | M122: NT | N122: Trường Trung cấp Ngoại thương | O122: XV | P122: x | Q122: x
...

Sheet THÔNG TIN SINH VIÊN XÉT VỚT T12
A1: STT | B1: Ngành học | C1: Lớp | D1: Mã SV | E1: Họ và | F1: Tên | G1: Ngày sinh | H1: Giới | I1: Đối tượng | J1: Số TC đã tích lũy | K1: Số môn còn nợ | L1: Số tín chỉ còn nợ | M1: Thời gian có QĐ | N1: Lý do xét vớt | O1: QLSV | P1: GV | Q1: Thời gian hết TGĐT | R1: Thời gian xét TN dự kiến | U1: QLSV phản hồi lý do không đăng ký TC kỳ 2
A2: 1 | B2: Công nghệ thông tin | C2: C17 | D2: 17C-10-42.0-02318 | E2: Nguyễn Mạnh | F2: Hoàng | G2: 32001 | H2: Nam | I2: ĐH | J2: 133 | K2: 2 | L2: 7 | M2: 42884 | N2: Hết TGĐT | O2: Huongdt | P2: Dungnt | Q2: 45806 | R2: 46174 | S2: Chưa học lại IT10 và IT15. Kỳ 2 không đăng ký học | T2: Hệ thống uni thiếu MM | U2: SV xin đăng ký bổ sung 2 môn còn nợ
A3: 2 | B3: Tài chính - Ngân hàng | C3: DTC18 | D3: 17C-45-42.0-03941 | E3: Trương Thanh | F3: Bình | G3: 35402 | H3: Nam | I3: THPT | J3: 130 | K3: 0 | L3: 0 | M3: 43035 | N3: Hết TGĐT | O3: Huongdt | P3: Dungnt | Q3: 45957 | R3: 46023 | S3: HTCT | U3: SV TN Tháng 1/2026
A4: 3 | B4: Ngôn ngữ Anh | C4: FTL321 | D4: 24C7101I1167 | E4: Nguyễn Thị | F4: Thơm | G4: 33236 | H4: Nữ | I4: CĐCN | J4: 30 | K4: 44 | L4: 111 | M4: 45366 | N4: CB2-BTH | O4: Huongdt | P4: Ngocnt | Q4: 47557 | R4: 46388 | S4: Không đăng ký tín chỉ kỳ 2/2025-2026 | U4: SV đang làm đơn BL ngày 19/12/2025 | V4: Phòng ko tiếp nhận đơn
A5: 4 | B5: Công nghệ thông tin | C5: CDNP217 | D5: 20C-10-55.0-04101 | E5: Nguyễn Phi | F5: Thức | G5: 32583 | H5: Nam | I5: CĐCN | J5: 109 | K5: 13 | L5: 43 | M5: 44054 | N5: CB2-BTH | O5: Khanhntk | P5: Quynhtnn | Q5: 46976 | S5: Không đăng ký tín chỉ kỳ 2/2025-2026 | T5: Có đăng ký tín chỉ kỳ 2 bổ sung | U5: xin đăng kí bổ sung
A6: 5 | B6: Ngôn ngữ Anh | C6: FQB57 | D6: 17C-71-43.9-03453 | E6: Đinh Thị Thùy | F6: Dung | G6: 32410 | H6: Nữ | I6: THPT | J6: 135 | K6: 0 | L6: 0 | M6: 42955 | N6: Hết TGĐT | O6: Khanhntk | P6: Hoangnm | Q6: 45877 | S6: HTCT | U6: SV TN Tháng 1/2026
A7: 6 | B7: Công nghệ thông tin | C7: CNT421 | D7: 24C1001S1336 | E7: Nguyễn Văn | F7: Khánh | G7: 35781 | H7: Nam | I7: THPT | J7: 20 | K7: 33 | L7: 106 | M7: 45380 | N7: CB2-BTH | O7: Lytth | P7: Travtl | Q7: 47571 | R7: 46447 | S7: Không đăng ký tín chỉ kỳ 2/2025-2026 | U7: SV làm đơn bảo lưu ngày 20/12/2025 | V7: Phòng ko tiếp nhận đơn
A8: 7 | B8: Luật | C8: HNT321 | D8: 24C5001S3805 | E8: Bùi Thị Minh | F8: Hiền | G8: 28003 | H8: Nữ | I8: ĐH | J8: 35 | K8: 29 | L8: 85 | M8: 45471 | N8: CB2-BTH | O8: Lytth | P8: Travtl | Q8: 47662 | R8: 46357 | S8: Không đăng ký tín chỉ kỳ 2/2025-2026 | T8: Hệ thống uni thiếu MM | U8: SV làm đơn bảo lưu ngày 20/12/2025 | V8: Phòng ko tiếp nhận đơn
A9: 8 | B9: Kế toán | C9: AVP519 | D9: 23C4116D0017 | E9: Khổng Văn | F9: Trường | G9: 35868 | H9: Nam | I9: TC | J9: 12 | K9: 40 | L9: 119 | M9: 44967 | N9: CB2-BTH | O9: Thanhdt | P9: Nhungnt | Q9: 47159 | S9: Có đăng ký tín chỉ kỳ 2/2025-2026
A10: 9 | B10: Ngôn ngữ Anh | C10: FDNAV312 | D10: 19C-71-55.1-02795 | E10: Đào Duy | F10: Tuấn | G10: 32151 | H10: Nam | I10: CĐKN | J10: 88 | K10: 21 | L10: 47 | M10: 43712 | N10: CB2-BTH | O10: Thuongptm | P10: Hoangnm | Q10: 46634 | R10: 44443 | S10: Không đăng ký tín chỉ kỳ 2/2025-2026 | U10: SV CHỈ CÒN THI TRẢ NỢ MÔN
A11: 10 | B11: Tài chính - Ngân hàng | C11: DDNAV515 | D11: 21C-45-55.1-03347 | E11: Nguyễn Trần Thùy | F11: Liên | G11: 35228 | H11: Nữ | I11: THPT | J11: 23 | K11: 42 | L11: 107 | M11: 44342 | N11: CB2-BTH | O11: Thuongptm | P11: Hoangnm | Q11: 47264 | R11: 45622 | S11: Không đăng ký tín chỉ kỳ 2/2025-2026 | T11: Có đăng ký tín chỉ kỳ 2 bổ sung | U11: xin đăng kí bổ sung
A12: 11 | B12: Công nghệ thông tin | C12: CDNCN520 | D12: 23C1002J3816 | E12: Bùi Doãn Minh | F12: Đức | G12: 35491 | H12: Nam | I12: TCCN | J12: 7 | K12: 40 | L12: 144 | M12: 45163 | N12: CB2-BTH | O12: Thuongptm | P12: Hoangnm | Q12: 47355 | R12: 46259 | S12: Có đăng ký tín chỉ kỳ 2/2025-2026
A13: 12 | B13: Kế toán | C13: ADNVT415 | D13: 21C-41-55.4-02494 | E13: Trần Thị Ngọc | F13: Hảo | G13: 29448 | H13: Nữ | I13: TCCN | J13: 68 | K13: 26 | L13: 63 | M13: 44320 | N13: CB2-BTH | O13: Thuongptm | P13: Sangpn | Q13: 47242 | R13: 45234 | S13: Không đăng ký tín chỉ kỳ 2/2025-2026 | T13: Có đăng ký tín chỉ kỳ 2 bổ sung | U13: xin đăng kí bổ sung
A14: 13 | B14: Kế toán | C14: ADNVT415 | D14: 21C-41-55.4-04514 | E14: Nguyễn Thị Thùy | F14: Trang | G14: 28452 | H14: Nữ | I14: TCCN | J14: 72 | K14: 23 | L14: 59 | M14: 44396 | N14: CB2-BTH | O14: Thuongptm | P14: Sangpn | Q14: 47318 | R14: 45310 | S14: Không đăng ký tín chỉ kỳ 2/2025-2026 | T14: Có đăng ký tín chỉ kỳ 2 bổ sung | U14: xin đăng kí bổ sung
A15: 15 | B15: Ngôn ngữ Anh | C15: FDNVT420 | D15: 23C7102H5776 | E15: Lê Văn | F15: Việt | G15: 32718 | H15: Nam | I15: CĐKN | J15: 40 | K15: 41 | L15: 96 | M15: 45266 | N15: CB2-BTH | O15: Thuongptm | P15: Sangpn | Q15: 47458 | R15: 46209 | S15: Có đăng ký tín chỉ kỳ 2/2025-2026
A16: 16 | B16: Luật | C16: HDNVT520 | D16: 23C5001S4839 | E16: Đinh Minh | F16: Thượng | G16: 35071 | H16: Nam | I16: THPT | J16: 55 | K16: 26 | L16: 76 | M16: 45230 | N16: CB2-BTH | O16: Thuongptm | P16: Sangpn | Q16: 47422 | R16: 46326 | S16: Có đăng ký tín chỉ kỳ 2/2025-2026
A17: 17 | B17: Ngôn ngữ Anh | C17: FNT521 | D17: 24C7101S3020 | E17: Tô Đức | F17: Hiếu | G17: 38398 | H17: Nam | I17: THPT | J17: 12 | K17: 52 | L17: 114 | M17: 45443 | N17: CB2-BTH | O17: Trangttq | P17: Travtl | Q17: 47634 | S17: Có đăng ký tín chỉ kỳ 2/2025-2026 | T17: Sinh viên đang học năm cuối ĐH Xây dựng. Đơn không có dấu đỏ
A18: 18 | B18: Công nghệ thông tin | C18: CDT119 | D18: 16A10010250 | E18: Hồ Minh | F18: Hoàng | G18: 35729 | H18: Nam | I18: THPT | J18: 123 | K18: 5 | L18: 18 | M18: 42603 | N18: Hết TGĐT | O18: Yenth | P18: Myntd | Q18: 45525 | S18: Không đăng ký tín chỉ kỳ 2/2025-2026 | U18: SV đã học xong hoãn thi - xin thi ghép
A19: 19 | B19: Ngôn ngữ Anh | C19: FDN57 | D19: 17C-71-43.7-04190 | E19: Võ Quang | F19: Phúc | G19: 33392 | H19: Nam | I19: THPT | J19: 95 | K19: 21 | L19: 48 | M19: 43046 | N19: Hết TGĐT | O19: Yenth | P19: Dungbn | Q19: 45968 | S19: Không đăng ký tín chỉ kỳ 2/2025-2026 | T19: Có đăng ký tín chỉ kỳ 2 bổ sung | U19: Sv còn nợ 17 HP chưa tích luỹ - Đã học 10 HP chờ thi, 6 HP xin học ghép kỳ 2 bổ sung, 1 học phần xin ghép kỳ 3 do ĐKTQ
A20: 20 | B20: Kế toán | C20: ALC515 | D20: 21C-41-49.4-03784 | E20: Vũ Thị Bích | F20: Thủy | G20: 29834 | H20: Nữ | I20: THPT | J20: 17 | K20: 41 | L20: 125 | M20: 44355 | N20: CB2-BTH | O20: Yenth | P20: Dungbn | Q20: 47277 | S20: Không đăng ký tín chỉ kỳ 2/2025-2026 | T20: ` | U20: SV chưa đăng ký do đang thất nghiệp, xin học từ kì sau
A21: 21 | B21: Ngôn ngữ Anh | C21: FYB220 | D21: 24C7113D0382 | E21: Hoàng Đình | F21: Tứ | G21: 09/04/1984 | H21: Nam | I21: Đại học | J21: 67 | K21: 33 | L21: =135-J21 -> 68 | M21: 45293 | N21: CB2-BTH | O21: Lytth | P21: Lyntn | Q21: 02/01/2030 | R21: 46082 | S21: Có đăng ký tín chỉ kỳ 2/2025-2026
A25: 14 | B25: Luật kinh tế | C25: EDNVT315 | D25: 21C-51-55.4-04462 | E25: Nghiêm Quốc | F25: Cường | G25: 30102 | H25: Nam | I25: CĐKN | J25: 87 | K25: 16 | L25: 44 | M25: 44396 | N25: CB2-BTH | O25: Thuongptm | P25: Sangpn | Q25: 47318 | S25: Có đăng ký tín chỉ kỳ 2/2025-2026 | T25: Chuyển BTH

Sheet THÔNG TIN
A1: STT | B1: Mã ĐVPH | C1: Trạm | D1: Tách file theo tên này | E1: ĐV PHĐT | F1: Quy mô tổng dưới 2 năm | G1: Quy mô tổng (1) | H1: Đang học dưới 2 năm | I1: Đang học (2) | J1: Bảo lưu dưới 2 năm | K1: Bảo lưu (3) | L1: Cảnh báo KLHT dưới 2 năm | M1: Cảnh báo KLHT (4) | N1: Cảnh báo KQHT dưới 2 năm | O1: Cảnh báo KQHT (5) | P1: Xét vớt dưới 2 năm | Q1: Xét vớt (6) | R1: BTH (7) | T1: XT (8) | U1: Thôi học (9) | V1: Quy mô còn lại sau xét | W1: HTCT (11) | X1: Trong đó số mới tuyển kỳ 1/2025-2026 | Y1: Ghi chú
R2: Do cảnh báo | S2: Do hết thời gian
I3: Đang học | K3: BL | M3: HT-CBKL1 | O3: HT-CBKQ1 | Q3: XV | R3: BTH-CB | S3: BTH-HTG | T3: XT | U3: Thôi học | V3: 10=(1)-(7)-(8)-(9) | W3: HTCT | X3: TS
A4: 1 | B4: AyunPa | C4: AyunPa | D4: 1.TK.AyunPa | E4: Trung tâm GDNN - GDTX AyunPa | F4: 0 | G4: 4 | H4: 0 | I4: 3 | J4: 0 | K4: 0 | L4: 0 | M4: 0 | N4: 0 | O4: 0 | P4: 0 | Q4: 0 | R4: 0 | S4: 0 | T4: 0 | U4: 0 | V4: 4 | W4: 1 | X4: 0
A5: 2 | B5: BG | C5: BG | D5: 2.TK.BG | E5: Trung tâm GDTX - Ngoại ngữ, Tin học tỉnh Bắc Ninh | F5: 8 | G5: 255 | H5: 6 | I5: 227 | J5: 1 | K5: 2 | L5: 1 | M5: 12 | N5: 0 | O5: 0 | P5: 0 | Q5: 0 | R5: 1 | S5: 0 | T5: 0 | U5: 1 | V5: 253 | W5: 12 | X5: 37
A6: 3 | B6: BK | C6: BK | D6: 3.TK.BK | E6: Trung tâm GDTX Bắc Kạn | F6: 0 | G6: 12 | H6: 0 | I6: 12 | J6: 0 | K6: 0 | L6: 0 | M6: 0 | N6: 0 | O6: 0 | P6: 0 | Q6: 0 | R6: 0 | S6: 0 | T6: 0 | U6: 0 | V6: 12 | W6: 0 | X6: 0
A7: 3 | B7: TX - BK | C7: BK | D7: 3.TK.BK | E7: Trung tâm GDTX Bắc Kạn | F7: 6 | G7: 73 | H7: 6 | I7: 20 | J7: 0 | K7: 11 | L7: 0 | M7: 39 | N7: 0 | O7: 0 | P7: 0 | Q7: 0 | R7: 1 | S7: 0 | T7: 0 | U7: 0 | V7: 72 | W7: 2 | X7: 0
A8: 4 | B8: BN | C8: BN | D8: 4.TK.BN | E8: Trung tâm GDTX Bắc Ninh | F8: 4 | G8: 167 | H8: 1 | I8: 138 | J8: 0 | K8: 0 | L8: 3 | M8: 16 | N8: 0 | O8: 0 | P8: 0 | Q8: 0 | R8: 2 | S8: 0 | T8: 3 | U8: 1 | V8: 161 | W8: 7 | X8: 37
A9: 4 | B9: TX - BN | C9: BN | D9: 4.TK.BN | E9: Trung tâm GDTX Bắc Ninh | F9: 0 | G9: 68 | H9: 0 | I9: 59 | J9: 0 | K9: 0 | L9: 0 | M9: 0 | N9: 0 | O9: 0 | P9: 0 | Q9: 0 | R9: 0 | S9: 0 | T9: 0 | U9: 0 | V9: 68 | W9: 9 | X9: 2
A10: 5 | B10: BP | C10: BP | D10: 5.TK.BP | E10: Trường Trung cấp Miền Nam | F10: 1 | G10: 130 | H10: 1 | I10: 118 | J10: 0 | K10: 7 | L10: 0 | M10: 0 | N10: 0 | O10: 0 | P10: 0 | Q10: 0 | R10: 4 | S10: 0 | T10: 0 | U10: 0 | V10: 126 | W10: 1 | X10: 9
A11: 6 | B11: DN - CT | C11: DN - CT | D11: 6.TK.DN.CT | E11: Trường CĐ Nghề Cần Thơ | F11: 0 | G11: 35 | H11: 0 | I11: 17 | J11: 0 | K11: 2 | L11: 0 | M11: 7 | N11: 0 | O11: 0 | P11: 0 | Q11: 0 | R11: 7 | S11: 1 | T11: 0 | U11: 0 | V11: 27 | W11: 1 | X11: 0
A12: 7 | B12: DN - LH | C12: DN - LH | D12: 7.TK.DN.LH | E12: Trung tâm GDNN - GDTX Lâm Hà | F12: 0 | G12: 11 | H12: 0 | I12: 2 | J12: 0 | K12: 0 | L12: 0 | M12: 1 | N12: 0 | O12: 0 | P12: 0 | Q12: 0 | R12: 0 | S12: 0 | T12: 0 | U12: 0 | V12: 11 | W12: 8 | X12: 0
A13: 8 | B13: DNA | C13: DNA | D13: 8.TK.DNA | E13: Trung tâm GDNN-GDTX tỉnh Đồng Nai | F13: 1 | G13: 75 | H13: 1 | I13: 56 | J13: 0 | K13: 2 | L13: 0 | M13: 6 | N13: 0 | O13: 0 | P13: 0 | Q13: 0 | R13: 1 | S13: 1 | T13: 8 | U13: 0 | V13: 65 | W13: 1 | X13: 17
A14: 9 | B14: DNAG | C14: DNAG | D14: 9.TK.DNAG | E14: Trường Trung cấp Hồng Hà Cần Thơ - Phân hiệu An Giang | F14: 0 | G14: 95 | H14: 0 | I14: 81 | J14: 0 | K14: 1 | L14: 0 | M14: 3 | N14: 0 | O14: 0 | P14: 0 | Q14: 0 | R14: 5 | S14: 0 | T14: 1 | U14: 0 | V14: 89 | W14: 4 | X14: 9
A15: 10 | B15: DNAV | C15: DNAV | D15: 10.TK.DNAV | E15: Trường Trung cấp Âu Việt | F15: 14 | G15: 376 | H15: 11 | I15: 258 | J15: 1 | K15: 6 | L15: 1 | M15: 21 | N15: 0 | O15: 0 | P15: 1 | Q15: 0 | R15: 58 | S15: 3 | T15: 2 | U15: 0 | V15: 313 | W15: 26 | X15: 7
... A88: 73 | B88: Edutop | C88: Edutop | D88: 73.TK.Edutop | E88: TTĐT Đà Nẵng - Edutop | F88: 0 | G88: 26 | H88: 0 | I88: 0 | J88: 0 | K88: 0 | L88: 0 | M88: 0 | N88: 0 | O88: 0 | P88: 0 | Q88: 0 | R88: 1 | S88: 25 | T88: 0 | U88: 0 | V88: 0 | W88: 0 | X88: 0
A89: TỔNG | F89: 605 | G89: 23892 | H89: 382 | I89: 19623 | J89: 167 | K89: 484 | L89: 43 | M89: 1220 | N89: 7 | O89: 251 | P89: 6 | Q89: 0 | R89: 710 | S89: 64 | T89: 331 | U89: 116 | V89: 22671 | W89: 1073 | X89: 3233

Sheet Mail+SDT
A1: ACC | B1: Email | C1: Di động | D1: Email cá nhân, cần thì lấy gửi thêm
A2: phuongth007 | B2: cuphuong77@gmail.com | C2: 819438537
A3: lamnh002 | B3: hoanglam25494@gmail.com | C3: 373981523
A4: hanhdn | B4: hanhdn@sacombank.com | C4: 912516778
A5: huept016 | B5: phamthihueqb2703@gmail.com | C5: 888923775
A6: hangptt009 | B6: hangpham9713@gmail.com | C6: 971630059
A7: tinhnv017 | B7: nguyenvantinh5656@gmail.com | C7: 961599058
A8: huyenht013 | B8: behuyen.197@gmail.com | C8: 962555694
A9: hungnm045 | B9: canine871@gmail.com | C9: 984529900
A10: tanld002 | B10: npstanle@gmail.com | C10: 961412899
A11: lepxh | B11: tranlinhchi1111998@gmail.com | C11: 888478855
A12: hungnh014 | B12: nguyenhungdho@gmail.com | C12: 911363639
A13: huyenttt013 | B13: tranthuyhuyen051199@gmail.com | C13: 981404471
... A70: huynhnhl | B70: huynhnguyenhole@gmail.com | C70: 775718532
A71: khanhdtp002 | B71: phuongkhanhla@gmail.com | C71: 0943 864 445
A72: lannh | B72: lannguyenhoang@gmail.com | C72: 902092785
A73: ngocnt019 | B73: ngocnguyenthi.ueh@gmail.com | C73: 386802828
A74: nhant002 | B74: chuotchanhche@yahoo.com.vn | C74: 908911961
A75: thamnt006 | B75: nguyentham09kt@gmail.com | C75: 911160188
A76: thanhnt031 | B76: 7764eya@gmail.com | C76: 869032795
A77: thaovt007 | B77: vothuthao2505@gmail.com | C77: 1275168757
A78: thinhch | B78: 13125473@st.hcmuaf.edu.vn | C78: 353123350
A79: thuongnt010 | B79: n.tthuong100490@gmail.com | C79: 937103674
A80: thuyntt022 | B80: thanhthuy241089@gmail.com | C80: 978912541
A81: thyttd | B81: thytran.lioa@gmail.com | C81: 918182096
A82: trinhnta | B82: aitrinhbk11@gmail.com | C82: 981807386
A83: tuanbx | B83: tuanhs24@yahoo.com | C83: 908840074
A84: tuantq005 | B84: quangtuan.ex1988@gmail.com | C84: 947236504
A85: xuantt005 | B85: xuantvt2015@gmail.com | C85: 0908 730 207
A86: hainvb | B86: piso.fs81@gmail.com | C86: 981749482
A87: haont007 | B87: nguyenhao1501kt@gmail.com | C87: 987371582
A88: liemnt003 | B88: liemfordhcm@gmail.com | C88: 943231122
A89: phuongtdd | B89: phuongtran1811.pt@gmail.com | C89: 396200010
A90: tanttt | B90: tankt0311@gmail.com | C90: 909079001
A91: thylnt | B91: thy.le.k3sba@gmail.com | C91: 386203198
A92: thongnt | B92: nguyenthong463@gmail.com | C92: 766850453
A93: duanpv | B93: duanchelsea1992@gmail.com | C93: 976473315
A94: hoatk | B94: hoa.tk911@gmail.com | C94: 968511206
A95: phuocnb | B95: baphuocnct@gmail.com | C95: 971912424
A96: thaoltp011 | B96: lethiphuongthao213@gmail.com | C96: 779640093
A97: tampt004 | B97: thanhtam.vnmilk11@gmail.com | C97: 939247800
... A99: ngocvtm | B99: vongoc244@gmail.com | C99: 937599349
A100: nhanhpdt | B100: nhanh.phan@yahoo.com.vn | C100: 0907 500 587
A101: nganpt007 | B101: baoloctruanang@gmail.com | C101: 979124579
A102: thaontt019 | B102: thaolam199587@gmail.com | C102: 708329468
A103: thutta | B103: thutu.160297@gmail.com | C103: 1654463207
A104: luutxp | B104: phongluu2809@gmail.com | C104: 901322286
A105: ngannt015 | B105: nganntbt@gmail.com | C105: 975760089
A106: quyenntm002 | B106: quyen.nguyenmy@yahoo.com | C106: 988404869
A107: thuannm | B107: ruanmingshun@gmail.com | C107: 783599424
A108: tuyetdta002 | B108: tuyet.dtlx25@gmail.com | C108: 902874717
A109: uyenpnl | B109: uyenpham8899@gmail.com | C109: 904642314
A110: nhungvt009 | B110: nhungvuvu36@gmail.com | C110: 933562658
A111: thuynm002 | B111: minhthuymt0524@gmail.com | C111: 961646760
A112: chinhv | B112: chinvanha@gmail.com | C112: 908502177
... A126: vanntt010 | B126: thuvannguyen2011@gmail.com | C126: 932124612
A127: diemvtk | B127: diemvo964@gmail.com | C127: 0362 818 964
A128: nghiacm | B128: cmnghia1516@gmail.com | C128: 903952898
A129: thinhnh004 | B129: hungthinh9000@gmail.com | C129: 968636867
A130: nhatlt | B130: letannhat2017@gmail.com | C130: 936707043
A131: uyenlat | B131: thuyuyen1102@gmail.com | C131: 901414008
A132: huydq005 | B132: adamhuy1409@gmail.com | C132: 901326860
A133: trainv | B133: trainv76@yahoo.com | C133: 968244556
A134: ngoctt005 | B134: tranthingoc11906@gmail.com | C134: 969286314
A135: vietnva | B135: viet.nguyen@stravel.vn | C135: 902643225
A136: phuongtd | B136: tadinhphuong98@gmail.com | C136: 338432191
A137: ynn | B137: ngocy.nguyen0301@gmail.com | C137: 905404750
A138: truonghd002 | B138: hoangductruong89@icloud.com, sirmanshion89@gmail.com | C138: 909054031
A139: vint003 | B139: thuyvi1902@gmail.com | C139: 368266126
... A146: dinhtc003 | B146: orthertran1@gmail.com | C146: 395159991
A147: tamdm002 | B147: tamsiam102013@gmail.com | C147: 0978948704; 0817725672
A148: tructlt | B148: thanhtruc171096@gmail.com | C148: 908380885
A149: loanntt009 | B149: loantn1983@yahoo.com | C149: 907718608
A150: tienlv004 | B150: viettienspkt@gmail.com | C150: 383650602
A151: tridv | B151: damtri63@gmail.com | C151: 369287529
A152: tanhm002 | B152: hmtan@ttgdqp.edu.vn | C152: 916020443
A153: anvt003 | B153: anheo19961@gmail.com | C153: 903964995
A154: hungnt033 | B154: hungnguyen8986@gmail.com | C154: 398787789
A155: luanpt003 | B155: luanpt.vietanhschool@gmail.com | C155: 975407425
A156: nganndd | B156: ngododuyngan@gmail.com | C156: 909754879
A157: tritm007 | B157: trithanminh@gmail.com | C157: 937817211
A158: truongnm006 | B158: nguyenben@vinatexvsc.com | C158: 937826613
A159: nhungndt | B159: nhungnguyendang@gmail.com | C159: 794687688
... A227: hangttk002 | B227: kimhangtrac@gmail.com | C227: 902091110
A228: hungdt004 | B228: dinhthaihung9999@gmail.com | C228: 0915680079
A229: trangptt016 | B229: trangptt109@gmail.com | C229: 903345513
A230: nghianm004 | B230: nmnghia2525@yahoo.com | C230: 938186866
A231: phuongnv015 | B231: nguyenphuongtthcmlq2@gmail.com | C231: 982482809
A232: xinhntk | B232: kimxinh3112@gmail.com | C232: 934029964
A233: dungnt095 | B233: tiendung17393@gmail.com | C233: 983704756
A234: kieuntm | B234: nguyendoni1970@gmail.com | C234: 908292529
A235: thaottt017 | B235: thaotran2060@gmail.com | C235: 848968957
A236: khanhnn006 | B236: binbin88bonbon@gmail.com | C236: 913423487
A237: mientt | B237: mien.tt@swpoc.vn | C237: 788825899
A238: phuongltt004 | B238: lethithemphuong@gmail.com | C238: 976574088
A239: phuongpt018 | B239: phuongdenxitrum@gmail.com | C239: 988456778
A240: vytlt | B240: tranletuongvy20102000@gmail.com | C240: 399626165
... A444: giaonk | B444: tongnghia1979@gmail.com | C444: 931155888
A445: hauhq | B445: hauqueho57@gmail.com | C445: 0919 093 157
A446: thiendq002 | B446: leducthien040271@gmail.com | C446: 903776106
...

Sheet DS nhập học k24
A1: STT | B1: mã sinh viên | C1: Mã học viên | D1: Ngày tạo | E1: Địa điểm học | F1: Ngành đào tạo | G1: Đối tượng | H1: Lớp quản lý | I1: Tài khoản | J1: Mật khẩu | K1: Họ | L1: Tên | M1: Ngày sinh | N1: Giới tính | O1: Nơi sinh | P1: Email | Q1: Số điện thoại | R1: Địa chỉ liên hệ | S1: Ghi chú | T1: Địa điểm
A2: 1 | B2: 25C5002D4649 | D2: 45888 | E2: Trường Trung cấp Tin học Kinh tế Sài Gòn | F2: Luật | G2: Trung học phổ thông | H2: 0625.HSG524A | I2: taidt006 | J2: 22122007 | K2: Dương Tiến | L2: Tài | M2: 39438 | N2: Nam | O2: Đồng Nai | P2: ngocquoc200783@gmail.com | Q2: 908109896 | R2: 33 Võ Nguyên Giáp, Tân Bình, Bình Minh, Đồng Nai | T2: 18. Sài Gòn | U2: {=_xludf.XLOOKUP(I2,DSSV!D:D,DSSV!P:P)} -> #NAME?
A3: 2 | B3: 25C5102D4651 | C3: R | D3: 45888 | E3: Trường Trung cấp Tin học Kinh tế Sài Gòn | F3: Luật kinh tế | G3: Trung học phổ thông | H3: 0625.ESG524A | I3: lieuvn | J3: 16102001 | K3: Vỏ Ngọc | L3: Liêu | M3: 37180 | N3: Nữ | O3: Kiên Giang | P3: lieuleuvongoc@gmail.com | Q3: 862449707 | R3: 793/28/1/12C1 Trần Xuân Soạn, phường Tân Hưng, quận 7, TP HCM | T3: 18. Sài Gòn | U3: {=_xludf.XLOOKUP(I3,DSSV!D:D,DSSV!P:P)} -> #NAME?
A4: 3 | B4: 25C7202D4654 | C4: R | D4: 45888 | E4: Trường Trung cấp Tin học Kinh tế Sài Gòn | F4: Ngôn ngữ Trung Quốc | G4: Trung học phổ thông | H4: 0625.OSG524A | I4: lanhn003 | J4: 10061990 | K4: Hồ Nhì | L4: Làn | M4: 33034 | N4: Nữ | O4: Xuân Lộc - Đồng Nai | P4: lauren.lanho@gmail.com | Q4: 357270910 | R4: Khu nhà ở TMDV cao tầng Lê Phong, kp Bình Hòa, p. Lái Thêu, tp. HCM | T4: 18. Sài Gòn | U4: {=_xludf.XLOOKUP(I4,DSSV!D:D,DSSV!P:P)} -> #NAME?
A5: 4 | B5: 25C5102D4652 | C5: R | D5: 45888 | E5: Trường Trung cấp Tin học Kinh tế Sài Gòn | F5: Luật kinh tế | G5: Trung học phổ thông | H5: 0625.ESG524A | I5: kinkn | J5: 30041994 | K5: Kóng Ngọc | L5: Kín | M5: 34454 | N5: Nữ | O5: Bà Rịa Vũng Tàu | P5: ngockin3004@gmail.com | Q5: 933709729 | R5: C7-13, khu DTA, tổ 8, Ấp Vũng Gấm, xã Phước An, Đồng Nai | T5: 18. Sài Gòn | U5: {=_xludf.XLOOKUP(I5,DSSV!D:D,DSSV!P:P)} -> #NAME?
A6: 5 | B6: 25C1002D4655 | C6: R | D6: 45888 | E6: Trường Trung cấp Tin học Kinh tế Sài Gòn | F6: Công nghệ thông tin | G6: Cao đẳng cùng ngành | H6: 0625.CSG224A | I6: chiennv017 | J6: 5022001 | K6: Nguyễn Văn | L6: Chiến | M6: 36927 | N6: Nam | O6: Thanh Hoá | P6: chiennguyen050220@gmail.com | Q6: 867425401 | R6: 1041/62/20 Trần Xuân Soạn, Phường Tân Hưng, TP HCM | T6: 18. Sài Gòn | U6: {=_xludf.XLOOKUP(I6,DSSV!D:D,DSSV!P:P)} -> #NAME?
A7: 6 | B7: 25C5002D4650 | C7: R | D7: 45888 | E7: Trường Trung cấp Tin học Kinh tế Sài Gòn | F7: Luật | G7: Trung học phổ thông | H7: 0625.HSG524A | I7: vutlq | J7: 18092004 | K7: Thái Lê Quang | L7: Vũ | M7: 38248 | N7: Nam | O7: TP HCM | P7: quangvu1892004@gmail.com | Q7: 353391809 | R7: 65/4 Phường Tân Thới Hiệp, TP HCM | T7: 18. Sài Gòn | U7: {=_xludf.XLOOKUP(I7,DSSV!D:D,DSSV!P:P)} -> #NAME?
A8: 7 | B8: 25C5001U4937 | C8: R/M | D8: 45890 | E8: Trường Trung cấp Kinh tế Kỹ thuật Thương mại | F8: Luật | G8: Đại học | H8: 0125.HKTM124A | I8: bachdv004 | J8: 2082001 | K8: Đông Văn | L8: Bách | M8: 37105 | N8: Nam | O8: Hà Nội | P8: bachdongvan28@gmail.com | Q8: 967239338 | R8: Cụm 9, xã Ô Diên, TP Hà Nội | T8: Thương Mại | U8: {=_xludf.XLOOKUP(I8,DSSV!D:D,DSSV!P:P)} -> #NAME?
A9: 8 | B9: 25C7201U4917 | C9: R | D9: 45890 | E9: Trường Trung cấp Kinh tế Kỹ thuật Thương mại | F9: Ngôn ngữ Trung Quốc | G9: Trung học phổ thông | H9: 0125.OKTM524A | I9: quynhntn026 | J9: 26122003 | K9: Nguyễn Thị Ngọc | L9: Quỳnh | M9: 37981 | N9: Nữ | O9: Lào Cai | P9: nguyenngocquynh261203@gmail.com | Q9: 348444962 | R9: 25 Trần Quốc Hoàn, Cầu Giấy, Hà Nội | T9: Thương Mại | U9: {=_xludf.XLOOKUP(I9,DSSV!D:D,DSSV!P:P)} -> #NAME?
A10: 9 | B10: 25C7201U4907 | C10: R | D10: 45890 | E10: Trường Trung cấp Kinh tế Kỹ thuật Thương mại | F10: Ngôn ngữ Trung Quốc | G10: Trung học phổ thông | H10: 0125.OKTM524A | I10: nganntk032 | J10: 21082002 | K10: Nguyễn Thị Kim | L10: Ngân | M10: 37489 | N10: Nữ | O10: Hưng Yên | P10: ngann2182002@gmail.com | Q10: 908901261 | R10: Thôn Thu Cúc, Thụy Hương, Thái Thụy, Thái Bình | T10: Thương Mại | U10: {=_xludf.XLOOKUP(I10,DSSV!D:D,DSSV!P:P)} -> #NAME?
A11: 10 | B11: 25C1001U4932 | C11: R | D11: 45890 | E11: Trường Trung cấp Kinh tế Kỹ thuật Thương mại | F11: Công nghệ thông tin | G11: Trung học phổ thông | H11: 0125.CKTM524A | I11: manhtq006 | J11: 31121999 | K11: Triệu Quang | L11: Mạnh | M11: 36525 | N11: Nam | O11: Ninh Bình | P11: quangmanh31121999@gmail.com | Q11: 857743499 | R11: Tiến Phong 1, Phường Vị Khê, Tỉnh Ninh Bình | T11: Thương Mại | U11: {=_xludf.XLOOKUP(I11,DSSV!D:D,DSSV!P:P)} -> #NAME?
A12: 11 | B12: 25C4201U4935 | C12: R | D12: 45890 | E12: Trường Trung cấp Kinh tế Kỹ thuật Thương mại | F12: Quản trị kinh doanh | G12: Trung học phổ thông | H12: 0125.BKTM524A | I12: tiennv033 | J12: 31102003 | K12: Nguyễn Văn | L12: Tiến | M12: 37925 | N12: Nam | O12: Quảng Ninh | P12: tien312003@gmail.com | Q12: 778395537 | R12: Tổ 70, khu 6A, phường Cửa Ông, tỉnh Quảng Ninh | T12: Thương Mại | U12: {=_xludf.XLOOKUP(I12,DSSV!D:D,DSSV!P:P)} -> #NAME?
A13: 12 | B13: 25C7201U4906 | C13: R | D13: 45890 | E13: Trường Trung cấp Kinh tế Kỹ thuật Thương mại | F13: Ngôn ngữ Trung Quốc | G13: Trung học phổ thông | H13: 0125.OKTM524A | I13: phuongph007 | J13: 6122006 | K13: Phạm Hà | L13: Phương | M13: 39057 | N13: Nữ | O13: Hải Dương | P13: phuongpham06122006@gmail.com | Q13: 963744878 | R13: Số 8 ngõ 1 Ngọc Lâm, phường Ngọc Lâm, Long Biên, Hà Nội | T13: Thương Mại | U13: {=_xludf.XLOOKUP(I13,DSSV!D:D,DSSV!P:P)} -> #NAME?
A14: 13 | B14: 25C7101U4927 | C14: R/M | D14: 45890 | E14: Trường Trung cấp Kinh tế Kỹ thuật Thương mại | F14: Ngôn ngữ Anh | G14: Cao đẳng khác ngành | H14: 0125.FKTM324A | I14: hoangpn007 | J14: 19041994 | K14: Phan Nguyễn | L14: Hoàng | M14: 34443 | N14: Nam | O14: Hà Tĩnh | P14: hoangphanht94@gmail.com | Q14: 975589558 | R14: Tổ 14, P. Yên Nghĩa, Hà Nội | T14: Thương Mại | U14: {=_xludf.XLOOKUP(I14,DSSV!D:D,DSSV!P:P)} -> #NAME?
... A25: 24 | B25: 25C7101U4929 | C25: R | D25: 45890 | E25: Trường Trung cấp Kinh tế Kỹ thuật Thương mại | F25: Ngôn ngữ Anh | G25: Trung học phổ thông | H25: 0125.FKTM524A | I25: thuvm004 | J25: 15112005 | K25: Vũ Minh | L25: Thư | M25: 38671 | N25: Nữ | O25: TP. Hải Phòng | P25: vuthu8577@gmail.com | Q25: 366875969 | R25: Thôn 8, Hùng Thắng, Tiên Lãng, Hải Phòng | T25: Thương Mại | U25: {=_xludf.XLOOKUP(I25,DSSV!D:D,DSSV!P:P)} -> #NAME?
A26: 25 | B26: 25C7201U4922 | D26: 45890 | E26: Trường Trung cấp Kinh tế Kỹ thuật Thương mại | F26: Ngôn ngữ Trung Quốc | G26: Trung học phổ thông | H26: 0125.OKTM524A | I26: longnx004 | J26: 18012000 | K26: Nguyễn Xuân | L26: Long | M26: 36543 | N26: Nam | O26: Hà Nội | P26: xuanlong.wrk@gmail.com | Q26: 876602058 | R26: TDP 14, Phường Phú Diễn, TP. Hà Nội | T26: Thương Mại | U26: {=_xludf.XLOOKUP(I26,DSSV!D:D,DSSV!P:P)} -> #NAME?
A27: 26 | B27: 25C4201U4936 | C27: R/M | D27: 45890 | E27: Trường Trung cấp Kinh tế Kỹ thuật Thương mại | F27: Quản trị kinh doanh | G27: Cao đẳng khác ngành | H27: 0125.BKTM324A | I27: tienpq002 | J27: 25101999 | K27: Phạm Quang | L27: Tiến | M27: 36458 | N27: Nam | O27: Ninh Bình | P27: tientanchau1999@gmail.com | Q27: 339851753 | R27: Xóm 10, Xuân Hưng, Ninh Bình | T27: Thương Mại | U27: {=_xludf.XLOOKUP(I27,DSSV!D:D,DSSV!P:P)} -> #NAME?
A28: 27 | B28: 25C7101U4930 | C28: R | D28: 45890 | E28: Trường Trung cấp Kinh tế Kỹ thuật Thương mại | F28: Ngôn ngữ Anh | G28: Cao đẳng khác ngành | H28: 0125.FKTM324A | I28: hoaktp | J28: 21022004 | K28: Kiều Thị Phương | L28: Hoa | M28: 38038 | N28: Nữ | O28: TP. Hà Nội | P28: hkieu4346@gmail.com | Q28: 385079204 | R28: Thôn Phú Lễ, xã Hạ Bằng, TP. Hà Nội | T28: Thương Mại | U28: {=_xludf.XLOOKUP(I28,DSSV!D:D,DSSV!P:P)} -> #NAME?
A29: 28 | B29: 25C7201U4919 | C29: R | D29: 45890 | E29: Trường Trung cấp Kinh tế Kỹ thuật Thương mại | F29: Ngôn ngữ Trung Quốc | G29: Trung học phổ thông | H29: 0125.OKTM524A | I29: kieucth | J29: 10012006 | K29: Cao Thị Hoàng | L29: Kiều | M29: 38727 | N29: Nữ | O29: Lâm Đồng | P29: ckieu6878@gmail.com | Q29: 865079206 | R29: Xã Hiền Quan, tỉnh Phú Thọ | T29: Thương Mại | U29: {=_xludf.XLOOKUP(I29,DSSV!D:D,DSSV!P:P)} -> #NAME?
A30: 29 | B30: 25C1001U4931 | C30: R/M | D30: 45890 | E30: Trường Trung cấp Kinh tế Kỹ thuật Thương mại | F30: Công nghệ thông tin | G30: Trung học phổ thông | H30: 0125.CKTM524A | I30: dattx | J30: 10032001 | K30: Trần Xuân | L30: Đạt | M30: 36960 | N30: Nam | O30: Phú Thọ | P30: tranxuandat.dev@gmail.com | Q30: 357339938 | R30: Khu Hùng Thao, Hà Thạch, Thị xã Phú Thọ, Phú Thọ | T30: Thương Mại | U30: {=_xludf.XLOOKUP(I30,DSSV!D:D,DSSV!P:P)} -> #NAME?
A31: 30 | B31: 25C7202D4969 | C31: R/M | D31: 45890 | E31: Trường Trung cấp Tin học Kinh tế Sài Gòn | F31: Ngôn ngữ Trung Quốc | G31: Cao đẳng khác ngành | H31: 0625.OSG324A | I31: mynt022 | J31: 18071999 | K31: Nguyễn Trà | L31: My | M31: 36359 | N31: Nữ | O31: Đắk Lắk | P31: chameinguyen@gmail.com | Q31: 935574221 | R31: 10B Hai Bà Trưng, phường Tăng Nhơn Phú, TP. HCM | T31: 18. Sài Gòn | U31: {=_xludf.XLOOKUP(I31,DSSV!D:D,DSSV!P:P)} -> #NAME?
A32: 31 | B32: 25C7202D4968 | C32: R | D32: 45890 | E32: Trường Trung cấp Tin học Kinh tế Sài Gòn | F32: Ngôn ngữ Trung Quốc | G32: Trung học phổ thông | H32: 0625.OSG524A | I32: thunta009 | J32: 7042007 | K32: Nguyễn Tường Anh | L32: Thư | M32: 39179 | N32: Nữ | O32: Lâm Đồng | P32: nguyentuonganhthu74@gmail.com | Q32: 335208052 | R32: 38/4 Tô Vĩnh Diện, Phường Cam Ly, Đà Lạt, tỉnh Lâm Đồng | T32: 18. Sài Gòn | U32: {=_xludf.XLOOKUP(I32,DSSV!D:D,DSSV!P:P)} -> #NAME?
A33: 32 | B33: 25C7202D4970 | C33: R/M | D33: 45890 | E33: Trường Trung cấp Tin học Kinh tế Sài Gòn | F33: Ngôn ngữ Trung Quốc | G33: Đại học | H33: 0625.OSG124A | I33: loanlth003 | J33: 10011999 | K33: Lê Trần Hồng | L33: Loan | M33: 36170 | N33: Nữ | O33: Khánh Hoà | P33: yphong23@gmail.com | Q33: 889141423 | R33: 113 Trần Quang Diệu, khu phố 10, p Phan Rang, Tỉnh Khánh Hoà | T33: 18. Sài Gòn | U33: {=_xludf.XLOOKUP(I33,DSSV!D:D,DSSV!P:P)} -> #NAME?
A34: 33 | B34: 25C7201U4920 | C34: R | D34: 45891 | E34: Trường Trung cấp Kinh tế Kỹ thuật Thương mại | F34: Ngôn ngữ Trung Quốc | G34: Trung học phổ thông | H34: 0125.OKTM524A | I34: maibtn003 | J34: 5112001 | K34: Bùi Thị Ngọc | L34: Mai | M34: 37200 | N34: Nữ | O34: Hà Nội | P34: ngocmai01dt@gmail.com | Q34: 973431396 | R34: Thôn Hoành 1, xã Phúc Sơn, Hà Nội | T34: Thương Mại | U34: {=_xludf.XLOOKUP(I34,DSSV!D:D,DSSV!P:P)} -> #NAME?
A35: 34 | B35: 25C7201U4924 | C35: R | D35: 45891 | E35: Trường Trung cấp Kinh tế Kỹ thuật Thương mại | F35: Ngôn ngữ Trung Quốc | G35: Trung học phổ thông | H35: 0125.OKTM524A | I35: ngoclb011 | J35: 10032004 | K35: Lã Bích | L35: Ngọc | M35: 38056 | N35: Nữ | O35: Lạng Sơn | P35: lacoi17032004@gmail.com | Q35: 336832512 | R35: Bản Roọc, Cao Lộc, Lạng Sơn | T35: Thương Mại | U35: {=_xludf.XLOOKUP(I35,DSSV!D:D,DSSV!P:P)} -> #NAME?
A36: 35 | B36: 25C5101U4940 | C36: R/M | D36: 45891 | E36: Trường Trung cấp Kinh tế Kỹ thuật Thương mại | F36: Luật kinh tế | G36: Đại học | H36: 0125.EKTM124A | I36: nhungnnt | J36: 29062001 | K36: Nguyễn Ngọc Trang | L36: Nhung | M36: 37071 | N36: Nữ | O36: Hà Nội | P36: tnhung290601@gmail.com | Q36: 989290601 | R36: Thôn Đồng Mít 1, xã Phúc Sơn, Hà Nội | T36: Thương Mại | U36: {=_xludf.XLOOKUP(I36,DSSV!D:D,DSSV!P:P)} -> #NAME?
A37: 36 | B37: 25C7201U4911 | C37: R | D37: 45891 | E37: Trường Trung cấp Kinh tế Kỹ thuật Thương mại | F37: Ngôn ngữ Trung Quốc | G37: Trung học phổ thông | H37: 0125.OKTM524A | I37: duyenpth005 | J37: 8062000 | K37: Phạm Thị Hồng | L37: Duyến | M37: 36685 | N37: Nữ | O37: Hưng Yên | P37: phamduyen2000bg@gmail.com | Q37: 398286257 | R37: Ngọ Phúc, Xuân Cẩm, Bắc Ninh | T37: Thương Mại | U37: {=_xludf.XLOOKUP(I37,DSSV!D:D,DSSV!P:P)} -> #NAME?
A38: 37 | B38: 25C7201U4921 | C38: R | D38: 45891 | E38: Trường Trung cấp Kinh tế Kỹ thuật Thương mại | F38: Ngôn ngữ Trung Quốc | G38: Trung học phổ thông | H38: 0125.OKTM524A | I38: sennt010 | J38: 29071997 | K38: Nguyễn Thị | L38: Sen | M38: 35640 | N38: Nữ | O38: Bắc Ninh | P38: heomapxinhxinh97@gmail.com | Q38: 376257362 | R38: Mẫu Sơn, Lục Nam, Bắc Ninh | T38: Thương Mại | U38: {=_xludf.XLOOKUP(I38,DSSV!D:D,DSSV!P:P)} -> #NAME?
... A44: 43 | B44: 25C5001U4938 | C44: R/M | D44: 45891 | E44: Trường Trung cấp Kinh tế Kỹ thuật Thương mại | F44: Luật | G44: Đại học | H44: 0125.HKTM124A | I44: hanhbt008 | J44: 23092001 | K44: Bế Thị | L44: Hạnh | M44: 37157 | N44: Nữ | O44: Quảng Ninh | P44: bhanh6924@gmail.com | Q44: 966329535 | R44: Khu phố Quản Vuông, Bình Khê, Quảng Ninh | T44: Thương Mại | U44: {=_xludf.XLOOKUP(I44,DSSV!D:D,DSSV!P:P)} -> #NAME?
A45: 44 | B45: #N/A | C45: R | D45: 45888 | E45: Trường Trung cấp Kinh tế Kỹ thuật Thương mại | F45: Ngôn ngữ Trung Quốc | G45: Trung học phổ thông | H45: 0125.OKTM524A | I45: thuylt062 | J45: 4091992 | K45: Lê Thị | L45: Thủy | M45: 33851 | N45: Nữ | O45: Ninh Bình | P45: thuthuy04091992nb@gmail.com | Q45: 326121692 | R45: Xóm 2 Thượng Hòa, Xã Gia Thanh, Huyện Gia Viễn, Tỉnh Ninh Bình | T45: Thương Mại | U45: {=_xludf.XLOOKUP(I45,DSSV!D:D,DSSV!P:P)} -> #NAME?
A46: 45 | B46: 25C7101U5005 | C46: R/M | D46: 45898 | E46: Trường Trung cấp Kinh tế Kỹ thuật Thương mại | F46: Ngôn ngữ Anh | G46: Đại học | H46: 0125.FKTM124A | I46: thaoqp002 | J46: 5012003 | K46: Quách Phương | L46: Thảo | M46: 37626 | N46: Nữ | O46: Cao Bằng | P46: quachthao5103@gmail.com | Q46: 856570686 | R46: Tổ 7 phường Tân Giang, tỉnh Cao Bằng | T46: Thương Mại | U46: {=_xludf.XLOOKUP(I46,DSSV!D:D,DSSV!P:P)} -> #NAME?
A47: 46 | B47: 25C5001U5008 | C47: R/M | D47: 45898 | E47: Trường Trung cấp Kinh tế Kỹ thuật Thương mại | F47: Luật | G47: Đại học | H47: 0125.HKTM124A | I47: trangntt126 | J47: 19081989 | K47: Nguyễn Thị Thu | L47: Trang | M47: 32739 | N47: Nữ | O47: TP. Hà Nội | P47: trang.tt198@gmail.com | Q47: 975545775 | R47: Căn 2005, HH2 chung cư 90 Nguyễn Tuân, Thanh Xuân, Hà Nội | T47: Thương Mại | U47: {=_xludf.XLOOKUP(I47,DSSV!D:D,DSSV!P:P)} -> #NAME?
A48: 47 | B48: 25C7201U5011 | C48: R | D48: 45898 | E48: Trường Trung cấp Kinh tế Kỹ thuật Thương mại | F48: Ngôn ngữ Trung Quốc | G48: Trung học phổ thông | H48: 0125.OKTM524A | I48: ngattt024 | J48: 27082001 | K48: Triệu Thị | L48: Ngát | M48: 37130 | N48: Nữ | O48: Bắc Ninh | P48: ngat.susu.2001@gmail.com | Q48: 356143020 | R48: Thôn Thống Nhất, xã Lạng Giang, tỉnh Bắc Ninh | T48: Thương Mại | U48: {=_xludf.XLOOKUP(I48,DSSV!D:D,DSSV!P:P)} -> #NAME?
A49: 48 | B49: 25C7201U5009 | C49: R | D49: 45898 | E49: Trường Trung cấp Kinh tế Kỹ thuật Thương mại | F49: Ngôn ngữ Trung Quốc | G49: Trung học phổ thông | H49: 0125.OKTM524A | I49: lylt008 | J49: 24032003 | K49: Lương Thị | L49: Ly | M49: 37704 | N49: Nữ | O49: Cao Bằng | P49: luongthily2403@gmail.com | Q49: 834778154 | R49: TDP Vân Cốc 1, phường Nếnh, tỉnh Bắc Ninh | T49: Thương Mại | U49: {=_xludf.XLOOKUP(I49,DSSV!D:D,DSSV!P:P)} -> #NAME?
A50: 49 | B50: 25C5001U5007 | C50: R/M | D50: 45898 | E50: Trường Trung cấp Kinh tế Kỹ thuật Thương mại | F50: Luật | G50: Đại học | H50: 0125.HKTM124A | I50: nhungtt032 | J50: 20101990 | K50: Trần Thị | L50: Nhung | M50: 33166 | N50: Nữ | O50: TP. Hà Nội | P50: nhungsvhhn@gmail.com | Q50: 961610090 | R50: P2748 CT12A KĐT Kim Văn Kim Lũ, Đại Kim, Hoàng Mai, Hà Nội | T50: Thương Mại | U50: {=_xludf.XLOOKUP(I50,DSSV!D:D,DSSV!P:P)} -> #NAME?
